Workbook

Sheet EXAMPLE FORM
E2: MUST READ: How to use? 1. Only click a checkbox when the topic on the left - is 100% completed 2. Don't check the box if you "just" checked the topic if it was applicable 3. The same topic can be in multiple stages (different levels of maturity) | F2: FR | G2: NL | H2: DE | I2: UK | J2: Adaptation topics (V) | K2: Topics not finalized (X)
F3: TRUE | G3: TRUE | H3: TRUE | I3: TRUE | J3: =(COUNTIF(F:I,TRUE))-COUNTIF(F3:I3,true) -> 23 | K3: =COUNTIF(F:I,FALSE) -> 41
B4: =K59 -> 0.36197917 | F4: =COUNTIF(F:F,TRUE) -> 9 | G4: =COUNTIF(G:G,TRUE) -> 7 | H4: =COUNTIF(H:H,TRUE) -> 6 | I4: =COUNTIF(I:I,TRUE) -> 5
F6: =COUNTIF(F:F,FALSE) -> 8 | G6: =COUNTIF(G:G,FALSE) -> 10 | H6: =COUNTIF(H:H,FALSE) -> 11 | I6: =COUNTIF(I:I,FALSE) -> 12
C8: Maturity | D8: # | E8: Topics | F8: FR | G8: NL | H8: DE | I8: UK | J8: Details | K8: Next steps
E9: If a topic is not relevant for the client - delete the checkbox | F9: Only check a box if the topic is fully integrated | J9: Explain what the issue is if not checked | K9: What would be the next steps to finalize the topic
B10: 1
C11: Keywords | F11: =IFERROR(__xludf.DUMMYFUNCTION("SPARKLINE(COUNTIF(F13:I26,TRUE),{""charttype"",""bar"";""max"",COUNTA(F13:I26);""color1"",""green""})"),"") | K11: =COUNTIF(F13:I26,TRUE)/COUNTA(F13:I26) -> 0.35416667
B13: =COUNTIF(F13:I17,TRUE)/COUNTA(F13:I17) -> 0.45 | C13: Basic | D13: 1 | E13: Low amount of keywords; generic keywords without including searc intent | F13: TRUE | G13: TRUE | H13: TRUE | I13: TRUE | J13: All good
D14: 2 | E14: Account structure (based on Hagakure) | F14: TRUE | G14: TRUE | H14: FALSE | I14: FALSE | J14: No Hagakure in place for DE&UK | K14: Copy strategy of NL+FR to other markets
D15: 3 | E15: Keyword research | F15: TRUE | G15: FALSE | H15: FALSE | I15: FALSE | J15: Only french cope found | K15: Align with SEO and SEA regarding reports
D16: 4 | E16: Standard Namig Convention | F16: TRUE | G16: FALSE | H16: TRUE | I16: FALSE | J16: NL and UK are missing naming convention | K16: Look into a naming convention builder / or tooling which helps for reporting
D17: 5 | E17: Set-up base range of keywords | F17: FALSE | G17: FALSE | H17: FALSE | I17: FALSE | J17: Not in place yet
B18: =COUNTIF(F18:I19,TRUE)/COUNTA(F18:I19) -> 0.5 | C18: Advanced | D18: 6 | E18: Campaign segmentation based on customer journey | F18: FALSE | G18: FALSE | H18: FALSE | I18: FALSE | J18: Customer journey for every country seems different | K18: Write down customer journey for all markets
D19: 7 | E19: Negative keyword list | F19: TRUE | G19: TRUE | H19: TRUE | I19: TRUE | J19: All good
B20: =COUNTIF(F20:I23,TRUE)/COUNTA(F20:I23) -> 0.25 | C20: Expert | D20: 8 | E20: Mcc Account | F20: TRUE | G20: TRUE | H20: TRUE | I20: TRUE | J20: All good
D21: 9 | E21: Expand account to search engines beyond Google Ads | F21: FALSE | G21: FALSE | H21: FALSE | I21: FALSE | J21: Only goole ads in place | K21: First focus by optimizing account before copying towards Bing
D22: 10 | E22: Implement broad match keywords | F22: FALSE | G22: FALSE | H22: FALSE | I22: FALSE | J22: Not in place yet
D23: 11 | E23: Implement DSA ad groups | F23: FALSE | G23: FALSE | H23: FALSE | I23: FALSE | J23: Not in place yet
B24: =COUNTIF(F24:I26,TRUE)/COUNTA(F24:I26) -> 0 | C24: Champion | D24: 12 | E24: Feed based DSA ad groups | J24: Not applicable as no feed related company
D25: 13 | E25: Third party tooling for using feed based keywords | F25: FALSE | G25: FALSE | H25: FALSE | I25: FALSE | J25: No tooling in place for this | K25: Find a tooling (RFP) to optimize campagin setups
D26: 14 | E26: Use business feeds to create large keyword range | J26: Not applicable as no feed related company
B27: 2
C28: Message | F28: =IFERROR(__xludf.DUMMYFUNCTION("SPARKLINE(COUNTIF(F30:I33,TRUE),{""charttype"",""bar"";""max"",COUNTA(F30:I33);""color1"",""green""})"),"") | K28: =COUNTIF(F30:I33,TRUE)/COUNTA(F30:I33) -> 0.375
B30: =COUNTIF(F30:I30,TRUE)/COUNTA(E30:I30) -> 0.8 | C30: Basic | D30: 1 | E30: Ad group tailored ads | F30: TRUE | G30: TRUE | H30: TRUE | I30: TRUE | J30: All good
B31: =COUNTIF(F31:I31,TRUE)/COUNTA(E31:I31) -> 0.4 | C31: Advanced | D31: 2 | E31: RSA reflect steps in customer journey | F31: TRUE | G31: TRUE | H31: FALSE | I31: FALSE | J31: For DE&UK no steps yet | K31: Implement same strategy for all markets
B32: =COUNTIF(F32:I32,TRUE)/COUNTA(E32:I32) -> 0 | C32: Expert | D32: 3 | E32: Customer based RSAs based on broad contextual signals | F32: FALSE | G32: FALSE | H32: FALSE | I32: FALSE | J32: Not in place yet
B33: =COUNTIF(F33:I33,TRUE)/COUNTA(E33:I33) -> 0 | C33: Champion | D33: 4 | E33: Tailored ad text by using contextual signals | F33: FALSE | G33: FALSE | H33: FALSE | I33: FALSE | J33: Not in place yet
B35: SUMMARY (relevance to be adjusted to client needs) | M35: << in the column on the left you can decide if a certain topic is more or less important compared to others - to decide how important it is for the total score of a client Example given: Feed management is not always relevant for a company (B2B). You can give the relevance a score of 0 and it won't be calculated in the total average score Default setting: all topics at 100%
E37: Topic | F37: Topic relevance 0-100% | K37: Total score
C39: 1 | E39: =C11 -> Keywords | F39: 1 | J39: =IFERROR(__xludf.DUMMYFUNCTION("F11"),"") | K39: =K11 -> 0.35416667
C41: 2 | E41: =C28 -> Message | F41: 0.6 | J41: =IFERROR(__xludf.DUMMYFUNCTION("F28"),"") | K41: =K28 -> 0.375
C43: 3
C45: 4
C47: 5
C49: 6
C51: 7
C53: 8
C55: 9
C57: 10
J59: Total average weighted score | K59: =IFERROR(__xludf.DUMMYFUNCTION("AVERAGE.WEIGHTED(K39:K57,F39:F57)"),0.3619791666666667) -> 0.36197917

Sheet (WIP) How to use this document
C3: Internal use: | D3: How to work with digital maturity assesment
C5: Tab | D5: Action | E5: Comment
B6: 1 | C6: General | D6: Always make a copy of this document before working in it
B7: 2 | C7: General | D7: Start with removing tabs you don't use (tip - hide them) | E7: The client shouldn't see the maturity model for other disciplines (easy to "do it themselves)
B8: 3 | C8: Exec Summary | D8: Remove the score in the exec summary view (not the chart) | E8: The reason why - the client sees you offer more then only one discipline (if we only offer 1 discipline)
B9: 4 | C9: Exec Summary | D9: Removing the score can be down in rule 14/15 of the exec summary (score is in white)
B10: 5 | C10: Exec Summary | D10: Flags - change the country name above the flag
B11: 6 | C11: Discipline | D11: Calculation: add new rules below or above a field > double check calculation | E11: If there already 2 rules - add one below the first one (will be automated)
B12: 7 | C12: Discipline | D12: Total score is a weighted sum of all the "chapters" (the ones in green)
B13: 8 | C13: Discipline

Sheet Exec. sum.
B2: Tasks done | E2: Open tasks | Q2: France | R2: Netherlands | T2: Germany | U2: Belgium | W2: United Kingdom | X2: United States | Z2: Italy
Q3: =IFERROR(__xludf.DUMMYFUNCTION("IMAGE(""https:""&IMPORTXML(""https://en.wikipedia.org/wiki/Gallery_of_sovereign_state_flags"",""//img/@src[contains(.,'""&SUBSTITUTE(Q2,"" "",""_"")&""' )]""))"),"") | R3: =IFERROR(__xludf.DUMMYFUNCTION("IMAGE(""https:""&IMPORTXML(""https://en.wikipedia.org/wiki/Gallery_of_sovereign_state_flags"",""//img/@src[contains(.,'""&SUBSTITUTE(R2,"" "",""_"")&""' )]""))"),"") | T3: =IFERROR(__xludf.DUMMYFUNCTION("IMAGE(""https:""&IMPORTXML(""https://en.wikipedia.org/wiki/Gallery_of_sovereign_state_flags"",""//img/@src[contains(.,'""&SUBSTITUTE(T2,"" "",""_"")&""' )]""))"),"") | U3: =IFERROR(__xludf.DUMMYFUNCTION("IMAGE(""https:""&IMPORTXML(""https://en.wikipedia.org/wiki/Gallery_of_sovereign_state_flags"",""//img/@src[contains(.,'""&SUBSTITUTE(U2,"" "",""_"")&""' )]""))"),"") | W3: =IFERROR(__xludf.DUMMYFUNCTION("IMAGE(""https:""&IMPORTXML(""https://en.wikipedia.org/wiki/Gallery_of_sovereign_state_flags"",""//img/@src[contains(.,'""&SUBSTITUTE(W2,"" "",""_"")&""' )]""))"),"") | X3: =IFERROR(__xludf.DUMMYFUNCTION("IMAGE(""https:""&IMPORTXML(""https://en.wikipedia.org/wiki/Gallery_of_sovereign_state_flags"",""//img/@src[contains(.,'""&SUBSTITUTE(X2,"" "",""_"")&""' )]""))"),"") | Z3: =IFERROR(__xludf.DUMMYFUNCTION("IMAGE(""https:""&IMPORTXML(""https://en.wikipedia.org/wiki/Gallery_of_sovereign_state_flags"",""//img/@src[contains(.,'""&SUBSTITUTE(Z2,"" "",""_"")&""' )]""))"),"")
C4: ='SEA - Google Ads'!M3+'SEA - Bing'!M3+META!M3+PINTEREST!M3+SEO!M3+'(WIP) CRO/UX'!M3+'Web Analytics'!M3+'DV360'!M3+'(WIP) LINKEDIN'!M3+'AI for SEO'!N3 -> #REF! | F4: ='SEA - Google Ads'!N3+'SEA - Bing'!N3+META!N3+PINTEREST!N3+SEO!N3+'(WIP) CRO/UX'!N3+'Web Analytics'!N3+'DV360'!N3+'(WIP) LINKEDIN'!N3+'AI for SEO'!N3 -> #REF! | Q4: FR | R4: NL | T4: DE | U4: BE | W4: UK | X4: US | Z4: IT
L5: The amount of tasks completed | Q5: TRUE | R5: TRUE | T5: TRUE | U5: TRUE | W5: TRUE | X5: TRUE | Z5: TRUE
Q6: ='SEA - Google Ads'!F4+'SEA - Bing'!F4+META!F4+PINTEREST!F4+SEO!F4+'(WIP) CRO/UX'!F4+'Web Analytics'!F4+'DV360'!F4+'(WIP) LINKEDIN'!F4 -> #REF! | R6: ='SEA - Google Ads'!G4+'SEA - Bing'!G4+META!G4+PINTEREST!G4+SEO!G4+'(WIP) CRO/UX'!G4+'Web Analytics'!G4+'DV360'!G4+'(WIP) LINKEDIN'!G4 -> #REF! | T6: ='SEA - Google Ads'!H4+'SEA - Bing'!H4+META!H4+PINTEREST!H4+SEO!H4+'(WIP) CRO/UX'!H4+'Web Analytics'!H4+'DV360'!H4+'(WIP) LINKEDIN'!H4 -> #REF! | U6: ='SEA - Google Ads'!I4+'SEA - Bing'!I4+META!I4+PINTEREST!I4+SEO!I4+'(WIP) CRO/UX'!I4+'Web Analytics'!I4+'DV360'!I4+'(WIP) LINKEDIN'!I4 -> #REF! | W6: ='SEA - Google Ads'!J4+'SEA - Bing'!J4+META!J4+PINTEREST!J4+SEO!J4+'(WIP) CRO/UX'!J4+'Web Analytics'!J4+'DV360'!J4+'(WIP) LINKEDIN'!J4 -> #REF! | X6: ='SEA - Google Ads'!K4+'SEA - Bing'!K4+META!K4+PINTEREST!K4+SEO!K4+'(WIP) CRO/UX'!K4+'Web Analytics'!K4+'DV360'!K4+'(WIP) LINKEDIN'!K4 -> #REF! | Z6: ='SEA - Google Ads'!L4+'SEA - Bing'!L4+META!L4+PINTEREST!L4+SEO!L4+'(WIP) CRO/UX'!L4+'Web Analytics'!L4+'DV360'!L4+'(WIP) LINKEDIN'!L4 -> #REF!
L7: The amount of open tasks | Q7: FALSE | R7: FALSE | T7: FALSE | U7: FALSE | W7: FALSE | X7: FALSE | Z7: FALSE
B10: Overall maturity level | E10: Paid Search | H10: Paid Search | K10: LinkedIn | N10: DV360 | Q10: Meta | T10: Pinterest | W10: SEO | Z10: Web Analytics | AC10: CRO / UX | AF10: AI
B12: =IF(C14<30,"Basic",IF(C14<60,"Advanced",IF(C14<84,"Expert",IF(C14>85,"Champion")))) -> Basic | E12: =IF(F14<30,"Basic",IF(F14<60,"Advanced",IF(F14<84,"Expert",IF(F14>85,"Champion")))) -> Basic | H12: =IF(I14<30,"Basic",IF(I14<60,"Advanced",IF(I14<84,"Expert",IF(I14>85,"Champion")))) -> Basic | K12: =IF(L14<30,"Basic",IF(L14<60,"Advanced",IF(L14<84,"Expert",IF(L14>85,"Champion")))) -> Basic | N12: =IF(O14<30,"Basic",IF(O14<60,"Advanced",IF(O14<84,"Expert",IF(O14>85,"Champion")))) -> Basic | Q12: =IF(R14<30,"Basic",IF(R14<60,"Advanced",IF(R14<84,"Expert",IF(R14>85,"Champion")))) -> Basic | T12: =IF(U14<30,"Basic",IF(U14<60,"Advanced",IF(U14<84,"Expert",IF(U14>85,"Champion")))) -> Basic | W12: =IF(X14<30,"Basic",IF(X14<60,"Advanced",IF(X14<84,"Expert",IF(X14>85,"Champion")))) -> Basic | Z12: =IF(AA14<30,"Basic",IF(AA14<60,"Advanced",IF(AA14<84,"Expert",IF(AA14>85,"Champion")))) -> Basic | AC12: =IF(AD14<30,"Basic",IF(AD14<60,"Advanced",IF(AD14<84,"Expert",IF(AD14>85,"Champion")))) -> Basic | AF12: =IF(AH14<30,"Basic",IF(AH14<60,"Advanced",IF(AH14<84,"Expert",IF(AH14>85,"Champion")))) -> Basic
B14: =SUM(E14+H14+Q14+W14+Z14+AC14+K14+N14+T14+AF14)/10 -> 0 | C14: =B14*100 -> 0 | E14: ='SEA - Google Ads'!B4 -> 0 | F14: =E14*100 -> 0 | H14: ='SEA - Bing'!B4 -> 0 | I14: =H14*100 -> 0 | K14: ='(WIP) LINKEDIN'!B4 -> 0 | L14: =K14*100 -> 0 | N14: ='DV360'!B4 -> 0 | O14: =N14*100 -> 0 | Q14: =META!B4 -> 0 | R14: =Q14*100 -> 0 | T14: =PINTEREST!B4 -> 0 | U14: =T14*100 -> 0 | W14: =SEO!B4 -> 0 | X14: =W14*100 -> 0 | Z14: ='Web Analytics'!B4 -> 0 | AA14: =Z14*100 -> 0 | AC14: =CROUX!B4 -> 0 | AD14: =AC14*100 -> 0 | AF14: ='AI for SEO'!B4 -> 0 | AG14: =AF14*100 -> 0 | AH14: =AF14*100 -> 0
B25: Q1 | H25: Q2 | N25: Q3 | T25: Q4
C26: Action | F26: Status | H26: Action | L26: Status | N26: Action | R26: Status | T26: Action | X26: Status
B27: Prio 1
B28: Prio 2
B29: Prio 3
B30: Prio 4
B31: Prio 5
B32: Prio 6

Sheet SEA - Google Ads
E2: MUST READ: How to use? 1. Only click a checkbox when the topic on the left - is 100% completed 2. Don't check the box if you "just" checked the topic if it was applicable 3. The same topic can be in multiple stages (different levels of maturity) | F2: FR | G2: NL | H2: DE | I2: BE | J2: UK | K2: US | L2: IT | M2: Adaptation topics (V) | N2: Topics not finalized (X) | P2: Last updated at 15/11/2023 by Sjoerd Lops & Valeria Briganti
F3: TRUE | G3: TRUE | H3: TRUE | I3: TRUE | J3: TRUE | K3: TRUE | L3: TRUE | M3: =(COUNTIF(F:L,TRUE))-COUNTIF(F3:L3,true) -> 0 | N3: =COUNTIF(F:L,FALSE) -> 623
B4: =N154 -> 0 | F4: =COUNTIF(F:F,TRUE)-1 -> 0 | G4: =COUNTIF(G:G,TRUE)-1 -> 0 | H4: =COUNTIF(H:H,TRUE)-1 -> 0 | I4: =COUNTIF(I:I,TRUE)-1 -> 0 | J4: =COUNTIF(J:J,TRUE)-1 -> 0 | K4: =COUNTIF(K:K,TRUE)-1 -> 0 | L4: =COUNTIF(L:L,TRUE)-1 -> 0
F6: =COUNTIF(F:F,FALSE) -> 89 | G6: =COUNTIF(G:G,FALSE) -> 89 | H6: =COUNTIF(H:H,FALSE) -> 89 | I6: =COUNTIF(I:I,FALSE) -> 89 | J6: =COUNTIF(J:J,FALSE) -> 89 | K6: =COUNTIF(K:K,FALSE) -> 89 | L6: =COUNTIF(L:L,FALSE) -> 89
C8: Maturity | D8: # | E8: Topics | F8: FR | G8: NL | H8: DE | I8: ES | J8: UK | K8: US | L8: IT | M8: Details | N8: Next steps
E9: If a topic is not relevant for the client - delete the checkbox | F9: Only check a box if the topic is fully integrated | M9: Explain what the issue is if not checked | N9: What would be the next steps to finalize the topic
B10: 1
C11: Keywords | F11: =IFERROR(__xludf.DUMMYFUNCTION("SPARKLINE(COUNTIF(F13:L26,TRUE),{""charttype"",""bar"";""max"",COUNTA(F13:L26);""color1"",""green""})"),"") | N11: =COUNTIF(F13:L26,TRUE)/COUNTA(F13:L26) -> 0 | P11: Commentbox for feedback
B13: =COUNTIF(F13:L17,TRUE)/COUNTA(F13:L17) -> 0 | C13: Basic | D13: 1 | E13: Low amount of keywords; generic keywords without including searc intent | F13: FALSE | G13: FALSE | H13: FALSE | I13: FALSE | J13: FALSE | K13: FALSE | L13: FALSE
D14: 2 | E14: Account structure (based on Hagakure) | F14: FALSE | G14: FALSE | H14: FALSE | I14: FALSE | J14: FALSE | K14: FALSE | L14: FALSE
D15: 3 | E15: Keyword research | F15: FALSE | G15: FALSE | H15: FALSE | I15: FALSE | J15: FALSE | K15: FALSE | L15: FALSE
D16: 4 | E16: Standard Namig Convention | F16: FALSE | G16: FALSE | H16: FALSE | I16: FALSE | J16: FALSE | K16: FALSE | L16: FALSE
D17: 5 | E17: Set-up base range of keywords | F17: FALSE | G17: FALSE | H17: FALSE | I17: FALSE | J17: FALSE | K17: FALSE | L17: FALSE
B18: =COUNTIF(F18:L19,TRUE)/COUNTA(F18:L19) -> 0 | C18: Advanced | D18: 6 | E18: Campaign segmentation based on customer journey | F18: FALSE | G18: FALSE | H18: FALSE | I18: FALSE | J18: FALSE | K18: FALSE | L18: FALSE
D19: 7 | E19: Negative keyword list | F19: FALSE | G19: FALSE | H19: FALSE | I19: FALSE | J19: FALSE | K19: FALSE | L19: FALSE
B20: =COUNTIF(F20:L23,TRUE)/COUNTA(F20:L23) -> 0 | C20: Expert | D20: 8 | E20: Mcc Account | F20: FALSE | G20: FALSE | H20: FALSE | I20: FALSE | J20: FALSE | K20: FALSE | L20: FALSE
D21: 9 | E21: Expand account to search engines beyond Google Ads | F21: FALSE | G21: FALSE | H21: FALSE | I21: FALSE | J21: FALSE | K21: FALSE | L21: FALSE
D22: 10 | E22: Implement broad match keywords | F22: FALSE | G22: FALSE | H22: FALSE | I22: FALSE | J22: FALSE | K22: FALSE | L22: FALSE
D23: 11 | E23: Implement DSA ad groups | F23: FALSE | G23: FALSE | H23: FALSE | I23: FALSE | J23: FALSE | K23: FALSE | L23: FALSE
B24: =COUNTIF(F24:L26,TRUE)/COUNTA(F24:L26) -> 0 | C24: Champion | D24: 12 | E24: Feed based DSA ad groups | F24: FALSE | G24: FALSE | H24: FALSE | I24: FALSE | J24: FALSE | K24: FALSE | L24: FALSE
D25: 13 | E25: Third party tooling for using feed based keywords | F25: FALSE | G25: FALSE | H25: FALSE | I25: FALSE | J25: FALSE | K25: FALSE | L25: FALSE
D26: 14 | E26: Use business feeds to create large keyword range | F26: FALSE | G26: FALSE | H26: FALSE | I26: FALSE | J26: FALSE | K26: FALSE | L26: FALSE
B27: 2
C28: Audiences / targeting | F28: =IFERROR(__xludf.DUMMYFUNCTION("SPARKLINE(COUNTIF(F30:L40,TRUE),{""charttype"",""bar"";""max"",COUNTA(F30:L40);""color1"",""green""})"),"") | N28: =COUNTIF(F30:L40,TRUE)/COUNTA(F30:L40) -> 0
B30: =COUNTIF(F30:L30,TRUE)/COUNTA(E30:L30) -> 0 | C30: Basic | D30: 1 | E30: Basic demographics and audiences | F30: FALSE | G30: FALSE | H30: FALSE | I30: FALSE | J30: FALSE | K30: FALSE | L30: FALSE
B31: =COUNTIF(F31:L35,TRUE)/COUNTA(E31:L35) -> 0 | C31: Advanced | D31: 2 | E31: Location targeting | F31: FALSE | G31: FALSE | H31: FALSE | I31: FALSE | J31: FALSE | K31: FALSE | L31: FALSE
D32: 3 | E32: Remarketing lists | F32: FALSE | G32: FALSE | H32: FALSE | I32: FALSE | J32: FALSE | K32: FALSE | L32: FALSE
D33: 4 | E33: Import Google Analytics remarketing audiences | F33: FALSE | G33: FALSE | H33: FALSE | I33: FALSE | J33: FALSE | K33: FALSE | L33: FALSE
D34: 5 | E34: Import Google Analyics audiences based on purchase behaviour / category interest | F34: FALSE | G34: FALSE | H34: FALSE | I34: FALSE | J34: FALSE | K34: FALSE | L34: FALSE
D35: 6 | E35: Import Google Analyics audiences based on page visits | F35: FALSE | G35: FALSE | H35: FALSE | I35: FALSE | J35: FALSE | K35: FALSE | L35: FALSE
B36: =COUNTIF(F36:L38,TRUE)/COUNTA(F36:L38) -> 0 | C36: Expert | D36: 7 | E36: Import CRM lists | F36: FALSE | G36: FALSE | H36: FALSE | I36: FALSE | J36: FALSE | K36: FALSE | L36: FALSE
D37: 8 | E37: Import Google Analyics predictive audiences | F37: FALSE | G37: FALSE | H37: FALSE | I37: FALSE | J37: FALSE | K37: FALSE | L37: FALSE
D38: 9 | E38: Incorporate all audiences above in the campaign settings | F38: FALSE | G38: FALSE | H38: FALSE | I38: FALSE | J38: FALSE | K38: FALSE | L38: FALSE
B39: =COUNTIF(F39:L40,TRUE)/COUNTA(E39:L40) -> 0 | C39: Champion | D39: 10 | E39: Use Instant BQML - Purchase, Product or Churn propensity | F39: FALSE | G39: FALSE | H39: FALSE | I39: FALSE | J39: FALSE | K39: FALSE | L39: FALSE
D40: 11 | E40: Real time CRM lists integration | F40: FALSE | G40: FALSE | H40: FALSE | I40: FALSE | J40: FALSE | K40: FALSE | L40: FALSE
B41: 3
C42: Conversion & KPI | F42: =IFERROR(__xludf.DUMMYFUNCTION("SPARKLINE(COUNTIF(F44:L55,TRUE),{""charttype"",""bar"";""max"",COUNTA(F44:L55);""color1"",""green""})"),"") | N42: =COUNTIF(F44:L55,TRUE)/COUNTA(F44:L55) -> 0
B44: =COUNTIF(F44:L46,TRUE)/COUNTA(F44:L46) -> 0 | C44: Basic | D44: 1 | E44: Conversion set-up | F44: FALSE | G44: FALSE | H44: FALSE | I44: FALSE | J44: FALSE | K44: FALSE | L44: FALSE
D45: 2 | E45: Conversion tags are implemented in GTM | F45: FALSE | G45: FALSE | H45: FALSE | I45: FALSE | J45: FALSE | K45: FALSE | L45: FALSE
D46: 3 | E46: Focus on increasing amount of conversions | F46: FALSE | G46: FALSE | H46: FALSE | I46: FALSE | J46: FALSE | K46: FALSE | L46: FALSE
B47: =COUNTIF(F47:L49,TRUE)/COUNTA(F47:L49) -> 0 | C47: Advanced | D47: 4 | E47: Conversion data (ensure conversion data) | F47: FALSE | G47: FALSE | H47: FALSE | I47: FALSE | J47: FALSE | K47: FALSE | L47: FALSE
D48: 5 | E48: Enhanced Conversions For lead generation Implemented | F48: FALSE | G48: FALSE | H48: FALSE | I48: FALSE | J48: FALSE | K48: FALSE | L48: FALSE
D49: 6 | E49: KPI based strategy (ROAS or CPA) | F49: FALSE | G49: FALSE | H49: FALSE | I49: FALSE | J49: FALSE | K49: FALSE | L49: FALSE
B50: =COUNTIF(F50:L51,TRUE)/COUNTA(F50:L51) -> 0 | C50: Expert | D50: 7 | E50: Segment your targets (based on contribution value) | F50: FALSE | G50: FALSE | H50: FALSE | I50: FALSE | J50: FALSE | K50: FALSE | L50: FALSE
D51: 8 | E51: Focus on growing revenue/ conversions against tROAS/tCPA | F51: FALSE | G51: FALSE | H51: FALSE | I51: FALSE | J51: FALSE | K51: FALSE | L51: FALSE
D52: 9 | E52: Implement third party tracking tool (cross-marketing channel reporting) | F52: FALSE | G52: FALSE | H52: FALSE | I52: FALSE | J52: FALSE | K52: FALSE | L52: FALSE
B53: =COUNTIF(F53:L55,TRUE)/COUNTA(F53:L55) -> 0 | C53: Champion | D53: 10 | E53: Integrate business level KPI data into Google Ads (margin) | F53: FALSE | G53: FALSE | H53: FALSE | I53: FALSE | J53: FALSE | K53: FALSE | L53: FALSE
D54: 11 | E54: Import cancellation and returns for a precise final ROAS | F54: FALSE | G54: FALSE | H54: FALSE | I54: FALSE | J54: FALSE | K54: FALSE | L54: FALSE
D55: 12 | E55: Steer on POAS, incremental ROAS/CPA | F55: FALSE | G55: FALSE | H55: FALSE | I55: FALSE | J55: FALSE | K55: FALSE | L55: FALSE
B56: 4
C57: Attribution | F57: =IFERROR(__xludf.DUMMYFUNCTION("SPARKLINE(COUNTIF(F59:L63,TRUE),{""charttype"",""bar"";""max"",COUNTA(F59:L63);""color1"",""green""})"),"") | N57: =COUNTIF(F59:L63,TRUE)/COUNTA(F59:L63) -> 0
B59: =COUNTIF(F59:L59,TRUE)/COUNTA(E59:L59) -> 0 | C59: Basic | D59: 1 | E59: Conversion settings are set to the right attribtuion model | F59: FALSE | G59: FALSE | H59: FALSE | I59: FALSE | J59: FALSE | K59: FALSE | L59: FALSE
B60: =COUNTIF(F60:L60,TRUE)/COUNTA(E60:L60) -> 0 | C60: Advanced | D60: 2 | E60: Conversion settings are set to DDA model | F60: FALSE | G60: FALSE | H60: FALSE | I60: FALSE | J60: FALSE | K60: FALSE | L60: FALSE
B61: =COUNTIF(F61:L61,TRUE)/COUNTA(E61:L61) -> 0 | C61: Expert | D61: 3 | E61: Import business data (scripting/ API). E.g.: returnrates, CLV, order frequency | F61: FALSE | G61: FALSE | H61: FALSE | I61: FALSE | J61: FALSE | K61: FALSE | L61: FALSE
B62: =COUNTIF(F62:L63,TRUE)/COUNTA(F62:L63) -> 0 | C62: Champion | D62: 4 | E62: Setup deduplicated conversion tracking | F62: FALSE | G62: FALSE | H62: FALSE | I62: FALSE | J62: FALSE | K62: FALSE | L62: FALSE
D63: 5 | E63: Setup conversion framework based on micro and macro conversions | F63: FALSE | G63: FALSE | H63: FALSE | I63: FALSE | J63: FALSE | K63: FALSE | L63: FALSE
B64: 5
C65: Bid Management | F65: =IFERROR(__xludf.DUMMYFUNCTION("SPARKLINE(COUNTIF(F67:L70,TRUE),{""charttype"",""bar"";""max"",COUNTA(F67:L70);""color1"",""green""})"),"") | N65: =COUNTIF(F67:L70,TRUE)/COUNTA(F67:L70) -> 0
B67: =COUNTIF(F67:L67,TRUE)/COUNTA(E67:L67) -> 0 | C67: Basic | D67: 1 | E67: Simple automated bid strategies (e.g.: SIS 90-95) | F67: FALSE | G67: FALSE | H67: FALSE | I67: FALSE | J67: FALSE | K67: FALSE | L67: FALSE
B68: =COUNTIF(F68:L68,TRUE)/COUNTA(E68:L68) -> 0 | C68: Advanced | D68: 2 | E68: Import Google Analytics remarketing audiences based on non convertors | F68: FALSE | G68: FALSE | H68: FALSE | I68: FALSE | J68: FALSE | K68: FALSE | L68: FALSE
B69: =COUNTIF(F69:L69,TRUE)/COUNTA(E69:L69) -> 0 | C69: Expert | D69: 3 | E69: Segment bid strategies based on performance | F69: FALSE | G69: FALSE | H69: FALSE | I69: FALSE | J69: FALSE | K69: FALSE | L69: FALSE
B70: =COUNTIF(F70:L70,TRUE)/COUNTA(E70:L70) -> 0 | C70: Champion | D70: 4 | E70: Smart bidding with VBB and othe applicable data enrichments | F70: FALSE | G70: FALSE | H70: FALSE | I70: FALSE | J70: FALSE | K70: FALSE | L70: FALSE
B71: 6
C72: Extensions | F72: =IFERROR(__xludf.DUMMYFUNCTION("SPARKLINE(COUNTIF(F74:L80,TRUE),{""charttype"",""bar"";""max"",COUNTA(F74:L80);""color1"",""green""})"),"") | N72: =COUNTIF(F74:L80,TRUE)/COUNTA(F74:L80) -> 0
B74: =COUNTIF(F74:L75,TRUE)/COUNTA(F74:L75) -> 0 | C74: Basic | D74: 1 | E74: Campaign level ad extensions | F74: FALSE | G74: FALSE | H74: FALSE | I74: FALSE | J74: FALSE | K74: FALSE | L74: FALSE
D75: 2 | E75: Account level ad extensions | F75: FALSE | G75: FALSE | H75: FALSE | I75: FALSE | J75: FALSE | K75: FALSE | L75: FALSE
B76: =COUNTIF(F76:L78,TRUE)/COUNTA(F76:L78) -> 0 | C76: Advanced | D76: 3 | E76: Expand use of extensions | F76: FALSE | G76: FALSE | H76: FALSE | I76: FALSE | J76: FALSE | K76: FALSE | L76: FALSE
D77: 4 | E77: Campaing level ad extensions (4) | F77: FALSE | G77: FALSE | H77: FALSE | I77: FALSE | J77: FALSE | K77: FALSE | L77: FALSE
D78: 5 | E78: Account level ad extensions (4) | F78: FALSE | G78: FALSE | H78: FALSE | I78: FALSE | J78: FALSE | K78: FALSE | L78: FALSE
B79: =COUNTIF(F79:L79,TRUE)/COUNTA(E79:L79) -> 0 | C79: Expert | D79: 6 | E79: Tailor campaign level ad extensions to needs | F79: FALSE | G79: FALSE | H79: FALSE | I79: FALSE | J79: FALSE | K79: FALSE | L79: FALSE
B80: =COUNTIF(F80:L80,TRUE)/COUNTA(E80:L80) -> 0 | C80: Champion | D80: 7 | E80: Tailor adgroup level ad extensions to needs for individual ad groups | F80: FALSE | G80: FALSE | H80: FALSE | I80: FALSE | J80: FALSE | K80: FALSE | L80: FALSE
B81: 7
C82: Message | F82: =IFERROR(__xludf.DUMMYFUNCTION("SPARKLINE(COUNTIF(F84:L87,TRUE),{""charttype"",""bar"";""max"",COUNTA(F84:L87);""color1"",""green""})"),"") | N82: =COUNTIF(F84:L87,TRUE)/COUNTA(F84:L87) -> 0
B84: =COUNTIF(F84:L84,TRUE)/COUNTA(E84:L84) -> 0 | C84: Basic | D84: 1 | E84: Ad group tailored ads | F84: FALSE | G84: FALSE | H84: FALSE | I84: FALSE | J84: FALSE | K84: FALSE | L84: FALSE
B85: =COUNTIF(F85:L85,TRUE)/COUNTA(E85:L85) -> 0 | C85: Advanced | D85: 2 | E85: RSA reflect steps in customer journey | F85: FALSE | G85: FALSE | H85: FALSE | I85: FALSE | J85: FALSE | K85: FALSE | L85: FALSE
B86: =COUNTIF(F86:L86,TRUE)/COUNTA(E86:L86) -> 0 | C86: Expert | D86: 3 | E86: Customer based RSAs based on broad contextual signals | F86: FALSE | G86: FALSE | H86: FALSE | I86: FALSE | J86: FALSE | K86: FALSE | L86: FALSE
B87: =COUNTIF(F87:L87,TRUE)/COUNTA(E87:L87) -> 0 | C87: Champion | D87: 4 | E87: Tailored ad text by using contextual signals | F87: FALSE | G87: FALSE | H87: FALSE | I87: FALSE | J87: FALSE | K87: FALSE | L87: FALSE
B88: 8
C89: Automation | F89: =IFERROR(__xludf.DUMMYFUNCTION("SPARKLINE(COUNTIF(F91:L100,TRUE),{""charttype"",""bar"";""max"",COUNTA(F91:L100);""color1"",""green""})"),"") | N89: =COUNTIF(F91:L100,TRUE)/COUNTA(F91:L100) -> 0
B91: =COUNTIF(F91:L93,TRUE)/COUNTA(F91:L93) -> 0 | C91: Basic | D91: 1 | E91: Set-up labeling tools | F91: FALSE | G91: FALSE | H91: FALSE | I91: FALSE | J91: FALSE | K91: FALSE | L91: FALSE
D92: 2 | E92: Set-up enable/pause rules | F92: FALSE | G92: FALSE | H92: FALSE | I92: FALSE | J92: FALSE | K92: FALSE | L92: FALSE
D93: 3 | E93: Set-up alerts for major drops | F93: FALSE | G93: FALSE | H93: FALSE | I93: FALSE | J93: FALSE | K93: FALSE | L93: FALSE
B94: =COUNTIF(F94:L95,TRUE)/COUNTA(F94:L95) -> 0 | C94: Advanced | D94: 4 | E94: Leverage 3rd party tooling for account hygience (aka running audits) | F94: FALSE | G94: FALSE | H94: FALSE | I94: FALSE | J94: FALSE | K94: FALSE | L94: FALSE
D95: 5 | E95: Set-up automated reporting | F95: FALSE | G95: FALSE | H95: FALSE | I95: FALSE | J95: FALSE | K95: FALSE | L95: FALSE
B96: =COUNTIF(F96:L97,TRUE)/COUNTA(F96:L97) -> 0 | C96: Expert | D96: 6 | E96: Cross platform or cross-account management tools | F96: FALSE | G96: FALSE | H96: FALSE | I96: FALSE | J96: FALSE | K96: FALSE | L96: FALSE
D97: 7 | E97: Tooling that helps delivering proactive optimization opportunities | F97: FALSE | G97: FALSE | H97: FALSE | I97: FALSE | J97: FALSE | K97: FALSE | L97: FALSE
B98: =COUNTIF(F98:L100,TRUE)/COUNTA(F98:L100) -> 0 | C98: Champion | D98: 8 | E98: Value based bidding (e.g.: Optimyzer) | F98: FALSE | G98: FALSE | H98: FALSE | I98: FALSE | J98: FALSE | K98: FALSE | L98: FALSE
D99: 9 | E99: Automated account reviews (e.g.: Wordstream) | F99: FALSE | G99: FALSE | H99: FALSE | I99: FALSE | J99: FALSE | K99: FALSE | L99: FALSE
D100: 10 | E100: Scalable keywords (e.g.: SpyFu) | F100: FALSE | G100: FALSE | H100: FALSE | I100: FALSE | J100: FALSE | K100: FALSE | L100: FALSE
B101: 9
C102: Feed Quality and GMC | F102: =IFERROR(__xludf.DUMMYFUNCTION("SPARKLINE(COUNTIF(F104:L114,TRUE),{""charttype"",""bar"";""max"",COUNTA(F104:L114);""color1"",""green""})"),"") | N102: =COUNTIF(F104:L114,TRUE)/COUNTA(F104:L114) -> 0
B104: =COUNTIF(F104:L108,TRUE)/COUNTA(F104:L108) -> 0 | C104: Basic | D104: 1 | E104: Provide high-quality data: titles, descriptions and specs | F104: FALSE | G104: FALSE | H104: FALSE | I104: FALSE | J104: FALSE | K104: FALSE | L104: FALSE
D105: 2 | E105: Provide high-quality data: image quality | F105: FALSE | G105: FALSE | H105: FALSE | I105: FALSE | J105: FALSE | K105: FALSE | L105: FALSE
D106: 3 | E106: Provide up-to-date data | F106: FALSE | G106: FALSE | H106: FALSE | I106: FALSE | J106: FALSE | K106: FALSE | L106: FALSE
D107: 4 | E107: Use of corresponding google categories | F107: FALSE | G107: FALSE | H107: FALSE | I107: FALSE | J107: FALSE | K107: FALSE | L107: FALSE
D108: 5 | E108: Absence of disapproved items | F108: FALSE | G108: FALSE | H108: FALSE | I108: FALSE | J108: FALSE | K108: FALSE | L108: FALSE
B109: =COUNTIF(F109:L111,TRUE)/COUNTA(F109:L111) -> 0 | C109: Advanced | D109: 6 | E109: use of product type and custom labels to signal that a product is high-priority | F109: FALSE | G109: FALSE | H109: FALSE | I109: FALSE | J109: FALSE | K109: FALSE | L109: FALSE
D110: 7 | E110: Automatic product updates and image improvements on | F110: FALSE | G110: FALSE | H110: FALSE | I110: FALSE | J110: FALSE | K110: FALSE | L110: FALSE
D111: 8 | E111: Use of GMC reports and dashboards | F111: FALSE | G111: FALSE | H111: FALSE | I111: FALSE | J111: FALSE | K111: FALSE | L111: FALSE
B112: =COUNTIF(F112:L113,TRUE)/COUNTA(F112:L113) -> 0 | C112: Expert | D112: 9 | E112: Prioritize your most valuable products when allocating budget | F112: FALSE | G112: FALSE | H112: FALSE | I112: FALSE | J112: FALSE | K112: FALSE | L112: FALSE
...

Sheet SEA - Bing
E2: MUST READ: How to use? 1. Only click a checkbox when the topic on the left - is 100% completed 2. Don't check the box if you "just" checked the topic if it was applicable 3. The same topic can be in multiple stages (different levels of maturity) | F2: FR | G2: NL | H2: DE | I2: BE | J2: UK | K2: US | L2: IT | M2: Adaptation topics (V) | N2: Topics not finalized (X) | P2: Last updated at 22/09/2023 by Sjoerd Lops
F3: TRUE | G3: TRUE | H3: TRUE | I3: TRUE | J3: TRUE | K3: TRUE | L3: TRUE | M3: =(COUNTIF(F:L,TRUE))-COUNTIF(F3:L3,true) -> 0 | N3: =COUNTIF(F:L,FALSE) -> 448
B4: =N123 -> 0 | F4: =COUNTIF(F:F,TRUE)-1 -> 0 | G4: =COUNTIF(G:G,TRUE)-1 -> 0 | H4: =COUNTIF(H:H,TRUE)-1 -> 0 | I4: =COUNTIF(I:I,TRUE)-1 -> 0 | J4: =COUNTIF(J:J,TRUE)-1 -> 0 | K4: =COUNTIF(K:K,TRUE)-1 -> 0 | L4: =COUNTIF(L:L,TRUE)-1 -> 0
F6: =COUNTIF(F:F,FALSE) -> 64 | G6: =COUNTIF(G:G,FALSE) -> 64 | H6: =COUNTIF(H:H,FALSE) -> 64 | I6: =COUNTIF(I:I,FALSE) -> 64 | J6: =COUNTIF(J:J,FALSE) -> 64 | K6: =COUNTIF(K:K,FALSE) -> 64 | L6: =COUNTIF(L:L,FALSE) -> 64
C8: Maturity | D8: # | E8: Topics | F8: FR | G8: NL | H8: DE | I8: BE | J8: UK | K8: US | L8: IT | M8: Details | N8: Comments / Action
E9: If a topic is not relevant for the client - delete the checkbox | F9: Only check a box if the topic is fully integrated | M9: Explain what the issue is if not checked | N9: What would be the next steps to finalize the topic
B10: 1
C11: Keywords | F11: =IFERROR(__xludf.DUMMYFUNCTION("SPARKLINE(COUNTIF(F13:L26,TRUE),{""charttype"",""bar"";""max"",COUNTA(F13:L26);""color1"",""green""})"),"") | N11: =COUNTIF(F13:L26,TRUE)/COUNTA(F13:L26) -> 0 | P11: Commentbox for feedback
B13: =COUNTIF(F13:L17,TRUE)/COUNTA(F13:L17) -> 0 | C13: Basic | D13: 1 | E13: Low amount of keywords; generic keywords without including searc intent | F13: FALSE | G13: FALSE | H13: FALSE | I13: FALSE | J13: FALSE | K13: FALSE | L13: FALSE
D14: 2 | E14: Account structure (based on Hagakure) | F14: FALSE | G14: FALSE | H14: FALSE | I14: FALSE | J14: FALSE | K14: FALSE | L14: FALSE
D15: 3 | E15: Keyword research | F15: FALSE | G15: FALSE | H15: FALSE | I15: FALSE | J15: FALSE | K15: FALSE | L15: FALSE
D16: 4 | E16: Standard Namig Convention | F16: FALSE | G16: FALSE | H16: FALSE | I16: FALSE | J16: FALSE | K16: FALSE | L16: FALSE
D17: 5 | E17: Set-up base range of keywords | F17: FALSE | G17: FALSE | H17: FALSE | I17: FALSE | J17: FALSE | K17: FALSE | L17: FALSE
B18: =COUNTIF(F18:L19,TRUE)/COUNTA(F18:L19) -> 0 | C18: Advanced | D18: 6 | E18: Campaign segmentation based on customer journey | F18: FALSE | G18: FALSE | H18: FALSE | I18: FALSE | J18: FALSE | K18: FALSE | L18: FALSE
D19: 7 | E19: Negative keyword list | F19: FALSE | G19: FALSE | H19: FALSE | I19: FALSE | J19: FALSE | K19: FALSE | L19: FALSE
B20: =COUNTIF(F20:L23,TRUE)/COUNTA(F20:L23) -> 0 | C20: Expert | D20: 8 | E20: Mcc Account | F20: FALSE | G20: FALSE | H20: FALSE | I20: FALSE | J20: FALSE | K20: FALSE | L20: FALSE
D21: 9 | E21: Expand account to search engines beyond Google Ads | F21: FALSE | G21: FALSE | H21: FALSE | I21: FALSE | J21: FALSE | K21: FALSE | L21: FALSE
D22: 10 | E22: Implement broad match keywords | F22: FALSE | G22: FALSE | H22: FALSE | I22: FALSE | J22: FALSE | K22: FALSE | L22: FALSE
D23: 11 | E23: Implement DSA ad groups | F23: FALSE | G23: FALSE | H23: FALSE | I23: FALSE | J23: FALSE | K23: FALSE | L23: FALSE
B24: =COUNTIF(F24:L26,TRUE)/COUNTA(F24:L26) -> 0 | C24: Champion | D24: 12 | E24: Feed based DSA ad groups | F24: FALSE | G24: FALSE | H24: FALSE | I24: FALSE | J24: FALSE | K24: FALSE | L24: FALSE
D25: 13 | E25: Third party tooling for using feed based keywords | F25: FALSE | G25: FALSE | H25: FALSE | I25: FALSE | J25: FALSE | K25: FALSE | L25: FALSE
D26: 14 | E26: Use business feeds to create large keyword range | F26: FALSE | G26: FALSE | H26: FALSE | I26: FALSE | J26: FALSE | K26: FALSE | L26: FALSE
B27: 2
C28: Audiences / targeting | F28: =IFERROR(__xludf.DUMMYFUNCTION("SPARKLINE(COUNTIF(F30:L38,TRUE),{""charttype"",""bar"";""max"",COUNTA(F30:L38);""color1"",""green""})"),"") | N28: =COUNTIF(F30:L38,TRUE)/COUNTA(F30:L38) -> 0
B30: =COUNTIF(F30:L30,TRUE)/COUNTA(E30:L30) -> 0 | C30: Basic | D30: 1 | E30: Basic demographics and audiences | F30: FALSE | G30: FALSE | H30: FALSE | I30: FALSE | J30: FALSE | K30: FALSE | L30: FALSE
B31: =COUNTIF(F31:L34,TRUE)/COUNTA(E31:L34) -> 0 | C31: Advanced | D31: 2 | E31: Location targetting | F31: FALSE | G31: FALSE | H31: FALSE | I31: FALSE | J31: FALSE | K31: FALSE | L31: FALSE
D32: 3 | E32: Remarketing lists | F32: FALSE | G32: FALSE | H32: FALSE | I32: FALSE | J32: FALSE | K32: FALSE | L32: FALSE
D33: 4 | E33: Import Google Analytics remarketing audiences | F33: FALSE | G33: FALSE | H33: FALSE | I33: FALSE | J33: FALSE | K33: FALSE | L33: FALSE
D34: 5 | E34: Import Google Analyics audiences based on page visits | F34: FALSE | G34: FALSE | H34: FALSE | I34: FALSE | J34: FALSE | K34: FALSE | L34: FALSE
B35: =COUNTIF(F35:L35,TRUE)/COUNTA(E35:L35) -> 0 | C35: Expert | D35: 6 | E35: Incorporate all audiences above in the campaignsettings | F35: FALSE | G35: FALSE | H35: FALSE | I35: FALSE | J35: FALSE | K35: FALSE | L35: FALSE
B36: =COUNTIF(F36:L38,TRUE)/COUNTA(E36:L38) -> 0 | C36: Champion | D36: 7 | E36: Import CRM lists | F36: FALSE | G36: FALSE | H36: FALSE | I36: FALSE | J36: FALSE | K36: FALSE | L36: FALSE
D37: 8 | E37: Import 1st party data based audiences | F37: FALSE | G37: FALSE | H37: FALSE | I37: FALSE | J37: FALSE | K37: FALSE | L37: FALSE
D38: 9 | E38: Create custom look-a-like audiences based on 1st party | F38: FALSE | G38: FALSE | H38: FALSE | I38: FALSE | J38: FALSE | K38: FALSE | L38: FALSE
B39: 3
C40: Conversion & KPI | F40: =IFERROR(__xludf.DUMMYFUNCTION("SPARKLINE(COUNTIF(F42:L52,TRUE),{""charttype"",""bar"";""max"",COUNTA(F42:L52);""color1"",""green""})"),"") | N40: =COUNTIF(F42:L52,TRUE)/COUNTA(F42:L52) -> 0
B42: =COUNTIF(F42:L44,TRUE)/COUNTA(F42:L44) -> 0 | C42: Basic | D42: 1 | E42: Conversion set-up | F42: FALSE | G42: FALSE | H42: FALSE | I42: FALSE | J42: FALSE | K42: FALSE | L42: FALSE
D43: 2 | E43: Conversion tags are implemented in GTM | F43: FALSE | G43: FALSE | H43: FALSE | I43: FALSE | J43: FALSE | K43: FALSE | L43: FALSE
D44: 3 | E44: Focus on increasing amount of conversions | F44: FALSE | G44: FALSE | H44: FALSE | I44: FALSE | J44: FALSE | K44: FALSE | L44: FALSE
B45: =COUNTIF(F45:L47,TRUE)/COUNTA(F45:L47) -> 0 | C45: Advanced | D45: 4 | E45: Conversion data (ensure conversion data) | F45: FALSE | G45: FALSE | H45: FALSE | I45: FALSE | J45: FALSE | K45: FALSE | L45: FALSE
D46: 5 | E46: Enhanced Conversions For lead generation Implemented | F46: FALSE | G46: FALSE | H46: FALSE | I46: FALSE | J46: FALSE | K46: FALSE | L46: FALSE
D47: 6 | E47: KPI based strategy (ROAS or CPA) | F47: FALSE | G47: FALSE | H47: FALSE | I47: FALSE | J47: FALSE | K47: FALSE | L47: FALSE
B48: =COUNTIF(F48:L49,TRUE)/COUNTA(F48:L49) -> 0 | C48: Expert | D48: 7 | E48: Segment your targets (based on contribution value) | F48: FALSE | G48: FALSE | H48: FALSE | I48: FALSE | J48: FALSE | K48: FALSE | L48: FALSE
D49: 8 | E49: Focus on growing revenue/ conversions against tROAS/tCPA | F49: FALSE | G49: FALSE | H49: FALSE | I49: FALSE | J49: FALSE | K49: FALSE | L49: FALSE
D50: 9 | E50: Implement third party tracking tool (cross-marketing channel reporting) | F50: FALSE | G50: FALSE | H50: FALSE | I50: FALSE | J50: FALSE | K50: FALSE | L50: FALSE
B51: =COUNTIF(F51:L52,TRUE)/COUNTA(F51:L52) -> 0 | C51: Champion | D51: 10 | E51: Integrate business level KPI data into Google Ads (margin) | F51: FALSE | G51: FALSE | H51: FALSE | I51: FALSE | J51: FALSE | K51: FALSE | L51: FALSE
D52: 11 | E52: Steer on POAS, incremental ROAS/CPA | F52: FALSE | G52: FALSE | H52: FALSE | I52: FALSE | J52: FALSE | K52: FALSE | L52: FALSE
B53: 4
C54: Attribution | F54: =IFERROR(__xludf.DUMMYFUNCTION("SPARKLINE(COUNTIF(F56:L60,TRUE),{""charttype"",""bar"";""max"",COUNTA(F56:L60);""color1"",""green""})"),"") | N54: =COUNTIF(F56:L60,TRUE)/COUNTA(F56:L60) -> 0
B56: =COUNTIF(F56:L56,TRUE)/COUNTA(E56:L56) -> 0 | C56: Basic | D56: 1 | E56: Conversion settings are set to the right attribtuion model | F56: FALSE | G56: FALSE | H56: FALSE | I56: FALSE | J56: FALSE | K56: FALSE | L56: FALSE
B57: =COUNTIF(F57:L57,TRUE)/COUNTA(E57:L57) -> 0 | C57: Advanced | D57: 2 | E57: Conversion settings are set to DDA model | F57: FALSE | G57: FALSE | H57: FALSE | I57: FALSE | J57: FALSE | K57: FALSE | L57: FALSE
B58: =COUNTIF(F58:L58,TRUE)/COUNTA(E58:L58) -> 0 | C58: Expert | D58: 3 | E58: Import business data (scripting/ API). E.g.: returnrates, CLV, order frequency | F58: FALSE | G58: FALSE | H58: FALSE | I58: FALSE | J58: FALSE | K58: FALSE | L58: FALSE
B59: =COUNTIF(F59:L60,TRUE)/COUNTA(F59:L60) -> 0 | C59: Champion | D59: 4 | E59: Setup deduplicated conversion tracking | F59: FALSE | G59: FALSE | H59: FALSE | I59: FALSE | J59: FALSE | K59: FALSE | L59: FALSE
D60: 5 | E60: Setup conversion framework based on micro and macro conversions | F60: FALSE | G60: FALSE | H60: FALSE | I60: FALSE | J60: FALSE | K60: FALSE | L60: FALSE
B61: 5
C62: Bid Management | F62: =IFERROR(__xludf.DUMMYFUNCTION("SPARKLINE(COUNTIF(F64:L67,TRUE),{""charttype"",""bar"";""max"",COUNTA(F64:L67);""color1"",""green""})"),"") | N62: =COUNTIF(F64:L67,TRUE)/COUNTA(F64:L67) -> 0
B64: =COUNTIF(F64:L64,TRUE)/COUNTA(E64:L64) -> 0 | C64: Basic | D64: 1 | E64: Simple automated bid strategies (e.g.: SIS 90-95) | F64: FALSE | G64: FALSE | H64: FALSE | I64: FALSE | J64: FALSE | K64: FALSE | L64: FALSE
B65: =COUNTIF(F65:L65,TRUE)/COUNTA(E65:L65) -> 0 | C65: Advanced | D65: 2 | E65: Import Google Analytics remarketing audiences based on non convertors | F65: FALSE | G65: FALSE | H65: FALSE | I65: FALSE | J65: FALSE | K65: FALSE | L65: FALSE
B66: =COUNTIF(F66:L66,TRUE)/COUNTA(E66:L66) -> 0 | C66: Expert | D66: 3 | E66: Segment bid strategies based on performance | F66: FALSE | G66: FALSE | H66: FALSE | I66: FALSE | J66: FALSE | K66: FALSE | L66: FALSE
B67: =COUNTIF(F67:L67,TRUE)/COUNTA(E67:L67) -> 0 | C67: Champion | D67: 4 | E67: Smart bidding with VBB and othe applicable data enrichments | F67: FALSE | G67: FALSE | H67: FALSE | I67: FALSE | J67: FALSE | K67: FALSE | L67: FALSE
B68: 6
C69: Extensions | F69: =IFERROR(__xludf.DUMMYFUNCTION("SPARKLINE(COUNTIF(F71:L77,TRUE),{""charttype"",""bar"";""max"",COUNTA(F71:L77);""color1"",""green""})"),"") | N69: =COUNTIF(F71:L77,TRUE)/COUNTA(F71:L77) -> 0
B71: =COUNTIF(F71:L72,TRUE)/COUNTA(F71:L72) -> 0 | C71: Basic | D71: 1 | E71: Campaign level ad extensions | F71: FALSE | G71: FALSE | H71: FALSE | I71: FALSE | J71: FALSE | K71: FALSE | L71: FALSE
D72: 2 | E72: Account level ad extensions | F72: FALSE | G72: FALSE | H72: FALSE | I72: FALSE | J72: FALSE | K72: FALSE | L72: FALSE
B73: =COUNTIF(F73:L75,TRUE)/COUNTA(F73:L75) -> 0 | C73: Advanced | D73: 3 | E73: Expand use of extensions | F73: FALSE | G73: FALSE | H73: FALSE | I73: FALSE | J73: FALSE | K73: FALSE | L73: FALSE
D74: 4 | E74: Campaing level ad extensions (4) | F74: FALSE | G74: FALSE | H74: FALSE | I74: FALSE | J74: FALSE | K74: FALSE | L74: FALSE
D75: 5 | E75: Account level ad extensions (4) | F75: FALSE | G75: FALSE | H75: FALSE | I75: FALSE | J75: FALSE | K75: FALSE | L75: FALSE
B76: =COUNTIF(F76:L76,TRUE)/COUNTA(E76:L76) -> 0 | C76: Expert | D76: 6 | E76: Tailor campaign level ad extensions to needs | F76: FALSE | G76: FALSE | H76: FALSE | I76: FALSE | J76: FALSE | K76: FALSE | L76: FALSE
B77: =COUNTIF(F77:L77,TRUE)/COUNTA(E77:L77) -> 0 | C77: Champion | D77: 7 | E77: Tailor adgroup level ad extensions to needs for individual ad groups | F77: FALSE | G77: FALSE | H77: FALSE | I77: FALSE | J77: FALSE | K77: FALSE | L77: FALSE
B78: 7
C79: Message | F79: =IFERROR(__xludf.DUMMYFUNCTION("SPARKLINE(COUNTIF(F81:L84,TRUE),{""charttype"",""bar"";""max"",COUNTA(F81:L84);""color1"",""green""})"),"") | N79: =COUNTIF(F81:L84,TRUE)/COUNTA(F81:L84) -> 0
B81: =COUNTIF(F81:L81,TRUE)/COUNTA(E81:L81) -> 0 | C81: Basic | D81: 1 | E81: Ad group tailored ads | F81: FALSE | G81: FALSE | H81: FALSE | I81: FALSE | J81: FALSE | K81: FALSE | L81: FALSE
B82: =COUNTIF(F82:L82,TRUE)/COUNTA(E82:L82) -> 0 | C82: Advanced | D82: 2 | E82: RSA reflect steps in customer journey | F82: FALSE | G82: FALSE | H82: FALSE | I82: FALSE | J82: FALSE | K82: FALSE | L82: FALSE
B83: =COUNTIF(F83:L83,TRUE)/COUNTA(E83:L83) -> 0 | C83: Expert | D83: 3 | E83: Customer based RSAs based on broad contextual signals | F83: FALSE | G83: FALSE | H83: FALSE | I83: FALSE | J83: FALSE | K83: FALSE | L83: FALSE
B84: =COUNTIF(F84:L84,TRUE)/COUNTA(E84:L84) -> 0 | C84: Champion | D84: 4 | E84: Tailored ad text by using contextual signals | F84: FALSE | G84: FALSE | H84: FALSE | I84: FALSE | J84: FALSE | K84: FALSE | L84: FALSE
B85: 8
C86: Automation | F86: =IFERROR(__xludf.DUMMYFUNCTION("SPARKLINE(COUNTIF(F88:L97,TRUE),{""charttype"",""bar"";""max"",COUNTA(F88:L97);""color1"",""green""})"),"") | N86: =COUNTIF(F88:L97,TRUE)/COUNTA(F88:L97) -> 0
B88: =COUNTIF(F88:L90,TRUE)/COUNTA(F88:L90) -> 0 | C88: Basic | D88: 1 | E88: Set-up labeling tools | F88: FALSE | G88: FALSE | H88: FALSE | I88: FALSE | J88: FALSE | K88: FALSE | L88: FALSE
D89: 2 | E89: Set-up enable/pause rules | F89: FALSE | G89: FALSE | H89: FALSE | I89: FALSE | J89: FALSE | K89: FALSE | L89: FALSE
D90: 3 | E90: Set-up alerts for major drops | F90: FALSE | G90: FALSE | H90: FALSE | I90: FALSE | J90: FALSE | K90: FALSE | L90: FALSE
B91: =COUNTIF(F91:L92,TRUE)/COUNTA(F91:L92) -> 0 | C91: Advanced | D91: 4 | E91: Leverage 3rd party tooling for account hygience (aka running audits) | F91: FALSE | G91: FALSE | H91: FALSE | I91: FALSE | J91: FALSE | K91: FALSE | L91: FALSE
D92: 5 | E92: Set-up automated reporting | F92: FALSE | G92: FALSE | H92: FALSE | I92: FALSE | J92: FALSE | K92: FALSE | L92: FALSE
B93: =COUNTIF(F93:L94,TRUE)/COUNTA(F93:L94) -> 0 | C93: Expert | D93: 6 | E93: Cross platform or cross-account management tools | F93: FALSE | G93: FALSE | H93: FALSE | I93: FALSE | J93: FALSE | K93: FALSE | L93: FALSE
D94: 7 | E94: Tooling that helps delivering proactive optimization opportunities | F94: FALSE | G94: FALSE | H94: FALSE | I94: FALSE | J94: FALSE | K94: FALSE | L94: FALSE
B95: =COUNTIF(F95:L97,TRUE)/COUNTA(F95:L97) -> 0 | C95: Champion | D95: 8 | E95: Value based bidding (e.g.: Optimyzer) | F95: FALSE | G95: FALSE | H95: FALSE | I95: FALSE | J95: FALSE | K95: FALSE | L95: FALSE
D96: 9 | E96: Automated account reviews (e.g.: Wordstream) | F96: FALSE | G96: FALSE | H96: FALSE | I96: FALSE | J96: FALSE | K96: FALSE | L96: FALSE
D97: 10 | E97: Scalable keywords (e.g.: SpyFu) | F97: FALSE | G97: FALSE | H97: FALSE | I97: FALSE | J97: FALSE | K97: FALSE | L97: FALSE
B99: SUMMARY (relevance to be adjusted to client needs) | P99: << in the column on the left you can decide if a certain topic is more or less important compared to others - to decide how important it is for the total score of a client Example given: Feed management is not always relevant for a company (B2B). You can give the relevance a score of 0 and it won't be calculated in the total average score Default setting: all topics at 100%
E101: Topic | F101: Topic relevance 0-100% | N101: Total score
C103: 1 | E103: =C11 -> Keywords | F103: 1 | M103: =IFERROR(__xludf.DUMMYFUNCTION("F11"),"") | N103: =N11 -> 0
C105: 2 | E105: =C28 -> Audiences / targeting | F105: 1 | M105: =IFERROR(__xludf.DUMMYFUNCTION("F28"),"") | N105: =N28 -> 0
C107: 3 | E107: =C40 -> Conversion & KPI | F107: 1 | M107: =IFERROR(__xludf.DUMMYFUNCTION("F40"),"") | N107: =N40 -> 0
C109: 4 | E109: =C54 -> Attribution | F109: 1 | M109: =IFERROR(__xludf.DUMMYFUNCTION("F54"),"") | N109: =N54 -> 0
C111: 5 | E111: =C62 -> Bid Management | F111: 1 | M111: =IFERROR(__xludf.DUMMYFUNCTION("F62"),"") | N111: =N62 -> 0
C113: 6 | E113: =C69 -> Extensions | F113: 1 | M113: =IFERROR(__xludf.DUMMYFUNCTION("F69"),"") | N113: =N69 -> 0
C115: 7 | E115: =C79 -> Message | F115: 1 | M115: =IFERROR(__xludf.DUMMYFUNCTION("F79"),"") | N115: =N79 -> 0
C117: 8 | E117: =C86 -> Automation | F117: 1 | M117: =IFERROR(__xludf.DUMMYFUNCTION("F86"),"") | N117: =N86 -> 0
C119: 9
C121: 10
M123: Total average weighted score | N123: =IFERROR(__xludf.DUMMYFUNCTION("AVERAGE.WEIGHTED(N103:N121,F103:F121)"),0.0) -> 0

Sheet META
E2: MUST READ: How to use? 1. Only click a checkbox when the topic on the left - is 100% completed 2. Don't check the box if you "just" checked the topic if it was applicable 3. The same topic can be in multiple stages (different levels of maturity) | F2: FR | G2: NL | H2: DE | I2: BE | J2: UK | K2: US | L2: IT | M2: Adaptation topics (V) | N2: Topics not finalized (X) | P2: Last updated at 04/12/2025 by Laman Guliyeva
F3: TRUE | G3: TRUE | H3: TRUE | I3: TRUE | J3: TRUE | K3: TRUE | L3: TRUE | M3: =(COUNTIF(F:L,TRUE))-COUNTIF(F3:L3,true) -> 0 | N3: =COUNTIF(F:L,FALSE) -> 483
B4: =N122 -> 0 | F4: =COUNTIF(F:F,TRUE)-1 -> 0 | G4: =COUNTIF(G:G,TRUE)-1 -> 0 | H4: =COUNTIF(H:H,TRUE)-1 -> 0 | I4: =COUNTIF(I:I,TRUE)-1 -> 0 | J4: =COUNTIF(J:J,TRUE)-1 -> 0 | K4: =COUNTIF(K:K,TRUE)-1 -> 0 | L4: =COUNTIF(L:L,TRUE)-1 -> 0
F6: =COUNTIF(F:F,FALSE) -> 69 | G6: =COUNTIF(G:G,FALSE) -> 69 | H6: =COUNTIF(H:H,FALSE) -> 69 | I6: =COUNTIF(I:I,FALSE) -> 69 | J6: =COUNTIF(J:J,FALSE) -> 69 | K6: =COUNTIF(K:K,FALSE) -> 69 | L6: =COUNTIF(L:L,FALSE) -> 69
C8: Maturity | D8: # | E8: Topics | F8: FR | G8: NL | H8: DE | I8: BE | J8: UK | K8: US | L8: IT | M8: Details | N8: Comments / Action
E9: If a topic is not relevant for the client - delete the checkbox | F9: Only check a box if the topic is fully integrated | M9: Explain what the issue is if not checked | N9: What would be the next steps to finalize the topic
B10: 1
C11: Campaign setup | F11: =IFERROR(__xludf.DUMMYFUNCTION("SPARKLINE(COUNTIF(F13:L23,TRUE),{""charttype"",""bar"";""max"",COUNTA(F13:L23);""color1"",""green""})"),"") | N11: =COUNTIF(F13:L23,TRUE)/COUNTA(F13:L23) -> 0 | P11: Commentbox for feedback
B13: 0 | C13: Basic | D13: 1 | E13: Campaign setup based on algorithms | F13: FALSE | G13: FALSE | H13: FALSE | I13: FALSE | J13: FALSE | K13: FALSE | L13: FALSE
D14: 2 | E14: Organized structure | F14: FALSE | G14: FALSE | H14: FALSE | I14: FALSE | J14: FALSE | K14: FALSE | L14: FALSE
B15: =COUNTIF(F15:L20,TRUE)/COUNTA(E15:L20) -> 0 | C15: Advanced | D15: 3 | E15: Simple structure (easy to understand) | F15: FALSE | G15: FALSE | H15: FALSE | I15: FALSE | J15: FALSE | K15: FALSE | L15: FALSE
D16: 4 | E16: Naming convention on campaign level | F16: FALSE | G16: FALSE | H16: FALSE | I16: FALSE | J16: FALSE | K16: FALSE | L16: FALSE
D17: 5 | E17: Naming convention on ad group level | F17: FALSE | G17: FALSE | H17: FALSE | I17: FALSE | J17: FALSE | K17: FALSE | L17: FALSE
D18: 6 | E18: Naming convention on ad level | F18: FALSE | G18: FALSE | H18: FALSE | I18: FALSE | J18: FALSE | K18: FALSE | L18: FALSE
D19: 7 | E19: Structure in line with offer on the website | F19: FALSE | G19: FALSE | H19: FALSE | I19: FALSE | J19: FALSE | K19: FALSE | L19: FALSE
D20: 8 | E20: Lookback windows | F20: FALSE | G20: FALSE | H20: FALSE | I20: FALSE | J20: FALSE | K20: FALSE | L20: FALSE
B21: =COUNTIF(F21:G21,TRUE)/COUNTA(F21:G21) -> 0 | C21: Expert | D21: 9 | E21: Advantage+ Sales Plus campaigns for ecommerce | F21: FALSE | G21: FALSE | H21: FALSE | I21: FALSE | J21: FALSE | K21: FALSE | L21: FALSE
B22: =COUNTIF(F22:L23,TRUE)/COUNTA(L22:BQ23) -> 0 | C22: Champion | D22: 9 | E22: Build campaign setups via Excel or external tooling (e.g. Smartly / ByCape.io) | F22: FALSE | G22: FALSE | H22: FALSE | I22: FALSE | J22: FALSE | K22: FALSE | L22: FALSE
D23: 10 | E23: Have a naming convention tool integration (grasp) | F23: FALSE | G23: FALSE | H23: FALSE | I23: FALSE | J23: FALSE | K23: FALSE | L23: FALSE
B24: 2
C25: Audiences & targeting | F25: =IFERROR(__xludf.DUMMYFUNCTION("SPARKLINE(COUNTIF(F27:L41,TRUE),{""charttype"",""bar"";""max"",COUNTA(F27:L41);""color1"",""green""})"),"") | N25: =COUNTIF(F27:L41,TRUE)/COUNTA(F27:L41) -> 0
B27: =COUNTIF(F27:L31,TRUE)/COUNTA(F27:L31) -> 0 | C27: Basic | D27: 1 | E27: Language targeting | F27: FALSE | G27: FALSE | H27: FALSE | I27: FALSE | J27: FALSE | K27: FALSE | L27: FALSE
D28: 2 | E28: Age targeting | F28: FALSE | G28: FALSE | H28: FALSE | I28: FALSE | J28: FALSE | K28: FALSE | L28: FALSE
D29: 3 | E29: Demographic targeting | F29: FALSE | G29: FALSE | H29: FALSE | I29: FALSE | J29: FALSE | K29: FALSE | L29: FALSE
D30: 4 | E30: Specific placement targeting | F30: FALSE | G30: FALSE | H30: FALSE | I30: FALSE | J30: FALSE | K30: FALSE | L30: FALSE
D31: 5 | E31: Dedicated campaign per market | F31: FALSE | G31: FALSE | H31: FALSE | I31: FALSE | J31: FALSE | K31: FALSE | L31: FALSE
B32: =COUNTIF(F32:L35,TRUE)/COUNTA(F32:L35) -> 0 | C32: Advanced | D32: 6 | E32: Is there an audience framework in place (and used for targeting?) | F32: FALSE | G32: FALSE | H32: FALSE | I32: FALSE | J32: FALSE | K32: FALSE | L32: FALSE
D33: 7 | E33: Is there a persona in place from client side (the ideal customer) | F33: FALSE | G33: FALSE | H33: FALSE | I33: FALSE | J33: FALSE | K33: FALSE | L33: FALSE
D34: 8 | E34: Retargeting audiences | F34: FALSE | G34: FALSE | H34: FALSE | I34: FALSE | J34: FALSE | K34: FALSE | L34: FALSE
D35: 9 | E35: Inplatform audiences (followers, retarget video viewers) | F35: FALSE | G35: FALSE | H35: FALSE | I35: FALSE | J35: FALSE | K35: FALSE | L35: FALSE
B36: =COUNTIF(F36:L40,TRUE)/COUNTA(F36:L40) -> 0 | C36: Expert | D36: 10 | E36: Event based audiences (on pixel events) | F36: FALSE | G36: FALSE | H36: FALSE | I36: FALSE | J36: FALSE | K36: FALSE | L36: FALSE
D37: 11 | E37: Bid adjustments per audience | F37: FALSE | G37: FALSE | H37: FALSE | I37: FALSE | J37: FALSE | K37: FALSE | L37: FALSE
D38: 12 | E38: Customer Match audiences | F38: FALSE | G38: FALSE | H38: FALSE | I38: FALSE | J38: FALSE | K38: FALSE | L38: FALSE
D39: 13 | E39: Is the Advantage+ Audiences set up used? | F39: FALSE | G39: FALSE | H39: FALSE | I39: FALSE | J39: FALSE | K39: FALSE | L39: FALSE
D40: 14 | E40: Audience Segments established | F40: FALSE | G40: FALSE | H40: FALSE | I40: FALSE | J40: FALSE | K40: FALSE | L40: FALSE
B41: =COUNTIF(F41:L41,TRUE)/COUNTA(F41:L41) -> 0 | C41: Champion | D41: 15 | E41: Customer Data Platform (CDP) integration | F41: FALSE | G41: FALSE | H41: FALSE | I41: FALSE | J41: FALSE | K41: FALSE | L41: FALSE
B42: 3
C43: Conversion & KPI | F43: =IFERROR(__xludf.DUMMYFUNCTION("SPARKLINE(COUNTIF(F45:L54,TRUE),{""charttype"",""bar"";""max"",COUNTA(F45:L54);""color1"",""green""})"),"") | N43: =COUNTIF(F45:L57,TRUE)/COUNTA(F45:L54) -> 0
B45: =COUNTIF(F45:L48,TRUE)/COUNTA(L45:BQ48) -> 0 | C45: Basic | D45: 1 | E45: General goal for Meta (total) | F45: FALSE | G45: FALSE | H45: FALSE | I45: FALSE | J45: FALSE | K45: FALSE | L45: FALSE
D46: 2 | E46: The Meta pixel has been installed on the website | F46: FALSE | G46: FALSE | H46: FALSE | I46: FALSE | J46: FALSE | K46: FALSE | L46: FALSE
D47: 3 | E47: Campaigns use the same Pixel across the funnel | F47: FALSE | G47: FALSE | H47: FALSE | I47: FALSE | J47: FALSE | K47: FALSE | L47: FALSE
D48: 4 | E48: Monthly performance check in on KPI's | F48: FALSE | G48: FALSE | H48: FALSE | I48: FALSE | J48: FALSE | K48: FALSE | L48: FALSE
B49: =COUNTIF(F49:L50,TRUE)/COUNTA(E49:L50) -> 0 | C49: Advanced | D49: 5 | E49: A clear KPI framework with goals per funnel | F49: FALSE | G49: FALSE | H49: FALSE | I49: FALSE | J49: FALSE | K49: FALSE | L49: FALSE
D50: 6 | E50: Classic events are made (view, add to cart, purchase) | F50: FALSE | G50: FALSE | H50: FALSE | I50: FALSE | J50: FALSE | K50: FALSE | L50: FALSE
B51: =COUNTIF(F51:L52,TRUE)/COUNTA(L51:BQ52) -> 0 | C51: Expert | D51: 7 | E51: Soft conversion have been added (such as a quality visit) | F51: FALSE | G51: FALSE | H51: FALSE | I51: FALSE | J51: FALSE | K51: FALSE | L51: FALSE
D52: 8 | E52: Conversion API setup | F52: FALSE | G52: FALSE | H52: FALSE | I52: FALSE | J52: FALSE | K52: FALSE | L52: FALSE
B53: =COUNTIF(F53:L54,TRUE)/COUNTA(E53:L54) -> 0 | C53: Champion | D53: 9 | E53: Goal per type of customer (new customer or returning customer) | F53: FALSE | G53: FALSE | H53: FALSE | I53: FALSE | J53: FALSE | K53: FALSE | L53: FALSE
D54: 10 | E54: Customer life time value | F54: FALSE | G54: FALSE | H54: FALSE | I54: FALSE | J54: FALSE | K54: FALSE | L54: FALSE
B55: 4
C56: Feeds & catalogues | F56: =IFERROR(__xludf.DUMMYFUNCTION("SPARKLINE(COUNTIF(F58:F64,TRUE),{""charttype"",""bar"";""max"",COUNTA(F58:F64);""color1"",""green""})"),"") | N56: =COUNTIF(F58:L64,TRUE)/COUNTA(F58:L64) -> 0
B58: =COUNTIF(F58:L58,TRUE)/COUNTA(F58:L58) -> 0 | C58: Basic | D58: 1 | E58: There is a productfeed connected from the "backend" to Meta | F58: FALSE | G58: FALSE | H58: FALSE | I58: FALSE | J58: FALSE | K58: FALSE | L58: FALSE
B59: =COUNTIF(F59:L62,TRUE)/COUNTA(E59:L62) -> 0 | C59: Advanced | D59: 2 | E59: There are top performing product lists in use | F59: FALSE | G59: FALSE | H59: FALSE | I59: FALSE | J59: FALSE | K59: FALSE | L59: FALSE
D60: 3 | E60: There are seasonality lists available | F60: FALSE | G60: FALSE | H60: FALSE | I60: FALSE | J60: FALSE | K60: FALSE | L60: FALSE
D61: 4 | E61: Catalogue match rate (last 28d) >90% | F61: FALSE | G61: FALSE | H61: FALSE | I61: FALSE | J61: FALSE | K61: FALSE | L61: FALSE
D62: 5 | E62: Pixel is connected to the catalogue | F62: FALSE | G62: FALSE | H62: FALSE | I62: FALSE | J62: FALSE | K62: FALSE | L62: FALSE
B63: =COUNTIF(F63:L64,TRUE)/COUNTA(E63:L64) -> 0 | C63: Expert | D63: 6 | E63: Shopping weight has been added to catalogue | F63: FALSE | G63: FALSE | H63: FALSE | I63: FALSE | J63: FALSE | K63: FALSE | L63: FALSE
D64: 7 | E64: Client is working with a feedmanagementtool | F64: FALSE | G64: FALSE | H64: FALSE | I64: FALSE | J64: FALSE | K64: FALSE | L64: FALSE
B65: 5
C66: Creative & content | F66: =IFERROR(__xludf.DUMMYFUNCTION("SPARKLINE(COUNTIF(F68:L82,TRUE),{""charttype"",""bar"";""max"",COUNTA(F68:L82);""color1"",""green""})"),"") | N66: =COUNTIF(F68:L82,TRUE)/COUNTA(F68:L82) -> 0
B68: =COUNTIF(F68:L72,TRUE)/COUNTA(F68:L72) -> 0 | C68: Basic | D68: 1 | E68: Usage of image ads | F68: FALSE | G68: FALSE | H68: FALSE | I68: FALSE | J68: FALSE | K68: FALSE | L68: FALSE
D69: 2 | E69: Usage of video ads | F69: FALSE | G69: FALSE | H69: FALSE | I69: FALSE | J69: FALSE | K69: FALSE | L69: FALSE
D70: 3 | E70: Usage of call to actions | F70: FALSE | G70: FALSE | H70: FALSE | I70: FALSE | J70: FALSE | K70: FALSE | L70: FALSE
D71: 4 | E71: Usage of brand name in the image | F71: FALSE | G71: FALSE | H71: FALSE | I71: FALSE | J71: FALSE | K71: FALSE | L71: FALSE
D72: 5 | E72: Copy Length | F72: FALSE | G72: FALSE | H72: FALSE | I72: FALSE | J72: FALSE | K72: FALSE | L72: FALSE
B73: =COUNTIF(F73:L78,TRUE)/COUNTA(F73:L78) -> 0 | C73: Advanced | D73: 6 | E73: Rotation mode of creatives | F73: FALSE | G73: FALSE | H73: FALSE | I73: FALSE | J73: FALSE | K73: FALSE | L73: FALSE
D74: 7 | E74: 3-4 ad texts per ad | F74: FALSE | G74: FALSE | H74: FALSE | I74: FALSE | J74: FALSE | K74: FALSE | L74: FALSE
D75: 8 | E75: Carousel ads | F75: FALSE | G75: FALSE | H75: FALSE | I75: FALSE | J75: FALSE | K75: FALSE | L75: FALSE
D76: 9 | E76: Collection ads | F76: FALSE | G76: FALSE | H76: FALSE | I76: FALSE | J76: FALSE | K76: FALSE | L76: FALSE
D77: 10 | E77: Both square as story images to match placement sizes | F77: FALSE | G77: FALSE | H77: FALSE | I77: FALSE | J77: FALSE | K77: FALSE | L77: FALSE
D78: 11 | E78: Multi-Advertiser Ads | F78: FALSE | G78: FALSE | H78: FALSE | I78: FALSE | J78: FALSE | K78: FALSE | L78: FALSE
B79: =COUNTIF(F79:L81,TRUE)/COUNTA(F79:L81) -> 0 | C79: Expert | D79: 12 | E79: Dynamic Product Ads (DPA) | F79: FALSE | G79: FALSE | H79: FALSE | I79: FALSE | J79: FALSE | K79: FALSE | L79: FALSE
D80: 13 | E80: If dynamic formats used (carousel, collection), is Meta allowed to automatically show the best performing variation? | F80: FALSE | G80: FALSE | H80: FALSE | I80: FALSE | J80: FALSE | K80: FALSE | L80: FALSE
D81: 14 | E81: Are the Advantage+ Creative Enhancements activated? | F81: FALSE | G81: FALSE | H81: FALSE | I81: FALSE | J81: FALSE | K81: FALSE | L81: FALSE
B82: =COUNTIF(F82:L82,TRUE)/COUNTA(F82:L82) -> 0 | C82: Champion | D82: 15 | E82: Dynamic Creative Optimization (DCO) - via tooling or other options | F82: FALSE | G82: FALSE | H82: FALSE | I82: FALSE | J82: FALSE | K82: FALSE | L82: FALSE
B83: 6
C84: Reporting | F84: =IFERROR(__xludf.DUMMYFUNCTION("SPARKLINE(COUNTIF(F86:L96,TRUE),{""charttype"",""bar"";""max"",COUNTA(F86:L96);""color1"",""green""})"),"") | N84: =COUNTIF(F86:L96,TRUE)/COUNTA(F86:L96) -> 0
B86: =COUNTIF(F86:L86,TRUE)/COUNTA(F86:L86) -> 0 | C86: Basic | D86: 1 | E86: Gathering insights from campaign overview | F86: FALSE | G86: FALSE | H86: FALSE | I86: FALSE | J86: FALSE | K86: FALSE | L86: FALSE
B87: =COUNTIF(F87:L91,TRUE)/COUNTA(F87:L91) -> 0 | C87: Advanced | D87: 2 | E87: Pre-defined Meta reports per funnel | F87: FALSE | G87: FALSE | H87: FALSE | I87: FALSE | J87: FALSE | K87: FALSE | L87: FALSE
D88: 3 | E88: Meta & website insights (GA) | F88: FALSE | G88: FALSE | H88: FALSE | I88: FALSE | J88: FALSE | K88: FALSE | L88: FALSE
D89: 4 | E89: A/B testing in Meta (experiments) | F89: FALSE | G89: FALSE | H89: FALSE | I89: FALSE | J89: FALSE | K89: FALSE | L89: FALSE
D90: 5 | E90: Budget management (check if budgets are aligned with objectives) | F90: FALSE | G90: FALSE | H90: FALSE | I90: FALSE | J90: FALSE | K90: FALSE | L90: FALSE
D91: 6 | E91: Monthly reporting meetings | F91: FALSE | G91: FALSE | H91: FALSE | I91: FALSE | J91: FALSE | K91: FALSE | L91: FALSE
B92: =COUNTIF(F92:L93,TRUE)/COUNTA(L92:BQ93) -> 0 | C92: Expert | D92: 7 | E92: Real time data dasboard | F92: FALSE | G92: FALSE | H92: FALSE | I92: FALSE | J92: FALSE | K92: FALSE | L92: FALSE
D93: 8 | E93: Consisted testing framework including hyptohesis | F93: FALSE | G93: FALSE | H93: FALSE | I93: FALSE | J93: FALSE | K93: FALSE | L93: FALSE
B94: =COUNTIF(F94:L96,TRUE)/COUNTA(L94:BQ96) -> 0 | C94: Champion | D94: 9 | E94: Brand lift studies | F94: FALSE | G94: FALSE | H94: FALSE | I94: FALSE | J94: FALSE | K94: FALSE | L94: FALSE
D95: 10 | E95: Conversion lift studies in Meta | F95: FALSE | G95: FALSE | H95: FALSE | I95: FALSE | J95: FALSE | K95: FALSE | L95: FALSE
D96: 11 | E96: Marketing mix modeling | F96: FALSE | G96: FALSE | H96: FALSE | I96: FALSE | J96: FALSE | K96: FALSE | L96: FALSE
B98: SUMMARY (relevance to be adjusted to client needs) | P98: << in the column on the left you can decide if a certain topic is more or less important compared to others - to decide how important it is for the total score of a client Example given: Feed management is not always relevant for a company (B2B). You can give the relevance a score of 0 and it won't be calculated in the total average score Default setting: all topics at 100%
E100: Topic | F100: Topic relevance 0-100% | N100: Total score
C102: 1 | E102: =C11 -> Campaign setup | F102: 1 | M102: =IFERROR(__xludf.DUMMYFUNCTION("F11"),"") | N102: =N11 -> 0
C104: 2 | E104: =C25 -> Audiences & targeting | F104: 1 | M104: =IFERROR(__xludf.DUMMYFUNCTION("F25"),"") | N104: =N66 -> 0
C106: 3 | E106: =C43 -> Conversion & KPI | F106: 1 | M106: =IFERROR(__xludf.DUMMYFUNCTION("F43"),"") | N106: =N43 -> 0
C108: 4 | E108: =C56 -> Feeds & catalogues | F108: 1 | M108: =IFERROR(__xludf.DUMMYFUNCTION("F56"),"") | N108: =N56 -> 0
C110: 5 | E110: =C66 -> Creative & content | F110: 1 | M110: =IFERROR(__xludf.DUMMYFUNCTION("F66"),"") | N110: =N66 -> 0
C112: 6 | E112: =C84 -> Reporting | F112: 1 | M112: =IFERROR(__xludf.DUMMYFUNCTION("F84"),"") | N112: =N84 -> 0
C114: 7
C116: 8
C118: 9
C120: 10
M122: Total average weighted score | N122: =IFERROR(__xludf.DUMMYFUNCTION("AVERAGE.WEIGHTED(N102:N120,F102:F120)"),0.0) -> 0

Sheet PINTEREST
E2: MUST READ: How to use? 1. Only click a checkbox when the topic on the left - is 100% completed 2. Don't check the box if you "just" checked the topic if it was applicable 3. The same topic can be in multiple stages (different levels of maturity) | F2: FR | G2: NL | H2: DE | I2: BE | J2: UK | K2: US | L2: IT | M2: Adaptation topics (V) | N2: Topics not finalized (X) | P2: Last updated at 06/02/2025 by Laman Guliyeva
F3: TRUE | G3: TRUE | H3: TRUE | I3: TRUE | J3: TRUE | K3: TRUE | L3: TRUE | M3: =(COUNTIF(F:L,TRUE))-COUNTIF(F3:L3,true) -> 0 | N3: =COUNTIF(F:L,FALSE) -> 413
B4: =N112 -> 0 | F4: =COUNTIF(F:F,TRUE)-1 -> 0 | G4: =COUNTIF(G:G,TRUE)-1 -> 0 | H4: =COUNTIF(H:H,TRUE)-1 -> 0 | I4: =COUNTIF(I:I,TRUE)-1 -> 0 | J4: =COUNTIF(J:J,TRUE)-1 -> 0 | K4: =COUNTIF(K:K,TRUE)-1 -> 0 | L4: =COUNTIF(L:L,TRUE)-1 -> 0
F6: =COUNTIF(F:F,FALSE) -> 59 | G6: =COUNTIF(G:G,FALSE) -> 59 | H6: =COUNTIF(H:H,FALSE) -> 59 | I6: =COUNTIF(I:I,FALSE) -> 59 | J6: =COUNTIF(J:J,FALSE) -> 59 | K6: =COUNTIF(K:K,FALSE) -> 59 | L6: =COUNTIF(L:L,FALSE) -> 59
C8: Maturity | D8: # | E8: Topics | F8: FR | G8: NL | H8: DE | I8: BE | J8: UK | K8: US | L8: IT | M8: Details | N8: Comments / Action
E9: If a topic is not relevant for the client - delete the checkbox | F9: Only check a box if the topic is fully integrated | M9: Explain what the issue is if not checked | N9: What would be the next steps to finalize the topic
B10: 1
C11: Campaign setup | F11: =IFERROR(__xludf.DUMMYFUNCTION("SPARKLINE(COUNTIF(F13:L23,TRUE),{""charttype"",""bar"";""max"",COUNTA(F13:L23);""color1"",""green""})"),"") | N11: =COUNTIF(F13:L23,TRUE)/COUNTA(F13:L23) -> 0 | P11: Commentbox for feedback
B13: =COUNTIF(F13:F14,TRUE)/COUNTA(F13:F14) -> 0 | C13: Basic | D13: 1 | E13: Campaign setup based on algorithms | F13: FALSE | G13: FALSE | H13: FALSE | I13: FALSE | J13: FALSE | K13: FALSE | L13: FALSE
D14: 2 | E14: Organized structure | F14: FALSE | G14: FALSE | H14: FALSE | I14: FALSE | J14: FALSE | K14: FALSE | L14: FALSE
B15: =COUNTIF(F15:F20,TRUE)/COUNTA(F15:F20) -> 0 | C15: Advanced | D15: 3 | E15: Simple structure (easy to understand) | F15: FALSE | G15: FALSE | H15: FALSE | I15: FALSE | J15: FALSE | K15: FALSE | L15: FALSE
D16: 4 | E16: Naming convention on campaign level | F16: FALSE | G16: FALSE | H16: FALSE | I16: FALSE | J16: FALSE | K16: FALSE | L16: FALSE
D17: 5 | E17: Naming convention on ad group level | F17: FALSE | G17: FALSE | H17: FALSE | I17: FALSE | J17: FALSE | K17: FALSE | L17: FALSE
D18: 6 | E18: Naming convention on ad level | F18: FALSE | G18: FALSE | H18: FALSE | I18: FALSE | J18: FALSE | K18: FALSE | L18: FALSE
D19: 7 | E19: Structure in line with offer on the website | F19: FALSE | G19: FALSE | H19: FALSE | I19: FALSE | J19: FALSE | K19: FALSE | L19: FALSE
D20: 8 | E20: Attribution windows | F20: FALSE | G20: FALSE | H20: FALSE | I20: FALSE | J20: FALSE | K20: FALSE | L20: FALSE
B21: =COUNTIF(F21,TRUE)/COUNTA(F21) -> 0 | C21: Expert | D21: 9 | E21: Pinterest Performance+ Campaigns | F21: FALSE | G21: FALSE | H21: FALSE | I21: FALSE | J21: FALSE | K21: FALSE | L21: FALSE
B22: =COUNTIF(F22:F23,TRUE)/COUNTA(F22:F23) -> 0 | C22: Champion | D22: 10 | E22: Build campaign setups via Excel or external tooling (e.g. Smartly / ByCape.io) | F22: FALSE | G22: FALSE | H22: FALSE | I22: FALSE | J22: FALSE | K22: FALSE | L22: FALSE
D23: 11 | E23: Have a naming convention tool integration (grasp) | F23: FALSE | G23: FALSE | H23: FALSE | I23: FALSE | J23: FALSE | K23: FALSE | L23: FALSE
B24: 2
C25: Audiences & targeting | F25: =IFERROR(__xludf.DUMMYFUNCTION("SPARKLINE(COUNTIF(F27:L40,TRUE),{""charttype"",""bar"";""max"",COUNTA(F27:L40);""color1"",""green""})"),"") | N25: =COUNTIF(F27:L40,TRUE)/COUNTA(F27:L40) -> 0
B27: =COUNTIF(F27:F30,TRUE)/COUNTA(F27:F30) -> 0 | C27: Basic | D27: 1 | E27: Language targeting | F27: FALSE | G27: FALSE | H27: FALSE | I27: FALSE | J27: FALSE | K27: FALSE | L27: FALSE
D28: 2 | E28: Age targeting | F28: FALSE | G28: FALSE | H28: FALSE | I28: FALSE | J28: FALSE | K28: FALSE | L28: FALSE
D29: 3 | E29: Demographic targeting | F29: FALSE | G29: FALSE | H29: FALSE | I29: FALSE | J29: FALSE | K29: FALSE | L29: FALSE
D30: 4 | E30: Dedicated campaign per market | F30: FALSE | G30: FALSE | H30: FALSE | I30: FALSE | J30: FALSE | K30: FALSE | L30: FALSE
B31: =COUNTIF(F31:F36,TRUE)/COUNTA(F31:F36) -> 0 | C31: Advanced | D31: 5 | E31: Is there an audience framework in place (and used for targeting?) | F31: FALSE | G31: FALSE | H31: FALSE | I31: FALSE | J31: FALSE | K31: FALSE | L31: FALSE
D32: 6 | E32: Is there a persona in place from client side (the ideal customer) | F32: FALSE | G32: FALSE | H32: FALSE | I32: FALSE | J32: FALSE | K32: FALSE | L32: FALSE
D33: 7 | E33: Pinterest Performance+ targeting activated | F33: FALSE | G33: FALSE | H33: FALSE | I33: FALSE | J33: FALSE | K33: FALSE | L33: FALSE
D34: 8 | E34: Device targeting | F34: FALSE | G34: FALSE | H34: FALSE | I34: FALSE | J34: FALSE | K34: FALSE | L34: FALSE
D35: 9 | E35: Retargeting audiences | F35: FALSE | G35: FALSE | H35: FALSE | I35: FALSE | J35: FALSE | K35: FALSE | L35: FALSE
D36: 10 | E36: Specific placement targeting | F36: FALSE | G36: FALSE | H36: FALSE | I36: FALSE | J36: FALSE | K36: FALSE | L36: FALSE
B37: =COUNTIF(F37:F39,TRUE)/COUNTA(F37:F39) -> 0 | C37: Expert | D37: 11 | E37: Inplatform audiences (followers, retarget video viewers) | F37: FALSE | G37: FALSE | H37: FALSE | I37: FALSE | J37: FALSE | K37: FALSE | L37: FALSE
D38: 12 | E38: Event based audiences (on pixel events) | F38: FALSE | G38: FALSE | H38: FALSE | I38: FALSE | J38: FALSE | K38: FALSE | L38: FALSE
D39: 14 | E39: Customer Match audiences | F39: FALSE | G39: FALSE | H39: FALSE | I39: FALSE | J39: FALSE | K39: FALSE | L39: FALSE
B40: =COUNTIF(F40,TRUE)/COUNTA(F40) -> 0 | C40: Champion | D40: 15 | E40: Customer Data Platform (CDP) integration | F40: FALSE | G40: FALSE | H40: FALSE | I40: FALSE | J40: FALSE | K40: FALSE | L40: FALSE
B41: 3
C42: Conversion & KPI | F42: =IFERROR(__xludf.DUMMYFUNCTION("SPARKLINE(COUNTIF(F44:L50,TRUE),{""charttype"",""bar"";""max"",COUNTA(F44:L50);""color1"",""green""})"),"") | N42: =COUNTIF(F44:L50,TRUE)/COUNTA(F44:L50) -> 0
B44: =COUNTIF(F44:F45,TRUE)/COUNTA(F44:F45) -> 0 | C44: Basic | D44: 1 | E44: General goal for Pinterest (total) | F44: FALSE | G44: FALSE | H44: FALSE | I44: FALSE | J44: FALSE | K44: FALSE | L44: FALSE
D45: 2 | E45: Monthly performance check in on KPI's | F45: FALSE | G45: FALSE | H45: FALSE | I45: FALSE | J45: FALSE | K45: FALSE | L45: FALSE
B46: =COUNTIF(F46:F48,TRUE)/COUNTA(F46:F48) -> 0 | C46: Advanced | D46: 3 | E46: A clear KPI framework with goals per funnel | F46: FALSE | G46: FALSE | H46: FALSE | I46: FALSE | J46: FALSE | K46: FALSE | L46: FALSE
D47: 4 | E47: The Pinterest Tag has been installed on the website | F47: FALSE | G47: FALSE | H47: FALSE | I47: FALSE | J47: FALSE | K47: FALSE | L47: FALSE
D48: 5 | E48: Classic events are made (view, add to cart, purchase) | F48: FALSE | G48: FALSE | H48: FALSE | I48: FALSE | J48: FALSE | K48: FALSE | L48: FALSE
B49: =COUNTIF(F49,TRUE)/COUNTA(F49) -> 0 | C49: Expert | D49: 6 | E49: Soft conversion have been added (such as a quality visit) | F49: FALSE | G49: FALSE | H49: FALSE | I49: FALSE | J49: FALSE | K49: FALSE | L49: FALSE
B50: =COUNTIF(F50,TRUE)/COUNTA(F50) -> 0 | C50: Champion | D50: 7 | E50: Conversion API setup | F50: FALSE | G50: FALSE | H50: FALSE | I50: FALSE | J50: FALSE | K50: FALSE | L50: FALSE
B51: 4
C52: Feeds & catalogues | F52: =IFERROR(__xludf.DUMMYFUNCTION("SPARKLINE(COUNTIF(F54:L60,TRUE),{""charttype"",""bar"";""max"",COUNTA(F54:L60);""color1"",""green""})"),"") | N52: =COUNTIF(F54:L60,TRUE)/COUNTA(F54:L60) -> 0
B54: =COUNTIF(F54:L54,TRUE)/COUNTA(F54:L54) -> 0 | C54: Basic | D54: 1 | E54: Catalogue is connected to Pinterest | F54: FALSE | G54: FALSE | H54: FALSE | I54: FALSE | J54: FALSE | K54: FALSE | L54: FALSE
B55: =COUNTIF(F55:L57,TRUE)/COUNTA(E55:L57) -> 0 | C55: Advanced | D55: 2 | E55: There are top performing product lists in use | F55: FALSE | G55: FALSE | H55: FALSE | I55: FALSE | J55: FALSE | K55: FALSE | L55: FALSE
D56: 3 | E56: There are seasonality lists available | F56: FALSE | G56: FALSE | H56: FALSE | I56: FALSE | J56: FALSE | K56: FALSE | L56: FALSE
D57: 4 | E57: Feedhealth 90% | F57: FALSE | G57: FALSE | H57: FALSE | I57: FALSE | J57: FALSE | K57: FALSE | L57: FALSE
B58: =COUNTIF(F58:L60,TRUE)/COUNTA(E58:L60) -> 0 | C58: Expert | D58: 5 | E58: Shopping weight has been added to catalogue | F58: FALSE | G58: FALSE | H58: FALSE | I58: FALSE | J58: FALSE | K58: FALSE | L58: FALSE
D59: 6 | E59: Client is working with a feedmanagementtool | F59: FALSE | G59: FALSE | H59: FALSE | I59: FALSE | J59: FALSE | K59: FALSE | L59: FALSE
D60: 7 | E60: Catalogue is used in the campaigns | F60: FALSE | G60: FALSE | H60: FALSE | I60: FALSE | J60: FALSE | K60: FALSE | L60: FALSE
B61: 5
C62: Creative & content | F62: =IFERROR(__xludf.DUMMYFUNCTION("SPARKLINE(COUNTIF(F64:L75,TRUE),{""charttype"",""bar"";""max"",COUNTA(F64:L75);""color1"",""green""})"),"") | N62: =COUNTIF(F64:L75,TRUE)/COUNTA(F64:L75) -> 0
B64: =COUNTIF(F64:F67,TRUE)/COUNTA(F64:F67) -> 0 | C64: Basic | D64: 1 | E64: Usage of image ads | F64: FALSE | G64: FALSE | H64: FALSE | I64: FALSE | J64: FALSE | K64: FALSE | L64: FALSE
D65: 2 | E65: Usage of video ads | F65: FALSE | G65: FALSE | H65: FALSE | I65: FALSE | J65: FALSE | K65: FALSE | L65: FALSE
D66: 3 | E66: Usage of call to actions | F66: FALSE | G66: FALSE | H66: FALSE | I66: FALSE | J66: FALSE | K66: FALSE | L66: FALSE
D67: 4 | E67: Usage of brand name in the image | F67: FALSE | G67: FALSE | H67: FALSE | I67: FALSE | J67: FALSE | K67: FALSE | L67: FALSE
D68: 5 | E68: Copy Length | F68: FALSE | G68: FALSE | H68: FALSE | I68: FALSE | J68: FALSE | K68: FALSE | L68: FALSE
B69: =COUNTIF(F69:F71,TRUE)/COUNTA(F69:F71) -> 0 | C69: Advanced | D69: 6 | E69: Rotation mode of creatives | F69: FALSE | G69: FALSE | H69: FALSE | I69: FALSE | J69: FALSE | K69: FALSE | L69: FALSE
D70: 7 | E70: Carousel ads | F70: FALSE | G70: FALSE | H70: FALSE | I70: FALSE | J70: FALSE | K70: FALSE | L70: FALSE
D71: 8 | E71: Idea/Quiz ads | F71: FALSE | G71: FALSE | H71: FALSE | I71: FALSE | J71: FALSE | K71: FALSE | L71: FALSE
B72: =COUNTIF(F72:F73,TRUE)/COUNTA(F72:F73) -> 0 | C72: Expert | D72: 9 | E72: Shopping Ads | F72: FALSE | G72: FALSE | H72: FALSE | I72: FALSE | J72: FALSE | K72: FALSE | L72: FALSE
D73: 10 | E73: Creative testing framework in place (based on e.g. 6 pillars of attention) | F73: FALSE | G73: FALSE | H73: FALSE | I73: FALSE | J73: FALSE | K73: FALSE | L73: FALSE
D74: 11 | E74: Premiere Spotlight Ads | F74: FALSE | G74: FALSE | H74: FALSE | I74: FALSE | J74: FALSE | K74: FALSE | L74: FALSE
B75: =COUNTIF(F74:F75,TRUE)/COUNTA(F74:F75) -> 0 | C75: Champion | D75: 12 | E75: Dynamic Creative Optimization (DCO) - via tooling or other options | F75: FALSE | G75: FALSE | H75: FALSE | I75: FALSE | J75: FALSE | K75: FALSE | L75: FALSE
B76: 6
C77: Reporting | F77: =IFERROR(__xludf.DUMMYFUNCTION("SPARKLINE(COUNTIF(F79:L86,TRUE),{""charttype"",""bar"";""max"",COUNTA(F79:L86);""color1"",""green""})"),"") | N77: =COUNTIF(F79:L86,TRUE)/COUNTA(F79:L86) -> 0
B79: =COUNTIF(F79,TRUE)/COUNTA(F79) -> 0 | C79: Basic | D79: 1 | E79: Gathering insights from campaign overview | F79: FALSE | G79: FALSE | H79: FALSE | I79: FALSE | J79: FALSE | K79: FALSE | L79: FALSE
B80: =COUNTIF(F80:F82,TRUE)/COUNTA(F80:F82) -> 0 | C80: Advanced | D80: 2 | E80: Pinterest & website insights (GA) | F80: FALSE | G80: FALSE | H80: FALSE | I80: FALSE | J80: FALSE | K80: FALSE | L80: FALSE
D81: 3 | E81: A/B testing in Pinterest | F81: FALSE | G81: FALSE | H81: FALSE | I81: FALSE | J81: FALSE | K81: FALSE | L81: FALSE
D82: 4 | E82: Monthly reporting meetings | F82: FALSE | G82: FALSE | H82: FALSE | I82: FALSE | J82: FALSE | K82: FALSE | L82: FALSE
B83: =COUNTIF(F83:F84,TRUE)/COUNTA(F83:F84) -> 0 | C83: Expert | D83: 5 | E83: Real time data dasboard | F83: FALSE | G83: FALSE | H83: FALSE | I83: FALSE | J83: FALSE | K83: FALSE | L83: FALSE
D84: 6 | E84: Consisted testing framework including hyptohesis | F84: FALSE | G84: FALSE | H84: FALSE | I84: FALSE | J84: FALSE | K84: FALSE | L84: FALSE
B85: =COUNTIF(F85:F86,TRUE)/COUNTA(F85:F86) -> 0 | C85: Champion | D85: 7 | E85: Brand lift studies | F85: FALSE | G85: FALSE | H85: FALSE | I85: FALSE | J85: FALSE | K85: FALSE | L85: FALSE
D86: 8 | E86: Marketing mix modeling | F86: FALSE | G86: FALSE | H86: FALSE | I86: FALSE | J86: FALSE | K86: FALSE | L86: FALSE
B88: SUMMARY (relevance to be adjusted to client needs) | P88: << in the column on the left you can decide if a certain topic is more or less important compared to others - to decide how important it is for the total score of a client Example given: Feed management is not always relevant for a company (B2B). You can give the relevance a score of 0 and it won't be calculated in the total average score Default setting: all topics at 100%
E90: Topic | F90: Topic relevance 0-100% | N90: Total score
C92: 1 | E92: =C11 -> Campaign setup | F92: 1 | M92: =IFERROR(__xludf.DUMMYFUNCTION("F11"),"") | N92: =N11 -> 0
C94: 2 | E94: =C25 -> Audiences & targeting | F94: 1 | M94: =IFERROR(__xludf.DUMMYFUNCTION("F25"),"") | N94: =N25 -> 0
C96: 3 | E96: =C42 -> Conversion & KPI | F96: 1 | M96: =IFERROR(__xludf.DUMMYFUNCTION("F42"),"") | N96: =N42 -> 0
C98: 4 | E98: =C52 -> Feeds & catalogues | F98: 1 | M98: =IFERROR(__xludf.DUMMYFUNCTION("F52"),"") | N98: =N52 -> 0
C100: 5 | E100: =C62 -> Creative & content | F100: 1 | M100: =IFERROR(__xludf.DUMMYFUNCTION("F62"),"") | N100: =N62 -> 0
C102: 6 | E102: =C77 -> Reporting | F102: 1 | M102: =IFERROR(__xludf.DUMMYFUNCTION("F77"),"") | N102: =N77 -> 0
C104: 7
C106: 8
C108: 9
C110: 10
M112: Total average weighted score | N112: =IFERROR(__xludf.DUMMYFUNCTION("AVERAGE.WEIGHTED(N92:N110,F92:F110)"),0.0) -> 0

Sheet TikTok
E2: MUST READ: How to use? 1. Only click a checkbox when the topic on the left - is 100% completed 2. Don't check the box if you "just" checked the topic if it was applicable 3. The same topic can be in multiple stages (different levels of maturity) | F2: FR | G2: NL | H2: DE | I2: BE | J2: UK | K2: US | L2: IT | M2: Adaptation topics (V) | N2: Topics not finalized (X) | P2: Last updated at 15/12/2025 by Laman Guliyeva
F3: TRUE | G3: TRUE | H3: TRUE | I3: TRUE | J3: TRUE | K3: TRUE | L3: TRUE | M3: =(COUNTIF(F:L,TRUE))-COUNTIF(F3:L3,true) -> 0 | N3: =COUNTIF(F:L,FALSE) -> 420
B4: =N109 -> 0 | F4: =COUNTIF(F:F,TRUE)-1 -> 0 | G4: =COUNTIF(G:G,TRUE)-1 -> 0 | H4: =COUNTIF(H:H,TRUE)-1 -> 0 | I4: =COUNTIF(I:I,TRUE)-1 -> 0 | J4: =COUNTIF(J:J,TRUE)-1 -> 0 | K4: =COUNTIF(K:K,TRUE)-1 -> 0 | L4: =COUNTIF(L:L,TRUE)-1 -> 0
F6: =COUNTIF(F:F,FALSE) -> 60 | G6: =COUNTIF(G:G,FALSE) -> 60 | H6: =COUNTIF(H:H,FALSE) -> 60 | I6: =COUNTIF(I:I,FALSE) -> 60 | J6: =COUNTIF(J:J,FALSE) -> 60 | K6: =COUNTIF(K:K,FALSE) -> 60 | L6: =COUNTIF(L:L,FALSE) -> 60
C8: Maturity | D8: # | E8: Topics | F8: FR | G8: NL | H8: DE | I8: BE | J8: UK | K8: US | L8: IT | M8: Details | N8: Comments / Action
E9: If a topic is not relevant for the client - delete the checkbox | F9: Only check a box if the topic is fully integrated | M9: Explain what the issue is if not checked | N9: What would be the next steps to finalize the topic
B10: 1
C11: Campaign setup | F11: =IFERROR(__xludf.DUMMYFUNCTION("SPARKLINE(COUNTIF(F13:L24,TRUE),{""charttype"",""bar"";""max"",COUNTA(F13:L24);""color1"",""green""})"),"") | N11: =COUNTIF(F13:L24,TRUE)/COUNTA(F13:L24) -> 0 | P11: Commentbox for feedback
B13: =COUNTIF(F13:L14,TRUE)/COUNTA(F13:L14) -> 0 | C13: Basic | D13: 1 | E13: Campaign setup based on algorithms | F13: FALSE | G13: FALSE | H13: FALSE | I13: FALSE | J13: FALSE | K13: FALSE | L13: FALSE
D14: 2 | E14: Organized structure | F14: FALSE | G14: FALSE | H14: FALSE | I14: FALSE | J14: FALSE | K14: FALSE | L14: FALSE
B15: =COUNTIF(F15:L20,TRUE)/COUNTA(J15:L20) -> 0 | C15: Advanced | D15: 3 | E15: Simple structure (easy to understand) | F15: FALSE | G15: FALSE | H15: FALSE | I15: FALSE | J15: FALSE | K15: FALSE | L15: FALSE
D16: 4 | E16: Naming convention on campaign level | F16: FALSE | G16: FALSE | H16: FALSE | I16: FALSE | J16: FALSE | K16: FALSE | L16: FALSE
D17: 5 | E17: Naming convention on ad group level | F17: FALSE | G17: FALSE | H17: FALSE | I17: FALSE | J17: FALSE | K17: FALSE | L17: FALSE
D18: 6 | E18: Naming convention on ad level | F18: FALSE | G18: FALSE | H18: FALSE | I18: FALSE | J18: FALSE | K18: FALSE | L18: FALSE
D19: 7 | E19: Structure in line with offer on the website | F19: FALSE | G19: FALSE | H19: FALSE | I19: FALSE | J19: FALSE | K19: FALSE | L19: FALSE
D20: 8 | E20: Attribution windows | F20: FALSE | G20: FALSE | H20: FALSE | I20: FALSE | J20: FALSE | K20: FALSE | L20: FALSE
B21: =COUNTIF(F21:JL22,TRUE)/COUNTA(F21:L22) -> 0 | C21: Expert | D21: 9 | E21: Smart+ Campaign | F21: FALSE | G21: FALSE | H21: FALSE | I21: FALSE | J21: FALSE | K21: FALSE | L21: FALSE
D22: 10 | E22: Search Campaign | F22: FALSE | G22: FALSE | H22: FALSE | I22: FALSE | J22: FALSE | K22: FALSE | L22: FALSE
B23: =COUNTIF(F23:L24,TRUE)/COUNTA(F23:L24) -> 0 | C23: Champion | D23: 11 | E23: Build campaign setups via Excel or external tooling | F23: FALSE | G23: FALSE | H23: FALSE | I23: FALSE | J23: FALSE | K23: FALSE | L23: FALSE
D24: 12 | E24: Have a naming convention tool integration (grasp) | F24: FALSE | G24: FALSE | H24: FALSE | I24: FALSE | J24: FALSE | K24: FALSE | L24: FALSE
B25: 2
C26: Audiences & targeting | F26: =IFERROR(__xludf.DUMMYFUNCTION("SPARKLINE(COUNTIF(F28:L44,TRUE),{""charttype"",""bar"";""max"",COUNTA(F28:L44);""color1"",""green""})"),"") | N26: =COUNTIF(F28:L44,TRUE)/COUNTA(F28:L44) -> 0
B28: =COUNTIF(F28:L33,TRUE)/COUNTA(F28:L33) -> 0 | C28: Basic | D28: 1 | E28: Language targeting | F28: FALSE | G28: FALSE | H28: FALSE | I28: FALSE | J28: FALSE | K28: FALSE | L28: FALSE
D29: 2 | E29: Age targeting | F29: FALSE | G29: FALSE | H29: FALSE | I29: FALSE | J29: FALSE | K29: FALSE | L29: FALSE
D30: 3 | E30: Demographic targeting | F30: FALSE | G30: FALSE | H30: FALSE | I30: FALSE | J30: FALSE | K30: FALSE | L30: FALSE
D31: 4 | E31: Dedicated campaign per market | F31: FALSE | G31: FALSE | H31: FALSE | I31: FALSE | J31: FALSE | K31: FALSE | L31: FALSE
D32: 5 | E32: Is Video download/sharing allowed? | F32: FALSE | G32: FALSE | H32: FALSE | I32: FALSE | J32: FALSE | K32: FALSE | L32: FALSE
D33: 6 | E33: User Comments allowed | F33: FALSE | G33: FALSE | H33: FALSE | I33: FALSE | J33: FALSE | K33: FALSE | L33: FALSE
B34: =COUNTIF(F34:L39,TRUE)/COUNTA(F34:L39) -> 0 | C34: Advanced | D34: 7 | E34: Is there an audience framework in place (and used for targeting?) | F34: FALSE | G34: FALSE | H34: FALSE | I34: FALSE | J34: FALSE | K34: FALSE | L34: FALSE
D35: 8 | E35: Is there a persona in place from client side (the ideal customer) | F35: FALSE | G35: FALSE | H35: FALSE | I35: FALSE | J35: FALSE | K35: FALSE | L35: FALSE
D36: 9 | E36: Device targeting | F36: FALSE | G36: FALSE | H36: FALSE | I36: FALSE | J36: FALSE | K36: FALSE | L36: FALSE
D37: 10 | E37: Retargeting audiences | F37: FALSE | G37: FALSE | H37: FALSE | I37: FALSE | J37: FALSE | K37: FALSE | L37: FALSE
D38: 11 | E38: Specific placement targeting | F38: FALSE | G38: FALSE | H38: FALSE | I38: FALSE | J38: FALSE | K38: FALSE | L38: FALSE
D39: 12 | E39: Inplatform audiences (followers, retarget video viewers) | F39: FALSE | G39: FALSE | H39: FALSE | I39: FALSE | J39: FALSE | K39: FALSE | L39: FALSE
B40: =COUNTIF(F40:L42,TRUE)/COUNTA(F40:L42) -> 0 | C40: Expert | D40: 13 | E40: Event based audiences (on pixel events) | F40: FALSE | G40: FALSE | H40: FALSE | I40: FALSE | J40: FALSE | K40: FALSE | L40: FALSE
D41: 14 | E41: Bid control added | F41: FALSE | G41: FALSE | H41: FALSE | I41: FALSE | J41: FALSE | K41: FALSE | L41: FALSE
D42: 15 | E42: Customer List audiences | F42: FALSE | G42: FALSE | H42: FALSE | I42: FALSE | J42: FALSE | K42: FALSE | L42: FALSE
B43: =COUNTIF(F43:L44,TRUE)/COUNTA(F43:L44) -> 0 | C43: Champion | D43: 16 | E43: Customer Data Platform (CDP) integration | F43: FALSE | G43: FALSE | H43: FALSE | I43: FALSE | J43: FALSE | K43: FALSE | L43: FALSE
D44: 17 | E44: Comments Management | F44: FALSE | G44: FALSE | H44: FALSE | I44: FALSE | J44: FALSE | K44: FALSE | L44: FALSE
B45: 3
C46: Conversion & KPI | F46: =IFERROR(__xludf.DUMMYFUNCTION("SPARKLINE(COUNTIF(F48:L54,TRUE),{""charttype"",""bar"";""max"",COUNTA(F48:L54);""color1"",""green""})"),"") | N46: =COUNTIF(F48:L54,TRUE)/COUNTA(F48:L54) -> 0
B48: =COUNTIF(F48:L49,TRUE)/COUNTA(F48:L49) -> 0 | C48: Basic | D48: 1 | E48: General goal for TikTok (total) | F48: FALSE | G48: FALSE | H48: FALSE | I48: FALSE | J48: FALSE | K48: FALSE | L48: FALSE
D49: 2 | E49: Monthly performance check in on KPI's | F49: FALSE | G49: FALSE | H49: FALSE | I49: FALSE | J49: FALSE | K49: FALSE | L49: FALSE
B50: =COUNTIF(F50:L52,TRUE)/COUNTA(F50:L52) -> 0 | C50: Advanced | D50: 3 | E50: A clear KPI framework with goals per funnel | F50: FALSE | G50: FALSE | H50: FALSE | I50: FALSE | J50: FALSE | K50: FALSE | L50: FALSE
D51: 4 | E51: The pixel has been installed on the website | F51: FALSE | G51: FALSE | H51: FALSE | I51: FALSE | J51: FALSE | K51: FALSE | L51: FALSE
D52: 5 | E52: Classic events are made (view, add to cart, purchase) | F52: FALSE | G52: FALSE | H52: FALSE | I52: FALSE | J52: FALSE | K52: FALSE | L52: FALSE
B53: =COUNTIF(F53:L53,TRUE)/COUNTA(F53:L53) -> 0 | C53: Expert | D53: 6 | E53: Soft conversion have been added (such as a quality visit) | F53: FALSE | G53: FALSE | H53: FALSE | I53: FALSE | J53: FALSE | K53: FALSE | L53: FALSE
B54: =COUNTIF(F54:L54,TRUE)/COUNTA(F54:L54) -> 0 | C54: Champion | D54: 7 | E54: Events API setup | F54: FALSE | G54: FALSE | H54: FALSE | I54: FALSE | J54: FALSE | K54: FALSE | L54: FALSE
B55: 4
C56: Creative & content | F56: =IFERROR(__xludf.DUMMYFUNCTION("SPARKLINE(COUNTIF(F58:L72,TRUE),{""charttype"",""bar"";""max"",COUNTA(F58:L72);""color1"",""green""})"),"") | N56: =COUNTIF(F58:L72,TRUE)/COUNTA(F58:L72) -> 0
B58: =COUNTIF(F58:L62,TRUE)/COUNTA(F58:L62) -> 0 | C58: Basic | D58: 1 | E58: Usage of image ads | F58: FALSE | G58: FALSE | H58: FALSE | I58: FALSE | J58: FALSE | K58: FALSE | L58: FALSE
D59: 2 | E59: Usage of video ads | F59: FALSE | G59: FALSE | H59: FALSE | I59: FALSE | J59: FALSE | K59: FALSE | L59: FALSE
D60: 3 | E60: Usage of carousel ads | F60: FALSE | G60: FALSE | H60: FALSE | I60: FALSE | J60: FALSE | K60: FALSE | L60: FALSE
D61: 4 | E61: Usage of call to actions | F61: FALSE | G61: FALSE | H61: FALSE | I61: FALSE | J61: FALSE | K61: FALSE | L61: FALSE
D62: 5 | E62: Usage of brand name in the image, videos | F62: FALSE | G62: FALSE | H62: FALSE | I62: FALSE | J62: FALSE | K62: FALSE | L62: FALSE
D63: 6 | E63: TikTok accout connected | F63: FALSE | G63: FALSE | H63: FALSE | I63: FALSE | J63: FALSE | K63: FALSE | L63: FALSE
B64: =COUNTIF(F64:L66,TRUE)/COUNTA(F64:L66) -> 0 | C64: Advanced | D64: 7 | E64: Rotation mode of creatives | F64: FALSE | G64: FALSE | H64: FALSE | I64: FALSE | J64: FALSE | K64: FALSE | L64: FALSE
D65: 8 | E65: Copy length | F65: FALSE | G65: FALSE | H65: FALSE | I65: FALSE | J65: FALSE | K65: FALSE | L65: FALSE
D66: 9 | E66: Music added to the image ads | F66: FALSE | G66: FALSE | H66: FALSE | I66: FALSE | J66: FALSE | K66: FALSE | L66: FALSE
B67: =COUNTIF(F67:L70,TRUE)/COUNTA(F67:L70) -> 0 | C67: Expert | D67: 11 | E67: Search ads | F67: FALSE | G67: FALSE | H67: FALSE | I67: FALSE | J67: FALSE | K67: FALSE | L67: FALSE
D68: 12 | E68: Smart Creatives Automation | F68: FALSE | G68: FALSE | H68: FALSE | I68: FALSE | J68: FALSE | K68: FALSE | L68: FALSE
D69: 13 | E69: Product Information Tagged | F69: FALSE | G69: FALSE | H69: FALSE | I69: FALSE | J69: FALSE | K69: FALSE | L69: FALSE
D70: 14 | E70: Carousel ads automated (smart covers) | F70: FALSE | G70: FALSE | H70: FALSE | I70: FALSE | J70: FALSE | K70: FALSE | L70: FALSE
B71: =COUNTIF(F71:L72,TRUE)/COUNTA(F71:L72) -> 0 | C71: Champion | D71: 15 | E71: Dynamic Creative Optimization (DCO) - via tooling or other options | F71: FALSE | G71: FALSE | H71: FALSE | I71: FALSE | J71: FALSE | K71: FALSE | L71: FALSE
D72: 16 | E72: Content Ads (TopView, Branded Hashtags, etc) | F72: FALSE | G72: FALSE | H72: FALSE | I72: FALSE | J72: FALSE | K72: FALSE | L72: FALSE
B73: 5
C74: Reporting | F74: =IFERROR(__xludf.DUMMYFUNCTION("SPARKLINE(COUNTIF(F76:L84,TRUE),{""charttype"",""bar"";""max"",COUNTA(F76:L84);""color1"",""green""})"),"") | N74: =COUNTIF(F76:L84,TRUE)/COUNTA(F76:L84) -> 0
B76: =COUNTIF(F76:L76,TRUE)/COUNTA(F76:L76) -> 0 | C76: Basic | D76: 1 | E76: Gathering insights from campaign overview | F76: FALSE | G76: FALSE | H76: FALSE | I76: FALSE | J76: FALSE | K76: FALSE | L76: FALSE
B77: =COUNTIF(F77:L80,TRUE)/COUNTA(F77:L80) -> 0 | C77: Advanced | D77: 2 | E77: Pre-defined TikTok reports per funnel | F77: FALSE | G77: FALSE | H77: FALSE | I77: FALSE | J77: FALSE | K77: FALSE | L77: FALSE
D78: 3 | E78: TikTok & website insights (GA) | F78: FALSE | G78: FALSE | H78: FALSE | I78: FALSE | J78: FALSE | K78: FALSE | L78: FALSE
D79: 4 | E79: Split testing in TikTok (experiments) | F79: FALSE | G79: FALSE | H79: FALSE | I79: FALSE | J79: FALSE | K79: FALSE | L79: FALSE
D80: 5 | E80: Monthly reporting meetings | F80: FALSE | G80: FALSE | H80: FALSE | I80: FALSE | J80: FALSE | K80: FALSE | L80: FALSE
B81: =COUNTIF(F81:L82,TRUE)/COUNTA(F81:L82) -> 0 | C81: Expert | D81: 6 | E81: Real time data dasboard | F81: FALSE | G81: FALSE | H81: FALSE | I81: FALSE | J81: FALSE | K81: FALSE | L81: FALSE
D82: 7 | E82: Consisted testing framework including hyptohesis | F82: FALSE | G82: FALSE | H82: FALSE | I82: FALSE | J82: FALSE | K82: FALSE | L82: FALSE
B83: =COUNTIF(F83:L84,TRUE)/COUNTA(F83:L84) -> 0 | C83: Champion | D83: 8 | E83: Brand lift studies | F83: FALSE | G83: FALSE | H83: FALSE | I83: FALSE | J83: FALSE | K83: FALSE | L83: FALSE
D84: 9 | E84: Marketing mix modeling | F84: FALSE | G84: FALSE | H84: FALSE | I84: FALSE | J84: FALSE | K84: FALSE | L84: FALSE
B86: SUMMARY (relevance to be adjusted to client needs) | P86: << in the column on the left you can decide if a certain topic is more or less important compared to others - to decide how important it is for the total score of a client Example given: Feed management is not always relevant for a company (B2B). You can give the relevance a score of 0 and it won't be calculated in the total average score Default setting: all topics at 100%
E88: Topic | F88: Topic relevance 0-100% | N88: Total score
C90: 1 | E90: =C11 -> Campaign setup | F90: 1 | M90: =IFERROR(__xludf.DUMMYFUNCTION("F11"),"") | N90: =N11 -> 0
C92: 2 | E92: =C26 -> Audiences & targeting | F92: 1 | M92: =IFERROR(__xludf.DUMMYFUNCTION("F26"),"") | N92: =N26 -> 0
C94: 3 | E94: =C46 -> Conversion & KPI | F94: 1 | M94: =IFERROR(__xludf.DUMMYFUNCTION("F46"),"") | N94: =N46 -> 0
C97: 4 | E97: =C56 -> Creative & content | F97: 1 | M97: =IFERROR(__xludf.DUMMYFUNCTION("F56"),"") | N97: =N56 -> 0
C99: 5 | E99: =C74 -> Reporting | F99: 1 | M99: =IFERROR(__xludf.DUMMYFUNCTION("F74"),"") | N99: =N74 -> 0
C101: 7
C103: 8
C105: 9
C107: 10
M109: Total average weighted score | N109: =IFERROR(__xludf.DUMMYFUNCTION("AVERAGE.WEIGHTED(N90:N107,F90:F107)"),0.0) -> 0

Sheet Snapchat
E2: MUST READ: How to use? 1. Only click a checkbox when the topic on the left - is 100% completed 2. Don't check the box if you "just" checked the topic if it was applicable 3. The same topic can be in multiple stages (different levels of maturity) | F2: FR | G2: NL | H2: DE | I2: BE | J2: UK | K2: US | L2: IT | M2: Adaptation topics (V) | N2: Topics not finalized (X) | P2: Last updated at 15/12/2025 by Laman Guliyeva
F3: TRUE | G3: TRUE | H3: TRUE | I3: TRUE | J3: TRUE | K3: TRUE | L3: TRUE | M3: =(COUNTIF(F:L,TRUE))-COUNTIF(F3:L3,true) -> 0 | N3: =COUNTIF(F:L,FALSE) -> 413
B4: =N111 -> 0 | F4: =COUNTIF(F:F,TRUE)-1 -> 0 | G4: =COUNTIF(G:G,TRUE)-1 -> 0 | H4: =COUNTIF(H:H,TRUE)-1 -> 0 | I4: =COUNTIF(I:I,TRUE)-1 -> 0 | J4: =COUNTIF(J:J,TRUE)-1 -> 0 | K4: =COUNTIF(K:K,TRUE)-1 -> 0 | L4: =COUNTIF(L:L,TRUE)-1 -> 0
F6: =COUNTIF(F:F,FALSE) -> 59 | G6: =COUNTIF(G:G,FALSE) -> 59 | H6: =COUNTIF(H:H,FALSE) -> 59 | I6: =COUNTIF(I:I,FALSE) -> 59 | J6: =COUNTIF(J:J,FALSE) -> 59 | K6: =COUNTIF(K:K,FALSE) -> 59 | L6: =COUNTIF(L:L,FALSE) -> 59
C8: Maturity | D8: # | E8: Topics | F8: FR | G8: NL | H8: DE | I8: BE | J8: UK | K8: US | L8: IT | M8: Details | N8: Comments / Action
E9: If a topic is not relevant for the client - delete the checkbox | F9: Only check a box if the topic is fully integrated | M9: Explain what the issue is if not checked | N9: What would be the next steps to finalize the topic
B10: 1
C11: Campaign setup | F11: =IFERROR(__xludf.DUMMYFUNCTION("SPARKLINE(COUNTIF(F13:L23,TRUE),{""charttype"",""bar"";""max"",COUNTA(F13:L23);""color1"",""green""})"),"") | N11: =COUNTIF(F13:L23,TRUE)/COUNTA(F13:L23) -> 0 | P11: Commentbox for feedback
B13: =COUNTIF(F13:L14,TRUE)/COUNTA(F13:L14) -> 0 | C13: Basic | D13: 1 | E13: Campaign setup based on algorithms | F13: FALSE | G13: FALSE | H13: FALSE | I13: FALSE | J13: FALSE | K13: FALSE | L13: FALSE
D14: 2 | E14: Organized structure | F14: FALSE | G14: FALSE | H14: FALSE | I14: FALSE | J14: FALSE | K14: FALSE | L14: FALSE
B15: =COUNTIF(F15:L20,TRUE)/COUNTA(F15:L20) -> 0 | C15: Advanced | D15: 3 | E15: Simple structure (easy to understand) | F15: FALSE | G15: FALSE | H15: FALSE | I15: FALSE | J15: FALSE | K15: FALSE | L15: FALSE
D16: 4 | E16: Naming convention on campaign level | F16: FALSE | G16: FALSE | H16: FALSE | I16: FALSE | J16: FALSE | K16: FALSE | L16: FALSE
D17: 5 | E17: Naming convention on ad group level | F17: FALSE | G17: FALSE | H17: FALSE | I17: FALSE | J17: FALSE | K17: FALSE | L17: FALSE
D18: 6 | E18: Naming convention on ad level | F18: FALSE | G18: FALSE | H18: FALSE | I18: FALSE | J18: FALSE | K18: FALSE | L18: FALSE
D19: 7 | E19: Structure in line with offer on the website | F19: FALSE | G19: FALSE | H19: FALSE | I19: FALSE | J19: FALSE | K19: FALSE | L19: FALSE
D20: 8 | E20: Attribution windows | F20: FALSE | G20: FALSE | H20: FALSE | I20: FALSE | J20: FALSE | K20: FALSE | L20: FALSE
B21: =COUNTIF(F21:L21,TRUE)/COUNTA(F21:L21) -> 0 | C21: Expert | D21: 9 | E21: Automatic Page View Campaign | F21: FALSE | G21: FALSE | H21: FALSE | I21: FALSE | J21: FALSE | K21: FALSE | L21: FALSE
B22: =COUNTIF(F22:L23,TRUE)/COUNTA(F22:L23) -> 0 | C22: Champion | D22: 10 | E22: Build campaign setups via Excel or external tooling | F22: FALSE | G22: FALSE | H22: FALSE | I22: FALSE | J22: FALSE | K22: FALSE | L22: FALSE
D23: 11 | E23: Have a naming convention tool integration (grasp) | F23: FALSE | G23: FALSE | H23: FALSE | I23: FALSE | J23: FALSE | K23: FALSE | L23: FALSE
B24: 2
C25: Audiences & targeting | F25: =IFERROR(__xludf.DUMMYFUNCTION("SPARKLINE(COUNTIF(F27:L41,TRUE),{""charttype"",""bar"";""max"",COUNTA(F27:L41);""color1"",""green""})"),"") | N25: =COUNTIF(F27:L41,TRUE)/COUNTA(F27:L41) -> 0
B27: =COUNTIF(F27:L30,TRUE)/COUNTA(F27:L30) -> 0 | C27: Basic | D27: 1 | E27: Language targeting | F27: FALSE | G27: FALSE | H27: FALSE | I27: FALSE | J27: FALSE | K27: FALSE | L27: FALSE
D28: 2 | E28: Age targeting | F28: FALSE | G28: FALSE | H28: FALSE | I28: FALSE | J28: FALSE | K28: FALSE | L28: FALSE
D29: 3 | E29: Demographic targeting | F29: FALSE | G29: FALSE | H29: FALSE | I29: FALSE | J29: FALSE | K29: FALSE | L29: FALSE
D30: 4 | E30: Dedicated campaign per market | F30: FALSE | G30: FALSE | H30: FALSE | I30: FALSE | J30: FALSE | K30: FALSE | L30: FALSE
B31: =COUNTIF(F31:L36,TRUE)/COUNTA(F31:L36) -> 0 | C31: Advanced | D31: 5 | E31: Is there an audience framework in place (and used for targeting?) | F31: FALSE | G31: FALSE | H31: FALSE | I31: FALSE | J31: FALSE | K31: FALSE | L31: FALSE
D32: 6 | E32: Is there a persona in place from client side (the ideal customer) | F32: FALSE | G32: FALSE | H32: FALSE | I32: FALSE | J32: FALSE | K32: FALSE | L32: FALSE
D33: 7 | E33: Device targeting | F33: FALSE | G33: FALSE | H33: FALSE | I33: FALSE | J33: FALSE | K33: FALSE | L33: FALSE
D34: 8 | E34: Retargeting audiences | F34: FALSE | G34: FALSE | H34: FALSE | I34: FALSE | J34: FALSE | K34: FALSE | L34: FALSE
D35: 9 | E35: Specific placement targeting | F35: FALSE | G35: FALSE | H35: FALSE | I35: FALSE | J35: FALSE | K35: FALSE | L35: FALSE
D36: 10 | E36: Inplatform audiences (followers, story viewers, retarget video viewers) | F36: FALSE | G36: FALSE | H36: FALSE | I36: FALSE | J36: FALSE | K36: FALSE | L36: FALSE
B37: =COUNTIF(F37:L40,TRUE)/COUNTA(F37:L40) -> 0 | C37: Expert | D37: 11 | E37: Event based audiences (on pixel events) | F37: FALSE | G37: FALSE | H37: FALSE | I37: FALSE | J37: FALSE | K37: FALSE | L37: FALSE
D38: 12 | E38: Smart Targeting On | F38: FALSE | G38: FALSE | H38: FALSE | I38: FALSE | J38: FALSE | K38: FALSE | L38: FALSE
D39: 13 | E39: Bid control added | F39: FALSE | G39: FALSE | H39: FALSE | I39: FALSE | J39: FALSE | K39: FALSE | L39: FALSE
D40: 14 | E40: Customer List audiences | F40: FALSE | G40: FALSE | H40: FALSE | I40: FALSE | J40: FALSE | K40: FALSE | L40: FALSE
B41: =COUNTIF(F41:L41,TRUE)/COUNTA(F41:L41) -> 0 | C41: Champion | D41: 15 | E41: Customer Data Platform (CDP) integration | F41: FALSE | G41: FALSE | H41: FALSE | I41: FALSE | J41: FALSE | K41: FALSE | L41: FALSE
B42: 3
C43: Conversion & KPI | F43: =IFERROR(__xludf.DUMMYFUNCTION("SPARKLINE(COUNTIF(F45:L51,TRUE),{""charttype"",""bar"";""max"",COUNTA(F45:L51);""color1"",""green""})"),"") | N43: =COUNTIF(F45:L51,TRUE)/COUNTA(F45:L51) -> 0
B45: =COUNTIF(F45:L46,TRUE)/COUNTA(F45:L46) -> 0 | C45: Basic | D45: 1 | E45: General goal for Snapchat (total) | F45: FALSE | G45: FALSE | H45: FALSE | I45: FALSE | J45: FALSE | K45: FALSE | L45: FALSE
D46: 2 | E46: Monthly performance check in on KPI's | F46: FALSE | G46: FALSE | H46: FALSE | I46: FALSE | J46: FALSE | K46: FALSE | L46: FALSE
B47: =COUNTIF(F47:L49,TRUE)/COUNTA(F47:L49) -> 0 | C47: Advanced | D47: 3 | E47: A clear KPI framework with goals per funnel | F47: FALSE | G47: FALSE | H47: FALSE | I47: FALSE | J47: FALSE | K47: FALSE | L47: FALSE
D48: 4 | E48: The pixel has been installed on the website | F48: FALSE | G48: FALSE | H48: FALSE | I48: FALSE | J48: FALSE | K48: FALSE | L48: FALSE
D49: 5 | E49: Classic events are made (view, add to cart, purchase) | F49: FALSE | G49: FALSE | H49: FALSE | I49: FALSE | J49: FALSE | K49: FALSE | L49: FALSE
B50: =COUNTIF(F50:L50,TRUE)/COUNTA(F50:L50) -> 0 | C50: Expert | D50: 6 | E50: Soft conversion have been added (such as a quality visit) | F50: FALSE | G50: FALSE | H50: FALSE | I50: FALSE | J50: FALSE | K50: FALSE | L50: FALSE
B51: =COUNTIF(F51:L51,TRUE)/COUNTA(F51:L51) -> 0 | C51: Champion | D51: 7 | E51: Conversion API setup | F51: FALSE | G51: FALSE | H51: FALSE | I51: FALSE | J51: FALSE | K51: FALSE | L51: FALSE
B52: 4
C53: Feeds & catalogues | F53: =IFERROR(__xludf.DUMMYFUNCTION("SPARKLINE(COUNTIF(F55:L61,TRUE),{""charttype"",""bar"";""max"",COUNTA(F55:L61);""color1"",""green""})"),"") | N53: =COUNTIF(F55:L61,TRUE)/COUNTA(F55:L61) -> 0
B55: =COUNTIF(F55:L55,TRUE)/COUNTA(F55:L55) -> 0 | C55: Basic | D55: 1 | E55: Catalogue is connected to Pinterest | F55: FALSE | G55: FALSE | H55: FALSE | I55: FALSE | J55: FALSE | K55: FALSE | L55: FALSE
B56: =COUNTIF(F56:L59,TRUE)/COUNTA(E56:L59) -> 0 | C56: Advanced | D56: 2 | E56: There are top performing product lists in use | F56: FALSE | G56: FALSE | H56: FALSE | I56: FALSE | J56: FALSE | K56: FALSE | L56: FALSE
D57: 3 | E57: There are seasonality lists available | F57: FALSE | G57: FALSE | H57: FALSE | I57: FALSE | J57: FALSE | K57: FALSE | L57: FALSE
D58: 5 | E58: Feedhealth 90% | F58: FALSE | G58: FALSE | H58: FALSE | I58: FALSE | J58: FALSE | K58: FALSE | L58: FALSE
D59: 6 | E59: Shopping weight has been added to catalogue | F59: FALSE | G59: FALSE | H59: FALSE | I59: FALSE | J59: FALSE | K59: FALSE | L59: FALSE
B60: =COUNTIF(F60:L61,TRUE)/COUNTA(E60:L61) -> 0 | C60: Expert | D60: 7 | E60: Client is working with a feedmanagementtool | F60: FALSE | G60: FALSE | H60: FALSE | I60: FALSE | J60: FALSE | K60: FALSE | L60: FALSE
D61: 8 | E61: Catalogue is used in the campaigns | F61: FALSE | G61: FALSE | H61: FALSE | I61: FALSE | J61: FALSE | K61: FALSE | L61: FALSE
B62: 4
C63: Creative & content | F63: =IFERROR(__xludf.DUMMYFUNCTION("SPARKLINE(COUNTIF(F65:L75,TRUE),{""charttype"",""bar"";""max"",COUNTA(F65:L75);""color1"",""green""})"),"") | N63: =COUNTIF(F65:L75,TRUE)/COUNTA(F65:L75) -> 0
B65: =COUNTIF(F65:L69,TRUE)/COUNTA(F65:L69) -> 0 | C65: Basic | D65: 1 | E65: Usage of image ads | F65: FALSE | G65: FALSE | H65: FALSE | I65: FALSE | J65: FALSE | K65: FALSE | L65: FALSE
D66: 2 | E66: Usage of video ads | F66: FALSE | G66: FALSE | H66: FALSE | I66: FALSE | J66: FALSE | K66: FALSE | L66: FALSE
D67: 3 | E67: Usage of story ads | F67: FALSE | G67: FALSE | H67: FALSE | I67: FALSE | J67: FALSE | K67: FALSE | L67: FALSE
D68: 4 | E68: Usage of call to actions | F68: FALSE | G68: FALSE | H68: FALSE | I68: FALSE | J68: FALSE | K68: FALSE | L68: FALSE
D69: 5 | E69: Usage of brand name in the image, videos | F69: FALSE | G69: FALSE | H69: FALSE | I69: FALSE | J69: FALSE | K69: FALSE | L69: FALSE
B70: =COUNTIF(F70:L72,TRUE)/COUNTA(F70:L72) -> 0 | C70: Advanced | D70: 6 | E70: Rotation mode of creatives | F70: FALSE | G70: FALSE | H70: FALSE | I70: FALSE | J70: FALSE | K70: FALSE | L70: FALSE
D71: 7 | E71: Copy length (Brand: Up to 25 characters with spaces, Headline: Up to 34 characters with spaces) | F71: FALSE | G71: FALSE | H71: FALSE | I71: FALSE | J71: FALSE | K71: FALSE | L71: FALSE
D72: 8 | E72: Music added to the ads | F72: FALSE | G72: FALSE | H72: FALSE | I72: FALSE | J72: FALSE | K72: FALSE | L72: FALSE
B73: =COUNTIF(F73:L74,TRUE)/COUNTA(F73:L74) -> 0 | C73: Expert | D73: 9 | E73: Collection ads | F73: FALSE | G73: FALSE | H73: FALSE | I73: FALSE | J73: FALSE | K73: FALSE | L73: FALSE
D74: 10 | E74: Commercial ads | F74: FALSE | G74: FALSE | H74: FALSE | I74: FALSE | J74: FALSE | K74: FALSE | L74: FALSE
B75: =COUNTIF(F75:L75,TRUE)/COUNTA(F75:L75) -> 0 | C75: Champion | D75: 11 | E75: Augmented Reality ads | F75: FALSE | G75: FALSE | H75: FALSE | I75: FALSE | J75: FALSE | K75: FALSE | L75: FALSE
B76: 5
C77: Reporting | F77: =IFERROR(__xludf.DUMMYFUNCTION("SPARKLINE(COUNTIF(F79:L86,TRUE),{""charttype"",""bar"";""max"",COUNTA(F79:L86);""color1"",""green""})"),"") | N77: =COUNTIF(F79:L86,TRUE)/COUNTA(F79:L86) -> 0
B79: =COUNTIF(F79:L79,TRUE)/COUNTA(F79:L79) -> 0 | C79: Basic | D79: 1 | E79: Gathering insights from campaign overview | F79: FALSE | G79: FALSE | H79: FALSE | I79: FALSE | J79: FALSE | K79: FALSE | L79: FALSE
B80: =COUNTIF(F80:L82,TRUE)/COUNTA(F80:L82) -> 0 | C80: Advanced | D80: 2 | E80: Snapchat & website insights (GA) | F80: FALSE | G80: FALSE | H80: FALSE | I80: FALSE | J80: FALSE | K80: FALSE | L80: FALSE
D81: 3 | E81: Split testing in Snapchat (experiments) | F81: FALSE | G81: FALSE | H81: FALSE | I81: FALSE | J81: FALSE | K81: FALSE | L81: FALSE
D82: 4 | E82: Monthly reporting meetings | F82: FALSE | G82: FALSE | H82: FALSE | I82: FALSE | J82: FALSE | K82: FALSE | L82: FALSE
B83: =COUNTIF(F83:L84,TRUE)/COUNTA(F83:L84) -> 0 | C83: Expert | D83: 5 | E83: Real time data dasboard | F83: FALSE | G83: FALSE | H83: FALSE | I83: FALSE | J83: FALSE | K83: FALSE | L83: FALSE
D84: 6 | E84: Consisted testing framework including hyptohesis | F84: FALSE | G84: FALSE | H84: FALSE | I84: FALSE | J84: FALSE | K84: FALSE | L84: FALSE
B85: =COUNTIF(F85:L86,TRUE)/COUNTA(F85:L86) -> 0 | C85: Champion | D85: 7 | E85: Brand lift studies | F85: FALSE | G85: FALSE | H85: FALSE | I85: FALSE | J85: FALSE | K85: FALSE | L85: FALSE
D86: 8 | E86: Marketing mix modeling | F86: FALSE | G86: FALSE | H86: FALSE | I86: FALSE | J86: FALSE | K86: FALSE | L86: FALSE
B88: SUMMARY (relevance to be adjusted to client needs) | P88: << in the column on the left you can decide if a certain topic is more or less important compared to others - to decide how important it is for the total score of a client Example given: Feed management is not always relevant for a company (B2B). You can give the relevance a score of 0 and it won't be calculated in the total average score Default setting: all topics at 100%
E90: Topic | F90: Topic relevance 0-100% | N90: Total score
C92: 1 | E92: =C11 -> Campaign setup | F92: 1 | M92: =IFERROR(__xludf.DUMMYFUNCTION("F11"),"") | N92: =N11 -> 0
C94: 2 | E94: =C25 -> Audiences & targeting | F94: 1 | M94: =IFERROR(__xludf.DUMMYFUNCTION("F25"),"") | N94: =N25 -> 0
C96: 3 | E96: =C43 -> Conversion & KPI | F96: 1 | M96: =IFERROR(__xludf.DUMMYFUNCTION("F43"),"") | N96: =N43 -> 0
C99: 4 | E99: =C63 -> Creative & content | F99: 1 | M99: =IFERROR(__xludf.DUMMYFUNCTION("F63"),"") | N99: =N63 -> 0
C101: 5 | E101: =C77 -> Reporting | F101: 1 | M101: =IFERROR(__xludf.DUMMYFUNCTION("F77"),"") | N101: =N77 -> 0
C103: 7
C105: 8
C107: 9
C109: 10
M111: Total average weighted score | N111: =IFERROR(__xludf.DUMMYFUNCTION("AVERAGE.WEIGHTED(N92:N109,F92:F109)"),0.0) -> 0

Sheet SEO
E2: MUST READ: How to use? 1. Only click a checkbox when the topic on the left - is 100% completed 2. Don't check the box if you "just" checked the topic if it was applicable 3. The same topic can be in multiple stages (different levels of maturity) | F2: FR | G2: NL | H2: DE | I2: BE | J2: UK | K2: US | L2: IT | M2: Adaptation topics (V) | N2: Topics not finalized (X) | P2: Last updated at 22/09/2023 by Arlette Opzeeland
F3: TRUE | G3: TRUE | H3: TRUE | I3: TRUE | J3: TRUE | K3: TRUE | L3: TRUE | M3: =(COUNTIF(F:L,TRUE))-COUNTIF(F3:L3,true) -> 0 | N3: =COUNTIF(F:L,FALSE) -> 245
B4: =N88 -> 0 | F4: =COUNTIF(F:F,TRUE)-1 -> 0 | G4: =COUNTIF(G:G,TRUE)-1 -> 0 | H4: =COUNTIF(H:H,TRUE)-1 -> 0 | I4: =COUNTIF(I:I,TRUE)-1 -> 0 | J4: =COUNTIF(J:J,TRUE)-1 -> 0 | K4: =COUNTIF(K:K,TRUE)-1 -> 0 | L4: =COUNTIF(L:L,TRUE)-1 -> 0
F6: =COUNTIF(F:F,FALSE) -> 35 | G6: =COUNTIF(G:G,FALSE) -> 35 | H6: =COUNTIF(H:H,FALSE) -> 35 | I6: =COUNTIF(I:I,FALSE) -> 35 | J6: =COUNTIF(J:J,FALSE) -> 35 | K6: =COUNTIF(K:K,FALSE) -> 35 | L6: =COUNTIF(L:L,FALSE) -> 35
C8: Maturity | D8: # | E8: Topics | F8: FR | G8: NL | H8: DE | I8: BE | J8: UK | K8: US | L8: IT | M8: Details | N8: Next steps
E9: If a topic is not relevant for the client - delete the checkbox | F9: Only check a box if the topic is fully integrated | M9: Explain what the issue is if not checked | N9: What would be the next steps to finalize the topic
B10: 1
C11: Technical: Website configuration | F11: =IFERROR(__xludf.DUMMYFUNCTION("SPARKLINE(COUNTIF(F13:L20,TRUE),{""charttype"",""bar"";""max"",COUNTA(F13:L20);""color1"",""green""})"),"") | N11: =COUNTIF(F13:L20,TRUE)/COUNTA(F13:L20) -> 0 | P11: Commentbox for feedback
B13: =COUNTIF(F13:L15,TRUE)/COUNTA(F13:L15) -> 0 | C13: Basic | D13: 1 | E13: 404 page | F13: FALSE | G13: FALSE | H13: FALSE | I13: FALSE | J13: FALSE | K13: FALSE | L13: FALSE
D14: 2 | E14: HTTPS protocol | F14: FALSE | G14: FALSE | H14: FALSE | I14: FALSE | J14: FALSE | K14: FALSE | L14: FALSE
D15: 3 | E15: Robots.txt file | F15: FALSE | G15: FALSE | H15: FALSE | I15: FALSE | J15: FALSE | K15: FALSE | L15: FALSE
B16: =COUNTIF(F16:L19,TRUE)/COUNTA(F16:L19) -> 0 | C16: Advanced | D16: 4 | E16: Homepage accessible through multiple URLS | F16: FALSE | G16: FALSE | H16: FALSE | I16: FALSE | J16: FALSE | K16: FALSE | L16: FALSE
D17: 5 | E17: Server environment (Server errors) | F17: FALSE | G17: FALSE | H17: FALSE | I17: FALSE | J17: FALSE | K17: FALSE | L17: FALSE
D18: 6 | E18: XML sitemap | F18: FALSE | G18: FALSE | H18: FALSE | I18: FALSE | J18: FALSE | K18: FALSE | L18: FALSE
D19: 7 | E19: One URL per page | F19: FALSE | G19: FALSE | H19: FALSE | I19: FALSE | J19: FALSE | K19: FALSE | L19: FALSE
B20: =COUNTIF(F20:L20,TRUE)/COUNTA(F20:L20) -> 0 | C20: Expert | D20: 8 | E20: HTML validity | F20: FALSE | G20: FALSE | H20: FALSE | I20: FALSE | J20: FALSE | K20: FALSE | L20: FALSE
B21: 2
C22: Technical: Site structure | F22: =IFERROR(__xludf.DUMMYFUNCTION("SPARKLINE(COUNTIF(F24:L31,TRUE),{""charttype"",""bar"";""max"",COUNTA(F24:L31);""color1"",""green""})"),"") | N22: =COUNTIF(F24:L31,TRUE)/COUNTA(F24:L31) -> 0
B24: =COUNTIF(F24:L25,TRUE)/COUNTA(F24:L25) -> 0 | C24: Basic | D24: 1 | E24: URL structure | F24: FALSE | G24: FALSE | H24: FALSE | I24: FALSE | J24: FALSE | K24: FALSE | L24: FALSE
D25: 4 | E25: Homepage links | F25: FALSE | G25: FALSE | H25: FALSE | I25: FALSE | J25: FALSE | K25: FALSE | L25: FALSE
B26: =COUNTIF(F26:L28,TRUE)/COUNTA(F26:L28) -> 0 | C26: Advanced | D26: 5 | E26: Canonical annotation | F26: FALSE | G26: FALSE | H26: FALSE | I26: FALSE | J26: FALSE | K26: FALSE | L26: FALSE
D27: 3 | E27: Internal links | F27: FALSE | G27: FALSE | H27: FALSE | I27: FALSE | J27: FALSE | K27: FALSE | L27: FALSE
D28: 7 | E28: Pagination | F28: FALSE | G28: FALSE | H28: FALSE | I28: FALSE | J28: FALSE | K28: FALSE | L28: FALSE
B29: =COUNTIF(F29:L30,TRUE)/COUNTA(F29:L30) -> 0 | C29: Expert | D29: 6 | E29: URL parameters | F29: FALSE | G29: FALSE | H29: FALSE | I29: FALSE | J29: FALSE | K29: FALSE | L29: FALSE
D30: 8 | E30: Internationalisation | F30: FALSE | G30: FALSE | H30: FALSE | I30: FALSE | J30: FALSE | K30: FALSE | L30: FALSE
B31: =COUNTIF(F31:L31,TRUE)/COUNTA(F31:L31) -> 0 | C31: Champion | D31: 2 | E31: Visitibilty of relevant content | F31: FALSE | G31: FALSE | H31: FALSE | I31: FALSE | J31: FALSE | K31: FALSE | L31: FALSE
B32: 3
C33: Technical: Website content | F33: =IFERROR(__xludf.DUMMYFUNCTION("SPARKLINE(COUNTIF(F35:L42,TRUE),{""charttype"",""bar"";""max"",COUNTA(F35:L42);""color1"",""green""})"),"") | N33: =COUNTIF(F35:L42,TRUE)/COUNTA(F35:L42) -> 0
B35: =COUNTIF(F35:L38,TRUE)/COUNTA(F35:L38) -> 0 | C35: Basic | D35: 1 | E35: Page titles | F35: FALSE | G35: FALSE | H35: FALSE | I35: FALSE | J35: FALSE | K35: FALSE | L35: FALSE
D36: 2 | E36: Meta description | F36: FALSE | G36: FALSE | H36: FALSE | I36: FALSE | J36: FALSE | K36: FALSE | L36: FALSE
D37: 3 | E37: Heading tags | F37: FALSE | G37: FALSE | H37: FALSE | I37: FALSE | J37: FALSE | K37: FALSE | L37: FALSE
D38: 4 | E38: Images, links, and alt attributes | F38: FALSE | G38: FALSE | H38: FALSE | I38: FALSE | J38: FALSE | K38: FALSE | L38: FALSE
B39: =COUNTIF(F39:L41,TRUE)/COUNTA(F39:L41) -> 0 | C39: Advanced | D39: 5 | E39: Monitoring / dashboarding | F39: FALSE | G39: FALSE | H39: FALSE | I39: FALSE | J39: FALSE | K39: FALSE | L39: FALSE
D40: 6 | E40: Keyword research | F40: FALSE | G40: FALSE | H40: FALSE | I40: FALSE | J40: FALSE | K40: FALSE | L40: FALSE
D41: 7 | E41: Focus keywords | F41: FALSE | G41: FALSE | H41: FALSE | I41: FALSE | J41: FALSE | K41: FALSE | L41: FALSE
B42: =COUNTIF(F42:L42,TRUE)/COUNTA(F42:L42) -> 0 | C42: Champion | D42: 8 | E42: Structured data | F42: FALSE | G42: FALSE | H42: FALSE | I42: FALSE | J42: FALSE | K42: FALSE | L42: FALSE
B43: 4
C44: Authority | F44: =IFERROR(__xludf.DUMMYFUNCTION("SPARKLINE(COUNTIF(F46:L48,TRUE),{""charttype"",""bar"";""max"",COUNTA(F46:L48);""color1"",""green""})"),"") | N44: =COUNTIF(F46:F48,TRUE)/COUNTA(F46:L48) -> 0
B46: =COUNTIF(F46:L46,TRUE)/COUNTA(F46:L46) -> 0 | C46: Basic | D46: 1 | E46: Relevance and Authority of Referring Domains | F46: FALSE | G46: FALSE | H46: FALSE | I46: FALSE | J46: FALSE | K46: FALSE | L46: FALSE
B47: =COUNTIF(F47:L48,TRUE)/COUNTA(F47:L48) -> 0 | C47: Advanced | D47: 2 | E47: Anchor Text Distribution | F47: FALSE | G47: FALSE | H47: FALSE | I47: FALSE | J47: FALSE | K47: FALSE | L47: FALSE
D48: 3 | E48: Link Quality and Spammy Backlinks | F48: FALSE | G48: FALSE | H48: FALSE | I48: FALSE | J48: FALSE | K48: FALSE | L48: FALSE
B49: 5
C50: Admin / Connections | F50: =IFERROR(__xludf.DUMMYFUNCTION("SPARKLINE(COUNTIF(F52:L55,TRUE),{""charttype"",""bar"";""max"",COUNTA(F52:L55);""color1"",""green""})"),"") | N50: =COUNTIF(F52:F55,TRUE)/COUNTA(F52:L55) -> 0
B52: =COUNTIF(F52:L55,TRUE)/COUNTA(F52:L55) -> 0 | C52: Basic | D52: 1 | E52: Search Console - Access / setup | F52: FALSE | G52: FALSE | H52: FALSE | I52: FALSE | J52: FALSE | K52: FALSE | L52: FALSE
D53: 2 | E53: Google Analytics connection | F53: FALSE | G53: FALSE | H53: FALSE | I53: FALSE | J53: FALSE | K53: FALSE | L53: FALSE
D54: 3 | E54: Google My Business (GMB) connection | F54: FALSE | G54: FALSE | H54: FALSE | I54: FALSE | J54: FALSE | K54: FALSE | L54: FALSE
D55: 4 | E55: Bing webmaster tool connection / setup | F55: FALSE | G55: FALSE | H55: FALSE | I55: FALSE | J55: FALSE | K55: FALSE | L55: FALSE
B56: 6
C57: Reporting & Tooling | F57: =IFERROR(__xludf.DUMMYFUNCTION("SPARKLINE(COUNTIF(F59:L62,TRUE),{""charttype"",""bar"";""max"",COUNTA(F59:L62);""color1"",""green""})"),"") | N57: =COUNTIF(F59:F62,TRUE)/COUNTA(F59:L62) -> 0
B59: =COUNTIF(F59:L61,TRUE)/COUNTA(F59:L61) -> 0 | C59: Basic | D59: 1 | E59: Standard KPI settings | F59: FALSE | G59: FALSE | H59: FALSE | I59: FALSE | J59: FALSE | K59: FALSE | L59: FALSE
D60: 2 | E60: Tooling for keyword research (e.g.: Ahrefs) | F60: FALSE | G60: FALSE | H60: FALSE | I60: FALSE | J60: FALSE | K60: FALSE | L60: FALSE
D61: 3 | E61: Tooling for technical settings (e.g.: Contentking or Screamingfrog) | F61: FALSE | G61: FALSE | H61: FALSE | I61: FALSE | J61: FALSE | K61: FALSE | L61: FALSE
B62: =COUNTIF(F62:L62,TRUE)/COUNTA(F62:L62) -> 0 | C62: Advanced | D62: 4 | E62: Real time report (based on crawling) | F62: FALSE | G62: FALSE | H62: FALSE | I62: FALSE | J62: FALSE | K62: FALSE | L62: FALSE
B64: SUMMARY (relevance to be adjusted to client needs) | P64: << in the column on the left you can decide if a certain topic is more or less important compared to others - to decide how important it is for the total score of a client Example given: Feed management is not always relevant for a company (B2B). You can give the relevance a score of 0 and it won't be calculated in the total average score Default setting: all topics at 100%
E66: Topic | F66: Topic relevance 0-100% | N66: Total score
C68: 1 | E68: =C11 -> Technical: Website configuration | F68: 1 | M68: =IFERROR(__xludf.DUMMYFUNCTION("F11"),"") | N68: =N11 -> 0
C70: 2 | E70: =C22 -> Technical: Site structure | F70: 1 | M70: =IFERROR(__xludf.DUMMYFUNCTION("F22"),"") | N70: =N22 -> 0
C72: 3 | E72: =C33 -> Technical: Website content | F72: 1 | M72: =IFERROR(__xludf.DUMMYFUNCTION("F33"),"") | N72: =N33 -> 0
C74: 4 | E74: =C44 -> Authority | F74: 1 | M74: =IFERROR(__xludf.DUMMYFUNCTION("F44"),"") | N74: =N44 -> 0
C76: 5 | E76: =C50 -> Admin / Connections | F76: 1 | M76: =IFERROR(__xludf.DUMMYFUNCTION("F50"),"") | N76: =N50 -> 0
C78: 6 | E78: =C57 -> Reporting & Tooling | F78: 1 | M78: =IFERROR(__xludf.DUMMYFUNCTION("F57"),"") | N78: =N57 -> 0
C80: 7
C82: 8
C84: 9
C86: 10
M88: Total average weighted score | N88: =IFERROR(__xludf.DUMMYFUNCTION("AVERAGE.WEIGHTED(N68:N86,F68:F86)"),0.0) -> 0

Sheet CROUX
B2: CRO/UX | E2: MUST READ: How to use? 1. Only click a checkbox when the topic on the left - is 100% completed 2. Don't check the box if you "just" checked the topic if it was applicable 3. The same topic can be in multiple stages (different levels of maturity) | F2: FR | G2: NL | H2: DE | I2: BE | J2: UK | K2: US | L2: IT | M2: Adaptation topics (V) | N2: Topics not finalized (X) | R2: Last updated at 23/09/2025 by Delphine Holbecq
F3: TRUE | G3: TRUE | H3: TRUE | I3: TRUE | J3: TRUE | K3: TRUE | L3: TRUE | M3: =(COUNTIF(E:L,TRUE))-COUNTIF(E3:L3,true) -> 0 | N3: =COUNTIF(E:L,FALSE) -> 588
B4: =P163 -> 0 | F4: =COUNTIF(F13:F132,TRUE) -> 0 | G4: =COUNTIF(G13:G132,TRUE) -> 0 | H4: =COUNTIF(H13:H132,TRUE) -> 0 | I4: =COUNTIF(I13:I132,TRUE) -> 0 | J4: =COUNTIF(J13:J132,TRUE) -> 0 | K4: =COUNTIF(K13:K132,TRUE) -> 0 | L4: =COUNTIF(L13:L132,TRUE) -> 0
F6: =COUNTIF(F13:F132,FALSE) -> 84 | G6: =COUNTIF(G13:G132,FALSE) -> 84 | H6: =COUNTIF(H13:H132,FALSE) -> 84 | I6: =COUNTIF(I13:I132,FALSE) -> 84 | J6: =COUNTIF(J13:J132,FALSE) -> 84 | K6: =COUNTIF(K13:K132,FALSE) -> 84 | L6: =COUNTIF(L13:L132,FALSE) -> 84
C8: Maturity | D8: # | E8: Topics | F8: FR | G8: NL | H8: DE | I8: BE | J8: UK | K8: US | L8: IT | M8: SR (Severity Rating) | N8: ER (Easy to fix Rating) | O8: Priority | P8: Comments / Action
E9: If a topic is not relevant for the client - delete the checkbox | F9: Only check a box if the topic is fully integrated | M9: S0. No violations found S1. Cosmetic problems only S2. Minor usability problems S3. Major usability problems S4. Usability catastrophe | N9: E0. Fix will require maximum effort E1. Fix will require considerable effort E2. Fix will require some effort E3. Fix is easy but with minor effort E4. Fix is trivial and easy to implement | O9: Topics with the highest rating get the highest priorty based on effort/impact | P9: What would be the next steps to finalize the topic
B10: 1
C11: Tools | F11: =IFERROR(__xludf.DUMMYFUNCTION("SPARKLINE(COUNTIF(F13:L20,TRUE),{""charttype"",""bar"";""max"",COUNTA(F13:L20);""color1"",""green""})"),"") | P11: =COUNTIF(F13:L20,TRUE)/COUNTA(F13:L20) -> 0
B13: =COUNTIF(F13:L16,TRUE)/COUNTA(F13:L16) -> 0 | C13: Basic | D13: 1 | E13: There is an a/b testing tool in place | F13: FALSE | G13: FALSE | H13: FALSE | I13: FALSE | J13: FALSE | K13: FALSE | L13: FALSE | M13: X | N13: X
D14: 2 | E14: GA4 is properly set up | F14: FALSE | G14: FALSE | H14: FALSE | I14: FALSE | J14: FALSE | K14: FALSE | L14: FALSE | M14: X | N14: X
D15: 3 | E15: There is a heatmap/sessions tool in place | F15: FALSE | G15: FALSE | H15: FALSE | I15: FALSE | J15: FALSE | K15: FALSE | L15: FALSE | M15: X | N15: X
D16: 4 | E16: Event racking is in place | F16: FALSE | G16: FALSE | H16: FALSE | I16: FALSE | J16: FALSE | K16: FALSE | L16: FALSE | M16: X | N16: X
B17: =COUNTIF(F17:L18,TRUE)/COUNTA(F17:L18) -> 0 | C17: Advanced | D17: 5 | E17: Custom dashboards for CRO KPIs | F17: FALSE | G17: FALSE | H17: FALSE | I17: FALSE | J17: FALSE | K17: FALSE | L17: FALSE | M17: X | N17: X
D18: 6 | E18: Event tracking for key interactions (clicks, scrolls, form submits) | F18: FALSE | G18: FALSE | H18: FALSE | I18: FALSE | J18: FALSE | K18: FALSE | L18: FALSE | M18: X | N18: X
B19: =COUNTIF(F19:L20,TRUE)/COUNTA(F19:L20) -> 0 | C19: Expert | D19: 5 | E19: Predictive analytics for conversion probability | F19: FALSE | G19: FALSE | H19: FALSE | I19: FALSE | J19: FALSE | K19: FALSE | L19: FALSE | M19: X | N19: X
D20: 6 | E20: Automated CRO insights via AI/ML integrations | F20: FALSE | G20: FALSE | H20: FALSE | I20: FALSE | J20: FALSE | K20: FALSE | L20: FALSE | M20: X | N20: X
B21: 2
C22: Testing & experiment | F22: =IFERROR(__xludf.DUMMYFUNCTION("SPARKLINE(COUNTIF(F24:L29,TRUE),{""charttype"",""bar"";""max"",COUNTA(F24:L29);""color1"",""green""})"),"") | P22: =COUNTIF(F24:L29,TRUE)/COUNTA(F24:L29) -> 0
B24: =COUNTIF(F24:L25,TRUE)/COUNTA(F24:L25) -> 0 | C24: Basic | D24: 1 | E24: A/B tests have been executed | F24: FALSE | G24: FALSE | H24: FALSE | I24: FALSE | J24: FALSE | K24: FALSE | L24: FALSE | M24: X | N24: X
D25: 2 | E25: There are clear KPIs for the A/B tests for hard and soft conversions and other goals | F25: FALSE | G25: FALSE | H25: FALSE | I25: FALSE | J25: FALSE | K25: FALSE | L25: FALSE | M25: X | N25: X
B26: =COUNTIF(F26:L28,TRUE)/COUNTA(F26:L28) -> 0 | C26: Advanced | D26: 4 | E26: There is a testing document (and backlog) available | F26: FALSE | G26: FALSE | H26: FALSE | I26: FALSE | J26: FALSE | K26: FALSE | L26: FALSE | M26: X | N26: X
D27: 5 | E27: Test calendar or roadmap is maintained | F27: FALSE | G27: FALSE | H27: FALSE | I27: FALSE | J27: FALSE | K27: FALSE | L27: FALSE | M27: X | N27: X
D28: 6 | E28: Segmentation in experiments | F28: FALSE | G28: FALSE | H28: FALSE | I28: FALSE | J28: FALSE | K28: FALSE | L28: FALSE | M28: X | N28: X
B29: =COUNTIF(F29:L29,TRUE)/COUNTA(F29:L29) -> 0 | C29: Expert | D29: 7 | E29: Continuous deployment of high-impact experiments | F29: FALSE | G29: FALSE | H29: FALSE | I29: FALSE | J29: FALSE | K29: FALSE | L29: FALSE | M29: X | N29: X
B30: 3
C31: AI Experience | F31: =IFERROR(__xludf.DUMMYFUNCTION("SPARKLINE(COUNTIF(F33:L37,TRUE),{""charttype"",""bar"";""max"",COUNTA(F33:L37);""color1"",""green""})"),"") | P31: =COUNTIF(F33:L37,TRUE)/COUNTA(F33:L37) -> 0
B33: =COUNTIF(F33:L33,TRUE)/COUNTA(F33:L33) -> 0 | C33: Basic | D33: 1 | E33: Basic AI-generated content (e.g. product recommendations, FAQs, chatbot responses) is present | F33: FALSE | G33: FALSE | H33: FALSE | I33: FALSE | J33: FALSE | K33: FALSE | L33: FALSE | M33: X | N33: X
B34: =COUNTIF(F34:L36,TRUE)/COUNTA(F34:L36) -> 0 | C34: Advanced | D34: 2 | E34: AI personalization of content and product listings | F34: FALSE | G34: FALSE | H34: FALSE | I34: FALSE | J34: FALSE | K34: FALSE | L34: FALSE | M34: X | N34: X
D35: 3 | E35: AI experiences are A/B tested and optimized like any other UX element | F35: FALSE | G35: FALSE | H35: FALSE | I35: FALSE | J35: FALSE | K35: FALSE | L35: FALSE | M35: X | N35: X
D36: 4 | E36: Hyper-personalized user journeys at individual level | F36: FALSE | G36: FALSE | H36: FALSE | I36: FALSE | J36: FALSE | K36: FALSE | L36: FALSE | M36: X | N36: X
B37: =COUNTIF(F37:L37,TRUE)/COUNTA(F37:L37) -> 0 | C37: Expert | D37: 5 | E37: AI self-learning loops for CRO improvements | F37: FALSE | G37: FALSE | H37: FALSE | I37: FALSE | J37: FALSE | K37: FALSE | L37: FALSE | M37: X | N37: X
B38: 4
C39: User experience: Visibility of System Status | F39: =IFERROR(__xludf.DUMMYFUNCTION("SPARKLINE(COUNTIF(F41:L47,TRUE),{""charttype"",""bar"";""max"",COUNTA(F41:L47);""color1"",""green""})"),"") | P39: =COUNTIF(F41:L47,TRUE)/COUNTA(F41:L47) -> 0
B41: =COUNTIF(F41:L42,TRUE)/COUNTA(F41:L42) -> 0 | C41: Basic | D41: 1 | E41: Every interface begins with a title/header that describes page content or function | F41: FALSE | G41: FALSE | H41: FALSE | I41: FALSE | J41: FALSE | K41: FALSE | L41: FALSE | O41: =M41+N41 -> 0
D42: 2 | E42: Selected interface elements are highlighted from other elements which are not selected | F42: FALSE | G42: FALSE | H42: FALSE | I42: FALSE | J42: FALSE | K42: FALSE | L42: FALSE | O42: =M42+N42 -> 0
B43: =COUNTIF(F43:L46,TRUE)/COUNTA(F43:L46) -> 0 | C43: Advanced | D43: 3 | E43: Users receive immediate visual feedback when elements are interacted with (e.g. clicked, dragged, hovered) | F43: FALSE | G43: FALSE | H43: FALSE | I43: FALSE | J43: FALSE | K43: FALSE | L43: FALSE | O43: =M43+N43 -> 0
D44: 4 | E44: Real-time stock/availability updates | F44: FALSE | G44: FALSE | H44: FALSE | I44: FALSE | J44: FALSE | K44: FALSE | L44: FALSE | O44: =M44+N44 -> 0
D45: 5 | E45: Progress bars for multi-step forms/checkout | F45: FALSE | G45: FALSE | H45: FALSE | I45: FALSE | J45: FALSE | K45: FALSE | L45: FALSE | O45: =M45+N45 -> 0
D46: 6 | E46: The current state of interactive elements (e.g. active, disabled, loading, completed) is clearly indicated | F46: FALSE | G46: FALSE | H46: FALSE | I46: FALSE | J46: FALSE | K46: FALSE | L46: FALSE | O46: =M46+N46 -> 0
B47: =COUNTIF(F47:L47,TRUE)/COUNTA(F47:L47) -> 0 | C47: Expert | D47: 7 | E47: Users are informed of any system delays longer than 400ms through appropriate feedback (e.g. spinner, progress bar, message) | F47: FALSE | G47: FALSE | H47: FALSE | I47: FALSE | J47: FALSE | K47: FALSE | L47: FALSE | O47: =M47+N47 -> 0
B48: 5
C49: User Experience: Match between the system and the real world | F49: =IFERROR(__xludf.DUMMYFUNCTION("SPARKLINE(COUNTIF(F51:L56,TRUE),{""charttype"",""bar"";""max"",COUNTA(F51:L56);""color1"",""green""})"),"") | P49: =COUNTIF(F51:L56,TRUE)/COUNTA(F51:L56) -> 0
B51: =COUNTIF(F51:L53,TRUE)/COUNTA(F51:L53) -> 0 | C51: Basic | D51: 1 | E51: Familiar language is used in the interface (no jargon) | F51: FALSE | G51: FALSE | H51: FALSE | I51: FALSE | J51: FALSE | K51: FALSE | L51: FALSE | O51: =M51+N51 -> 0
D52: 2 | E52: Icons and images match with the user expectations | F52: FALSE | G52: FALSE | H52: FALSE | I52: FALSE | J52: FALSE | K52: FALSE | L52: FALSE | O52: =M52+N52 -> 0
D53: 3 | E53: Menu choices fit into meaningful categories and follow logical, user-centered categorization that aligns with users’ mental models | F53: FALSE | G53: FALSE | H53: FALSE | I53: FALSE | J53: FALSE | K53: FALSE | L53: FALSE | O53: =M53+N53 -> 0
B54: =COUNTIF(F54:L54,TRUE)/COUNTA(F54:L54) -> 0 | C54: Advanced | D54: 3 | E54: Adaptive content based on local idioms and norms | F54: FALSE | G54: FALSE | H54: FALSE | I54: FALSE | J54: FALSE | K54: FALSE | L54: FALSE | O54: =M54+N54 -> 0
B55: =COUNTIF(F55:L56,TRUE)/COUNTA(F55:L56) -> 0 | C55: Expert | D55: 4 | E55: Dynamic content in local tone and idiom | F55: FALSE | G55: FALSE | H55: FALSE | I55: FALSE | J55: FALSE | K55: FALSE | L55: FALSE | O55: =M55+N55 -> 0
D56: 5 | E56: Predictive adaptation based on user behavior and context | F56: FALSE | G56: FALSE | H56: FALSE | I56: FALSE | J56: FALSE | K56: FALSE | L56: FALSE | O56: =M56+N56 -> 0
B57: 6
C58: User Experience: User control and freedom | F58: =IFERROR(__xludf.DUMMYFUNCTION("SPARKLINE(COUNTIF(F60:L66,TRUE),{""charttype"",""bar"";""max"",COUNTA(F60:L66);""color1"",""green""})"),"") | P58: =COUNTIF(F60:L66,TRUE)/COUNTA(F60:L66) -> 0
B60: =COUNTIF(F60:L61,TRUE)/COUNTA(F60:L61) -> 0 | C60: Basic | D60: 1 | E60: There is clear navigation to home | F60: FALSE | G60: FALSE | H60: FALSE | I60: FALSE | J60: FALSE | K60: FALSE | L60: FALSE | O60: =M60+N60 -> 0
D61: 2 | E61: Users can cancel or interrupt ongoing actions (e.g. uploads, form submissions, processing) | F61: FALSE | G61: FALSE | H61: FALSE | I61: FALSE | J61: FALSE | K61: FALSE | L61: FALSE | O61: =M61+N61 -> 0
B62: =COUNTIF(F62:L64,TRUE)/COUNTA(F62:L64) -> 0 | C62: Advanced | D62: 3 | E62: In multi-level menus, users can easily navigate back to previous levels or parent menus | F62: FALSE | G62: FALSE | H62: FALSE | I62: FALSE | J62: FALSE | K62: FALSE | L62: FALSE | O62: =M62+N62 -> 0
D63: 3 | E63: Draft-saving in forms or configurations | F63: FALSE | G63: FALSE | H63: FALSE | I63: FALSE | J63: FALSE | K63: FALSE | L63: FALSE | O63: =M63+N63 -> 0
D64: 4 | E64: Users are asked to confirm before performing irreversible or destructive actions (e.g. delete, reset, submit final) | F64: FALSE | G64: FALSE | H64: FALSE | I64: FALSE | J64: FALSE | K64: FALSE | L64: FALSE | O64: =M64+N64 -> 0
B65: =COUNTIF(F65:L66,TRUE)/COUNTA(F65:L66) -> 0 | C65: Expert | D65: 5 | E65: Predictive recovery from accidental actions | F65: FALSE | G65: FALSE | H65: FALSE | I65: FALSE | J65: FALSE | K65: FALSE | L65: FALSE | O65: =M65+N65 -> 0
D66: 6 | E66: Fully reversible actions across all flows | F66: FALSE | G66: FALSE | H66: FALSE | I66: FALSE | J66: FALSE | K66: FALSE | L66: FALSE | O66: =M66+N66 -> 0
B67: 7
C68: User Experience: Consistency and adherence to standards | F68: =IFERROR(__xludf.DUMMYFUNCTION("SPARKLINE(COUNTIF(F70:L73,TRUE),{""charttype"",""bar"";""max"",COUNTA(F70:L73);""color1"",""green""})"),"") | P68: =COUNTIF(F70:L73,TRUE)/COUNTA(F70:L73) -> 0
B70: =COUNTIF(F70:L71,TRUE)/COUNTA(F70:L71) -> 0 | C70: Basic | D70: 1 | E70: The interface avoids excessive use of ALL CAPS, especially in body text, to support readability | F70: FALSE | G70: FALSE | H70: FALSE | I70: FALSE | J70: FALSE | K70: FALSE | L70: FALSE | O70: =M70+N70 -> 0
D71: 2 | E71: Interactive elements (e.g. buttons, icons, links) are consistently labeled to clearly reflect their purpose | F71: FALSE | G71: FALSE | H71: FALSE | I71: FALSE | J71: FALSE | K71: FALSE | L71: FALSE | O71: =M71+N71 -> 0
B72: =COUNTIF(F72:L72,TRUE)/COUNTA(F72:L72) -> 0 | C72: Advanced | D72: 3 | E72: Form field behavior (e.g. capitalization, input validation, formatting) is consistent across the interface and aligns with user expectations | F72: FALSE | G72: FALSE | H72: FALSE | I72: FALSE | J72: FALSE | K72: FALSE | L72: FALSE | O72: =M72+N72 -> 0
B73: =COUNTIF(F73:L73,TRUE)/COUNTA(F73:L73) -> 0 | C73: Expert | D73: 4 | E73: Design patterns and interaction behaviors follow established platform or industry conventions consistently across all screens | F73: FALSE | G73: FALSE | H73: FALSE | I73: FALSE | J73: FALSE | K73: FALSE | L73: FALSE | O73: =M73+N73 -> 0
B74: 8
C75: User Experience: Error prevention | F75: =IFERROR(__xludf.DUMMYFUNCTION("SPARKLINE(COUNTIF(F77:L82,TRUE),{""charttype"",""bar"";""max"",COUNTA(F77:L82);""color1"",""green""})"),"") | P75: =COUNTIF(F77:L82,TRUE)/COUNTA(F77:L82) -> 0
B77: =COUNTIF(F77:L78,TRUE)/COUNTA(F77:L78) -> 0 | C77: Basic | D77: 1 | E77: Instructions are concise, clear, and unambiguous to guide user input | F77: FALSE | G77: FALSE | H77: FALSE | I77: FALSE | J77: FALSE | K77: FALSE | L77: FALSE | O77: =M77+N77 -> 0
D78: 2 | E78: Required fields marked in forms | F78: FALSE | G78: FALSE | H78: FALSE | I78: FALSE | J78: FALSE | K78: FALSE | L78: FALSE | O78: =M78+N78 -> 0
B79: =COUNTIF(F79:L81,TRUE)/COUNTA(F79:L81) -> 0 | C79: Advanced | D79: 3 | E79: Error messages clearly explain the cause of the problem and, when possible, suggest how to fix it | F79: FALSE | G79: FALSE | H79: FALSE | I79: FALSE | J79: FALSE | K79: FALSE | L79: FALSE | O79: =M79+N79 -> 0
D80: 4 | E80: Input errors are clearly highlighted on the affected fields with visible cues (e.g. red border, icon) | F80: FALSE | G80: FALSE | H80: FALSE | I80: FALSE | J80: FALSE | K80: FALSE | L80: FALSE | O80: =M80+N80 -> 0
D81: 5 | E81: Error and warning messages use constructive, empathetic language that avoids blaming or confusing the user | F81: FALSE | G81: FALSE | H81: FALSE | I81: FALSE | J81: FALSE | K81: FALSE | L81: FALSE | O81: =M81+N81 -> 0
B82: =COUNTIF(F82:L82,TRUE)/COUNTA(F82:L82) -> 0 | C82: Expert | D82: 6 | E82: Predictive warnings and error prevention | F82: FALSE | G82: FALSE | H82: FALSE | I82: FALSE | J82: FALSE | K82: FALSE | L82: FALSE | O82: =M82+N82 -> 0
B83: 9
C84: User Experience: Recognition rather than recall | F84: =IFERROR(__xludf.DUMMYFUNCTION("SPARKLINE(COUNTIF(F86:L91,TRUE),{""charttype"",""bar"";""max"",COUNTA(F86:L91);""color1"",""green""})"),"") | P84: =COUNTIF(F86:L91,TRUE)/COUNTA(F86:L91) -> 0
B86: =COUNTIF(F86:L87,TRUE)/COUNTA(F86:L87) -> 0 | C86: Basic | D86: 1 | E86: Similar interface elements behave consistently, providing predictable interactions across the system | F86: FALSE | G86: FALSE | H86: FALSE | I86: FALSE | J86: FALSE | K86: FALSE | L86: FALSE | O86: =M86+N86 -> 0
D87: 2 | E87: Component sizes, colors, and styles are used consistently to support visual recognition | F87: FALSE | G87: FALSE | H87: FALSE | I87: FALSE | J87: FALSE | K87: FALSE | L87: FALSE | O87: =M87+N87 -> 0
B88: =COUNTIF(F88:L89,TRUE)/COUNTA(F88:L89) -> 0 | C88: Advanced | D88: 3 | E88: Page layouts and navigation align with users’ mental models and expectations to facilitate recognition | F88: FALSE | G88: FALSE | H88: FALSE | I88: FALSE | J88: FALSE | K88: FALSE | L88: FALSE | O88: =M88+N88 -> 0
D89: 4 | E89: All necessary information and options required to complete an action are clearly visible or easily accessible without unnecessary memory load | F89: FALSE | G89: FALSE | H89: FALSE | I89: FALSE | J89: FALSE | K89: FALSE | L89: FALSE | O89: =M89+N89 -> 0
B90: =COUNTIF(F90:L91,TRUE)/COUNTA(F90:L91) -> 0 | C90: Expert | D90: 5 | E90: User history-based predictive navigation | F90: FALSE | G90: FALSE | H90: FALSE | I90: FALSE | J90: FALSE | K90: FALSE | L90: FALSE | O90: =M90+N90 -> 0
D91: 6 | E91: Dynamic/AI-driven surfacing of next best action | F91: FALSE | G91: FALSE | H91: FALSE | I91: FALSE | J91: FALSE | K91: FALSE | L91: FALSE | O91: =M91+N91 -> 0
B92: 10
C93: User Experience: Flexibility and efficiency of use | F93: =IFERROR(__xludf.DUMMYFUNCTION("SPARKLINE(COUNTIF(F95:L101,TRUE),{""charttype"",""bar"";""max"",COUNTA(F95:L101);""color1"",""green""})"),"") | P93: =COUNTIF(F95:L101,TRUE)/COUNTA(F95:L101) -> 0
B95: =COUNTIF(F95:L95,TRUE)/COUNTA(F95:L95) -> 0 | C95: Basic | D95: 1 | E95: The system provides shortcuts/ quick actions for efficiency for experienced users | F95: FALSE | G95: FALSE | H95: FALSE | I95: FALSE | J95: FALSE | K95: FALSE | L95: FALSE | O95: =M95+N95 -> 0
B96: =COUNTIF(F96:L100,TRUE)/COUNTA(F96:L100) -> 0 | C96: Advanced | D96: 2 | E96: The shortcuts are customizable | F96: FALSE | G96: FALSE | H96: FALSE | I96: FALSE | J96: FALSE | K96: FALSE | L96: FALSE | O96: =M96+N96 -> 0
D97: 3 | E97: The system supports multiple methods for completing actions, catering to different user preferences and contexts | F97: FALSE | G97: FALSE | H97: FALSE | I97: FALSE | J97: FALSE | K97: FALSE | L97: FALSE | O97: =M97+N97 -> 0
D98: 4 | E98: Sorting & filtering options on listings | F98: FALSE | G98: FALSE | H98: FALSE | I98: FALSE | J98: FALSE | K98: FALSE | L98: FALSE | O98: =M98+N98 -> 0
D99: 5 | E99: Saved filters and preferences | F99: FALSE | G99: FALSE | H99: FALSE | I99: FALSE | J99: FALSE | K99: FALSE | L99: FALSE | O99: =M99+N99 -> 0
D100: 6 | E100: The system scales for new users as well as advanced users | F100: FALSE | G100: FALSE | H100: FALSE | I100: FALSE | J100: FALSE | K100: FALSE | L100: FALSE | O100: =M100+N100 -> 0
B101: =COUNTIF(F101:L101,TRUE)/COUNTA(F101:L101) -> 0 | C101: Expert | D101: 7 | E101: Fully personalized UI per user behavior | F101: FALSE | G101: FALSE | H101: FALSE | I101: FALSE | J101: FALSE | K101: FALSE | L101: FALSE | O101: =M101+N101 -> 0
B102: 11
C103: User Experience: Aesthetic and minimalism in design | F103: =IFERROR(__xludf.DUMMYFUNCTION("SPARKLINE(COUNTIF(F105:L111,TRUE),{""charttype"",""bar"";""max"",COUNTA(F105:L111);""color1"",""green""})"),"") | P103: =COUNTIF(F105:L111,TRUE)/COUNTA(F105:L111) -> 0
B105: =COUNTIF(F105:L108,TRUE)/COUNTA(F105:L108) -> 0 | C105: Basic | D105: 1 | E105: Only (and all) information essential to decision making displayed on the screen | F105: FALSE | G105: FALSE | H105: FALSE | I105: FALSE | J105: FALSE | K105: FALSE | L105: FALSE | O105: =M105+N105 -> 0
D106: 2 | E106: Each visual element stands out from its background | F106: FALSE | G106: FALSE | H106: FALSE | I106: FALSE | J106: FALSE | K106: FALSE | L106: FALSE | O106: =M106+N106 -> 0
D107: 3 | E107: Related items are grouped visually and separated from other groups by adequate white space, supporting quick scanning and comprehension | F107: FALSE | G107: FALSE | H107: FALSE | I107: FALSE | J107: FALSE | K107: FALSE | L107: FALSE | O107: =M107+N107 -> 0
D108: 4 | E108: Consistent whitespace usage | F108: FALSE | G108: FALSE | H108: FALSE | I108: FALSE | J108: FALSE | K108: FALSE | L108: FALSE | O108: =M108+N108 -> 0
B109: =COUNTIF(F109:L110,TRUE)/COUNTA(F109:L110) -> 0 | C109: Advanced | D109: 5 | E109: Visual hierarchy supports main conversion path | F109: FALSE | G109: FALSE | H109: FALSE | I109: FALSE | J109: FALSE | K109: FALSE | L109: FALSE | O109: =M109+N109 -> 0
D110: 6 | E110: Mobile-first design approach | F110: FALSE | G110: FALSE | H110: FALSE | I110: FALSE | J110: FALSE | K110: FALSE | L110: FALSE | O110: =M110+N110 -> 0
B111: =COUNTIF(F111:L111,TRUE)/COUNTA(F111:L111) -> 0 | C111: Expert | D111: 7 | E111: Personalized minimalism per user preference | F111: FALSE | G111: FALSE | H111: FALSE | I111: FALSE | J111: FALSE | K111: FALSE | L111: FALSE | O111: =M111+N111 -> 0
B112: 12
C113: User Experience: Recognition, diagnosis, and recovery from errors | F113: =IFERROR(__xludf.DUMMYFUNCTION("SPARKLINE(COUNTIF(F115:L121,TRUE),{""charttype"",""bar"";""max"",COUNTA(F115:L121);""color1"",""green""})"),"") | P113: =COUNTIF(F115:L121,TRUE)/COUNTA(F115:L121) -> 0
B115: =COUNTIF(F115:L117,TRUE)/COUNTA(F115:L117) -> 0 | C115: Basic | D115: 1 | E115: There is a clear indication that an error has occurred | F115: FALSE | G115: FALSE | H115: FALSE | I115: FALSE | J115: FALSE | K115: FALSE | L115: FALSE | O115: =M115+N115 -> 0
...

Sheet AI for SEO
B2: AI for SEO | E2: MUST READ: How to use? 1. Only click a checkbox when the topic on the left - is 100% completed 2. Don't check the box if you "just" checked the topic if it was applicable 3. The same topic can be in multiple stages (different levels of maturity) | F2: FR | G2: NL | H2: DE | I2: BE | J2: UK | K2: US | L2: IT | M2: Adaptation topics (V) | N2: Topics not finalized (X)
F3: TRUE | G3: TRUE | H3: TRUE | I3: TRUE | J3: TRUE | K3: TRUE | L3: TRUE | M3: =(COUNTIF(F:L,TRUE))-COUNTIF(F3:L3,true) -> 0 | N3: =COUNTIF(F:L,FALSE) -> 287
B4: =N79 -> 0 | F4: =COUNTIF(F:F,TRUE)-1 -> 0 | G4: =COUNTIF(G:G,TRUE)-1 -> 0 | H4: =COUNTIF(H:H,TRUE)-1 -> 0 | I4: =COUNTIF(I:I,TRUE)-1 -> 0 | J4: =COUNTIF(J:J,TRUE)-1 -> 0 | K4: =COUNTIF(K:K,TRUE)-1 -> 0 | L4: =COUNTIF(L:L,TRUE)-1 -> 0
F6: =COUNTIF(F:F,FALSE) -> 41 | G6: =COUNTIF(G:G,FALSE) -> 41 | H6: =COUNTIF(H:H,FALSE) -> 41 | I6: =COUNTIF(I:I,FALSE) -> 41 | J6: =COUNTIF(J:J,FALSE) -> 41 | K6: =COUNTIF(K:K,FALSE) -> 41 | L6: =COUNTIF(L:L,FALSE) -> 41
C8: Maturity | D8: # | E8: Topics | M8: Details | N8: Comments / Action | O8: More Examples | P8: Impact | Q8: Effort
E9: If a topic is not relevant for the client - delete the checkbox | F9: Only check a box if the topic is fully integrated | M9: Explain what the issue is if not checked | N9: What would be the next steps to finalize the topic
B10: 1
E11: Technical: Infrastructure | F11: =IFERROR(__xludf.DUMMYFUNCTION("SPARKLINE(COUNTIF(F13:F24,TRUE),{""charttype"",""bar"";""max"",COUNTA(F13:F24);""color1"",""green""})"),"") | N11: =COUNTIF(F13:L24,TRUE)/COUNTA(F13:L24) -> 0
B13: =COUNTIF(F13:L16,TRUE)/COUNTA(F13:L16) -> 0 | C13: Basic | D13: 1 | E13: Server-side rendering for the main content (SSR, ISR, of SSG) | F13: FALSE | G13: FALSE | H13: FALSE | I13: FALSE | J13: FALSE | K13: FALSE | L13: FALSE | S13: Commentbox for feedback
D14: 2 | E14: HTTPS protocol | F14: FALSE | G14: FALSE | H14: FALSE | I14: FALSE | J14: FALSE | K14: FALSE | L14: FALSE
D15: 3 | E15: Robots.txt is configured to provide access for crawlers like, GPTBot, Bingbot, Perplexitybot, ClaudeBot, Grok etc. | F15: FALSE | G15: FALSE | H15: FALSE | I15: FALSE | J15: FALSE | K15: FALSE | L15: FALSE
D16: 4 | E16: Has an active acount for webmaster tools, such as Google Search Console, and Bing webmaster tools | F16: FALSE | G16: FALSE | H16: FALSE | I16: FALSE | J16: FALSE | K16: FALSE | L16: FALSE
B17: =COUNTIF(F17:L23,TRUE)/COUNTA(F17:L23) -> 0 | C17: Advanced | D17: 5 | E17: Homepage accessible through multiple URL's | F17: FALSE | G17: FALSE | H17: FALSE | I17: FALSE | J17: FALSE | K17: FALSE | L17: FALSE
D18: 6 | E18: Makes use of symantic headers HTML-tags, such as <article>, <header>, <section> | F18: FALSE | G18: FALSE | H18: FALSE | I18: FALSE | J18: FALSE | K18: FALSE | L18: FALSE
D19: 7 | E19: Core content is not hidden behind JavaScript | F19: FALSE | G19: FALSE | H19: FALSE | I19: FALSE | J19: FALSE | K19: FALSE | L19: FALSE
D20: 8 | E20: XML sitemap submitted at Bing webmasters tools, and Google Search Console | F20: FALSE | G20: FALSE | H20: FALSE | I20: FALSE | J20: FALSE | K20: FALSE | L20: FALSE
D21: 9 | E21: Canonical tags are correctly set up | F21: FALSE | G21: FALSE | H21: FALSE | I21: FALSE | J21: FALSE | K21: FALSE | L21: FALSE
D22: 10 | E22: Href lang tags are correctly set up | F22: FALSE | G22: FALSE | H22: FALSE | I22: FALSE | J22: FALSE | K22: FALSE | L22: FALSE
D23: 11 | E23: No duplicate content with other languages (ask client) | F23: FALSE | G23: FALSE | H23: FALSE | I23: FALSE | J23: FALSE | K23: FALSE | L23: FALSE
B24: =COUNTIF(F24:L24,TRUE)/COUNTA(F24:L24) -> 0 | C24: Expert | D24: 12 | E24: Pages load quick (<2,5s),for both desktop and mobile (PageSpeed Insights) (check 6 different pages at minimum) | F24: FALSE | G24: FALSE | H24: FALSE | I24: FALSE | J24: FALSE | K24: FALSE | L24: FALSE
B25: 2
E26: Authority | F26: =IFERROR(__xludf.DUMMYFUNCTION("SPARKLINE(COUNTIF(F28:F35,TRUE),{""charttype"",""bar"";""max"",COUNTA(F28:F35);""color1"",""green""})"),"") | N26: =COUNTIF(F28:L35,TRUE)/COUNTA(F28:L35) -> 0
B28: =COUNTIF(F28:L29,TRUE)/COUNTA(F28:L29) -> 0 | C28: Basic | D28: 1 | E28: Branded content has consistent USPs, and has prove of expertise related to the brand | F28: FALSE | G28: FALSE | H28: FALSE | I28: FALSE | J28: FALSE | K28: FALSE | L28: FALSE
D29: 2 | E29: The site has 10+ pages with a relative strong backlink profile compared to competitors | F29: FALSE | G29: FALSE | H29: FALSE | I29: FALSE | J29: FALSE | K29: FALSE | L29: FALSE
B30: =COUNTIF(F30:L33,TRUE)/COUNTA(F30:L33) -> 0 | C30: Advanced | D30: 3 | E30: Guest blogs/PR at publications which collaborate with OpenAI or Gemini (for example: Reuters, Wired, QG, Time, The Atlantic, nu.nl etc.) | F30: FALSE | G30: FALSE | H30: FALSE | I30: FALSE | J30: FALSE | K30: FALSE | L30: FALSE
D31: 4 | E31: Active profiles at LinkedIn, Crunchbase, Glassdoor, Facebook, instagram, TikTok, comparison websites etc. | F31: FALSE | G31: FALSE | H31: FALSE | I31: FALSE | J31: FALSE | K31: FALSE | L31: FALSE
D32: 5 | E32: Mentions, and backlinks from niche fora or Reddit, Quora etc. | F32: FALSE | G32: FALSE | H32: FALSE | I32: FALSE | J32: FALSE | K32: FALSE | L32: FALSE
D33: 7 | E33: Authority pages such as 'about', 'Team', 'Mission' are up to date. | F33: FALSE | G33: FALSE | H33: FALSE | I33: FALSE | J33: FALSE | K33: FALSE | L33: FALSE
B34: =COUNTIF(F34:L34,TRUE)/COUNTA(F34:L34) -> 0 | C34: Expert | D34: 8 | E34: Freshness of citations, and backlinks, are published to the website from authoritive sites with 5k+ organic traffic on a monthly basis. | F34: FALSE | G34: FALSE | H34: FALSE | I34: FALSE | J34: FALSE | K34: FALSE | L34: FALSE
B35: =COUNTIF(F35:L35,TRUE)/COUNTA(F35:L35) -> 0 | C35: Champion | D35: 10 | E35: Has citations or no follow links from Wikipedia (if relevant) | F35: FALSE | G35: FALSE | H35: FALSE | I35: FALSE | J35: FALSE | K35: FALSE | L35: FALSE
B36: 3
E37: Reputation management | F37: =IFERROR(__xludf.DUMMYFUNCTION("SPARKLINE(COUNTIF(F39:F46,TRUE),{""charttype"",""bar"";""max"",COUNTA(F39:F46);""color1"",""green""})"),"") | N37: =COUNTIF(F39:L46,TRUE)/COUNTA(F39:L46) -> 0
B39: =COUNTIF(F39:L44,TRUE)/COUNTA(F39:L44) -> 0 | C39: Basic | D39: 1 | E39: Google Business Profile is complete (NAP, opening hours, categories etc.). | F39: FALSE | G39: FALSE | H39: FALSE | I39: FALSE | J39: FALSE | K39: FALSE | L39: FALSE
D40: 2 | E40: Bing Places is complete (NAP, openingstijden, categorieën). | F40: FALSE | G40: FALSE | H40: FALSE | I40: FALSE | J40: FALSE | K40: FALSE | L40: FALSE
D41: 3 | E41: Collecting reviews at websites like: Trustpilot, Clutch, G2, Yelp, Facebook, Instagram etc. | F41: FALSE | G41: FALSE | H41: FALSE | I41: FALSE | J41: FALSE | K41: FALSE | L41: FALSE
D42: 4 | E42: Ask at the client if they have policies and a structure to react at negative reviews (do they have templates for example) | F42: FALSE | G42: FALSE | H42: FALSE | I42: FALSE | J42: FALSE | K42: FALSE | L42: FALSE
D43: 5 | E43: Positive reviews are stimulated via e-mail, QR code, chatbot of thank you page etc. (ask client) | F43: FALSE | G43: FALSE | H43: FALSE | I43: FALSE | J43: FALSE | K43: FALSE | L43: FALSE
D44: 6 | E44: FAQ page has included also frequent asked questions about the brand, complains or reviews/ experiences. | F44: FALSE | G44: FALSE | H44: FALSE | I44: FALSE | J44: FALSE | K44: FALSE | L44: FALSE
B45: 0 | C45: Advanced | D45: 7 | E45: Company information is up to date on external directory, review- or local business websites. | F45: FALSE | G45: FALSE | H45: FALSE | I45: FALSE | J45: FALSE | K45: FALSE | L45: FALSE
B46: =COUNTIF(F46:L46,TRUE)/COUNTA(F46:L46) -> 0 | C46: Expert | D46: 8 | E46: Has a crisisplan if a bad review bombing situation appears. (ask client) | F46: FALSE | G46: FALSE | H46: FALSE | I46: FALSE | J46: FALSE | K46: FALSE | L46: FALSE
B48: 4 | E48: Content | F48: =IFERROR(__xludf.DUMMYFUNCTION("SPARKLINE(COUNTIF(F50:F58,TRUE),{""charttype"",""bar"";""max"",COUNTA(F50:F58);""color1"",""green""})"),"") | N48: =COUNTIF(F50:L58,TRUE)/COUNTA(F50:L58) -> 0
B50: =COUNTIF(F50:L56,TRUE)/COUNTA(F50:L56) -> 0 | C50: Basic | D50: 1 | E50: Content is written in a conversational style using natural language, synonyms, and logical follow-up structure. | F50: FALSE | G50: FALSE | H50: FALSE | I50: FALSE | J50: FALSE | K50: FALSE | L50: FALSE
D51: 2 | E51: Topic clusters are created with internal links to subtopics (e.g. [insert example]). | F51: FALSE | G51: FALSE | H51: FALSE | I51: FALSE | J51: FALSE | K51: FALSE | L51: FALSE
D52: 3 | E52: Each page includes a clear H1 and a logical structure of H2 and H3 headings. | F52: FALSE | G52: FALSE | H52: FALSE | I52: FALSE | J52: FALSE | K52: FALSE | L52: FALSE
D53: 4 | E53: FAQs are included with concrete answers (ideally based on user data). | F53: FALSE | G53: FALSE | H53: FALSE | I53: FALSE | J53: FALSE | K53: FALSE | L53: FALSE
D54: 5 | E54: Content features tables, bullet points, how-to guides, tips, or step-by-step lists. | F54: FALSE | G54: FALSE | H54: FALSE | I54: FALSE | J54: FALSE | K54: FALSE | L54: FALSE
D55: 6 | E55: Sources are cited where possible, with outbound links to reliable domains. | F55: FALSE | G55: FALSE | H55: FALSE | I55: FALSE | J55: FALSE | K55: FALSE | L55: FALSE
D56: 7 | E56: Proprietary data, use cases, or research findings are used to strengthen the content. | F56: FALSE | G56: FALSE | H56: FALSE | I56: FALSE | J56: FALSE | K56: FALSE | L56: FALSE
B57: =COUNTIF(F57:L58,TRUE)/COUNTA(F57:L58) -> 0 | C57: Champion | D57: 8 | E57: Videos, images, and infographics are optimised and include alt texts. | F57: FALSE | G57: FALSE | H57: FALSE | I57: FALSE | J57: FALSE | K57: FALSE | L57: FALSE
D58: 9 | E58: Content is regularly updated and includes a visible update date (e.g. "Last updated on..."). | F58: FALSE | G58: FALSE | H58: FALSE | I58: FALSE | J58: FALSE | K58: FALSE | L58: FALSE
B60: 5 | E60: Baseline check | F60: =IFERROR(__xludf.DUMMYFUNCTION("SPARKLINE(COUNTIF(F62:L65,TRUE),{""charttype"",""bar"";""max"",COUNTA(F62:L65);""color1"",""green""})"),"") | N60: =COUNTIF(F62:L65,TRUE)/COUNTA(F62:L65) -> 0
B62: =COUNTIF(F62:L64,TRUE)/COUNTA(F62:L64) -> 0 | C62: Basic | D62: 1 | E62: Use SearchGPT within ChatGPT to search for: “What are the benefits of [your brand]?” or consult the brand radar on Ahrefs.com or SEOClarity. Record the date, which tool you used, and the number of results you found. Specifically, note how often the site appears in AI Overviews with a link and how often as a citation. | F62: FALSE | G62: FALSE | H62: FALSE | I62: FALSE | J62: FALSE | K62: FALSE | L62: FALSE | N62: With this Looker Studio Template: https://lookerstudio.google.com/u/0/reporting/86cf535e-4f58-4493-ad94-f1f798b03021/page/mcWQF |
D63: 2 | E63: Track traffic from ChatGPT or Bing using UTM tags in URLs or referral traffic data in GA4. | F63: FALSE | G63: FALSE | H63: FALSE | I63: FALSE | J63: FALSE | K63: FALSE | L63: FALSE | M63: With this Looker Studio Template: https://lookerstudio.google.com/u/0/reporting/86cf535e-4f58-4493-ad94-f1f798b03021/page/mcWQF |
D64: 3 | E64: Compare results with two competitors. | F64: FALSE | G64: FALSE | H64: FALSE | I64: FALSE | J64: FALSE | K64: FALSE | L64: FALSE
D65: 4 | E65: Repeat this assessment regularly (e.g. once per month or quarter). | F65: FALSE | G65: FALSE | H65: FALSE | I65: FALSE | J65: FALSE | K65: FALSE | L65: FALSE
F66: SUMMARY (relevance can be adjusted per clients need) | O66: << in the column on the left you can decide if a certain topic is more or less important compared to others - to decide how important it is for the total score of a client Example given: Feed management is not always relevant for a company (B2B). You can give the relevance a score of 0 and it won't be calculated in the total average score Default setting: all topics at 100%
E68: Topic | M68: Topic relevance 0-100% | N68: Total score
C70: 1 | E70: Technical: Infrastructure | M70: =IFERROR(__xludf.DUMMYFUNCTION("F11"),"") | N70: =N11 -> 0
C72: 2 | E72: Authority | M72: =IFERROR(__xludf.DUMMYFUNCTION("F26"),"") | N72: =N26 -> 0
C74: 3 | E74: Reputatie management | M74: =IFERROR(__xludf.DUMMYFUNCTION("F37"),"") | N74: =N37 -> 0
C76: 4 | E76: Content | M76: =IFERROR(__xludf.DUMMYFUNCTION("F48"),"") | N76: =N48 -> 0
C78: 5 | E78: =E60 -> Baseline check | M78: =IFERROR(__xludf.DUMMYFUNCTION("F60"),"") | N78: =N60 -> 0
M79: Total average weighted score | N79: =AVERAGE(N70:N78) -> 0

Sheet Web Analytics
E2: MUST READ: How to use? 1. Only click a checkbox when the topic on the left - is 100% completed 2. Don't check the box if you "just" checked the topic if it was applicable 3. The same topic can be in multiple stages (different levels of maturity) | F2: FR | G2: NL | H2: DE | I2: BE | J2: UK | K2: US | L2: IT | M2: Adaptation topics (V) | N2: Topics not finalized (X) | P2: Last updated at 22/09/2023 by Nadiia Kolesnyk
F3: TRUE | G3: TRUE | H3: TRUE | I3: TRUE | J3: TRUE | K3: TRUE | L3: TRUE | M3: =(COUNTIF(F:L,TRUE))-COUNTIF(F3:L3,true) -> 0 | N3: =COUNTIF(F:L,FALSE) -> 511
B4: =N123 -> 0 | F4: =COUNTIF(F:F,TRUE)-1 -> 0 | G4: =COUNTIF(G:G,TRUE)-1 -> 0 | H4: =COUNTIF(H:H,TRUE)-1 -> 0 | I4: =COUNTIF(I:I,TRUE)-1 -> 0 | J4: =COUNTIF(J:J,TRUE)-1 -> 0 | K4: =COUNTIF(K:K,TRUE)-1 -> 0 | L4: =COUNTIF(L:L,TRUE)-1 -> 0
F6: =COUNTIF(F:F,FALSE) -> 73 | G6: =COUNTIF(G:G,FALSE) -> 73 | H6: =COUNTIF(H:H,FALSE) -> 73 | I6: =COUNTIF(I:I,FALSE) -> 73 | J6: =COUNTIF(J:J,FALSE) -> 73 | K6: =COUNTIF(K:K,FALSE) -> 73 | L6: =COUNTIF(L:L,FALSE) -> 73
C8: Maturity | D8: # | E8: Topics | F8: FR | G8: NL | H8: DE | I8: BE | J8: UK | K8: US | L8: IT | M8: Details | N8: Comments / Action
E9: If a topic is not relevant for the client - delete the checkbox | F9: Only check a box if the topic is fully integrated | M9: Explain what the issue is if not checked | N9: What would be the next steps to finalize the topic
B10: 1
C11: Tracking coverage | F11: =IFERROR(__xludf.DUMMYFUNCTION("SPARKLINE(COUNTIF(F13:L20,TRUE),{""charttype"",""bar"";""max"",COUNTA(F13:L20);""color1"",""green""})"),"") | N11: =COUNTIF(F13:L20,TRUE)/COUNTA(F13:L20) -> 0 | P11: Commentbox for feedback
B13: =COUNTIF(F13:L18,TRUE)/COUNTA(F13:L18) -> 0 | C13: Basic | D13: 1 | E13: Tracking code installed on all pages (check for Pages / Screens without tracking code) | F13: FALSE | G13: FALSE | H13: FALSE | I13: FALSE | J13: FALSE | K13: FALSE | L13: FALSE | N13: =IFERROR(SWITCH(M13,"fail",0,"pass with recommendations",(#REF!*0.5),"pass",(#REF!*1),"n/a",""),"")
D14: 2 | E14: Code added to 404 pages | F14: FALSE | G14: FALSE | H14: FALSE | I14: FALSE | J14: FALSE | K14: FALSE | L14: FALSE | N14: =IFERROR(SWITCH(M14,"fail",0,"pass with recommendations",(#REF!*0.5),"pass",(#REF!*1),"n/a",""),"")
D15: 3 | E15: GA4 is installed via GTM | F15: FALSE | G15: FALSE | H15: FALSE | I15: FALSE | J15: FALSE | K15: FALSE | L15: FALSE | N15: =IFERROR(SWITCH(M15,"fail",0,"pass with recommendations",(#REF!*0.5),"pass",(#REF!*1),"n/a",""),"")
D16: 4 | E16: Correct DataLayer | F16: FALSE | G16: FALSE | H16: FALSE | I16: FALSE | J16: FALSE | K16: FALSE | L16: FALSE | N16: =IFERROR(SWITCH(M16,"fail",0,"pass with recommendations",(#REF!*0.5),"pass",(#REF!*1),"n/a",""),"")
D17: 5 | E17: Tracking code is in correct place in source code | F17: FALSE | G17: FALSE | H17: FALSE | I17: FALSE | J17: FALSE | K17: FALSE | L17: FALSE | N17: =IFERROR(SWITCH(M17,"fail",0,"pass with recommendations",(#REF!*0.5),"pass",(#REF!*1),"n/a",""),"")
D18: 6 | E18: Verify that you are receiving the analytics data in your reports | F18: FALSE | G18: FALSE | H18: FALSE | I18: FALSE | J18: FALSE | K18: FALSE | L18: FALSE | N18: =IFERROR(SWITCH(M18,"fail",0,"pass with recommendations",(#REF!*0.5),"pass",(#REF!*1),"n/a",""),"")
B19: =COUNTIF(F19:L19,TRUE)/COUNTA(F19:L19) -> 0 | C19: Advanced | D19: 7 | E19: No traffic from unexpected domains (test domains, other sites, etc.) | F19: FALSE | G19: FALSE | H19: FALSE | I19: FALSE | J19: FALSE | K19: FALSE | L19: FALSE | N19: =IFERROR(SWITCH(M19,"fail",0,"pass with recommendations",(#REF!*0.5),"pass",(#REF!*1),"n/a",""),"")
B20: =COUNTIF(F20:L20,TRUE)/COUNTA(F20:L20) -> 0 | C20: Expert | D20: 8 | E20: Conset banner is added and works correctly | F20: FALSE | G20: FALSE | H20: FALSE | I20: FALSE | J20: FALSE | K20: FALSE | L20: FALSE | N20: =IFERROR(SWITCH(M20,"fail",0,"pass with recommendations",(#REF!*0.5),"pass",(#REF!*1),"n/a",""),"")
B21: 2
C22: Property settings | F22: =IFERROR(__xludf.DUMMYFUNCTION("SPARKLINE(COUNTIF(F24:L41,TRUE),{""charttype"",""bar"";""max"",COUNTA(F24:L41);""color1"",""green""})"),"") | N22: =COUNTIF(F24:L41,TRUE)/COUNTA(F24:L41) -> 0
B24: =COUNTIF(F24:L29,TRUE)/COUNTA(F24:L29) -> 0 | C24: Basic | D24: 1 | E24: Property name | F24: FALSE | G24: FALSE | H24: FALSE | I24: FALSE | J24: FALSE | K24: FALSE | L24: FALSE | N24: =IFERROR(SWITCH(M24,"fail",0,"pass with recommendations",(#REF!*0.5),"pass",(#REF!*1),"n/a",""),"")
D25: 2 | E25: Right subproperty names | F25: FALSE | G25: FALSE | H25: FALSE | I25: FALSE | J25: FALSE | K25: FALSE | L25: FALSE | N25: =IFERROR(SWITCH(M25,"fail",0,"pass with recommendations",(#REF!*0.5),"pass",(#REF!*1),"n/a",""),"")
D26: 3 | E26: Correct industry category | F26: FALSE | G26: FALSE | H26: FALSE | I26: FALSE | J26: FALSE | K26: FALSE | L26: FALSE | N26: =IFERROR(SWITCH(M26,"fail",0,"pass with recommendations",(#REF!*0.5),"pass",(#REF!*1),"n/a",""),"")
D27: 4 | E27: Correct time zone settings | F27: FALSE | G27: FALSE | H27: FALSE | I27: FALSE | J27: FALSE | K27: FALSE | L27: FALSE | N27: =IFERROR(SWITCH(M27,"fail",0,"pass with recommendations",(#REF!*0.5),"pass",(#REF!*1),"n/a",""),"")
D28: 5 | E28: Correct currency settings | F28: FALSE | G28: FALSE | H28: FALSE | I28: FALSE | J28: FALSE | K28: FALSE | L28: FALSE | N28: =IFERROR(SWITCH(M28,"fail",0,"pass with recommendations",(#REF!*0.5),"pass",(#REF!*1),"n/a",""),"")
D29: 6 | E29: Correct users roles; no users outside of organisation | F29: FALSE | G29: FALSE | H29: FALSE | I29: FALSE | J29: FALSE | K29: FALSE | L29: FALSE
B30: =COUNTIF(F30:L37,TRUE)/COUNTA(F30:L37) -> 0 | C30: Advanced | D30: 7 | E30: Google Signals are enabled (adjusted with privacy policy) | F30: FALSE | G30: FALSE | H30: FALSE | I30: FALSE | J30: FALSE | K30: FALSE | L30: FALSE | N30: =IFERROR(SWITCH(M30,"fail",0,"pass with recommendations",(#REF!*0.5),"pass",(#REF!*1),"n/a",""),"")
D31: 8 | E31: Granular location and device data collection is allowed in all regions | F31: FALSE | G31: FALSE | H31: FALSE | I31: FALSE | J31: FALSE | K31: FALSE | L31: FALSE | N31: =IFERROR(SWITCH(M31,"fail",0,"pass with recommendations",(#REF!*0.5),"pass",(#REF!*1),"n/a",""),"")
D32: 9 | E32: Ads personalisation is allowed in all regions | F32: FALSE | G32: FALSE | H32: FALSE | I32: FALSE | J32: FALSE | K32: FALSE | L32: FALSE | N32: =IFERROR(SWITCH(M32,"fail",0,"pass with recommendations",(#REF!*0.5),"pass",(#REF!*1),"n/a",""),"")
D33: 10 | E33: User data collection acknowledgement | F33: FALSE | G33: FALSE | H33: FALSE | I33: FALSE | J33: FALSE | K33: FALSE | L33: FALSE | N33: =IFERROR(SWITCH(M33,"fail",0,"pass with recommendations",(#REF!*0.5),"pass",(#REF!*1),"n/a",""),"")
D34: 11 | E34: Correct terms in data retention | F34: FALSE | G34: FALSE | H34: FALSE | I34: FALSE | J34: FALSE | K34: FALSE | L34: FALSE | N34: =IFERROR(SWITCH(M34,"fail",0,"pass with recommendations",(#REF!*0.5),"pass",(#REF!*1),"n/a",""),"")
D35: 12 | E35: The Reporting Attribution in the Attribution Settings is correct | F35: FALSE | G35: FALSE | H35: FALSE | I35: FALSE | J35: FALSE | K35: FALSE | L35: FALSE | N35: =IFERROR(SWITCH(M35,"fail",0,"pass with recommendations",(#REF!*0.5),"pass",(#REF!*1),"n/a",""),"")
D36: 13 | E36: Are Acquisition Conversion Events in the Attribution Settings is correct | F36: FALSE | G36: FALSE | H36: FALSE | I36: FALSE | J36: FALSE | K36: FALSE | L36: FALSE | N36: =IFERROR(SWITCH(M36,"fail",0,"pass with recommendations",(#REF!*0.5),"pass",(#REF!*1),"n/a",""),"")
D37: 14 | E37: All Other Conversion Events in the Attribution Settings are correct | F37: FALSE | G37: FALSE | H37: FALSE | I37: FALSE | J37: FALSE | K37: FALSE | L37: FALSE | N37: =IFERROR(SWITCH(M37,"fail",0,"pass with recommendations",(#REF!*0.5),"pass",(#REF!*1),"n/a",""),"")
B38: =COUNTIF(F38:L39,TRUE)/COUNTA(F38:L39) -> 0 | C38: Expert | D38: 15 | E38: Added data filters, they are working correctly | F38: FALSE | G38: FALSE | H38: FALSE | I38: FALSE | J38: FALSE | K38: FALSE | L38: FALSE | N38: =IFERROR(SWITCH(M38,"fail",0,"pass with recommendations",(#REF!*0.5),"pass",(#REF!*1),"n/a",""),"")
D39: 16 | E39: Cookie-overriding settings are added | F39: FALSE | G39: FALSE | H39: FALSE | I39: FALSE | J39: FALSE | K39: FALSE | L39: FALSE | N39: =IFERROR(SWITCH(M39,"fail",0,"pass with recommendations",(#REF!*0.5),"pass",(#REF!*1),"n/a",""),"")
B40: =COUNTIF(F40:L41,TRUE)/COUNTA(F40:L41) -> 0 | C40: Champion | D40: 17 | E40: Data import is enabled | F40: FALSE | G40: FALSE | H40: FALSE | I40: FALSE | J40: FALSE | K40: FALSE | L40: FALSE
D41: 18 | E41: Measurement Protocol API secrets are created (if applicable) | F41: FALSE | G41: FALSE | H41: FALSE | I41: FALSE | J41: FALSE | K41: FALSE | L41: FALSE
B42: 3
C43: Product links | F43: =IFERROR(__xludf.DUMMYFUNCTION("SPARKLINE(COUNTIF(F45:L49,TRUE),{""charttype"",""bar"";""max"",COUNTA(F45:L49);""color1"",""green""})"),"") | N43: =COUNTIF(F45:L49,TRUE)/COUNTA(F45:L49) -> 0
B45: =COUNTIF(F45:L50,TRUE)/COUNTA(F45:L50) -> 0 | C45: Basic | D45: 1 | E45: Correct Google Ads account is linked | F45: FALSE | G45: FALSE | H45: FALSE | I45: FALSE | J45: FALSE | K45: FALSE | L45: FALSE | N45: =IFERROR(SWITCH(M45,"fail",0,"pass with recommendations",(#REF!*0.5),"pass",(#REF!*1),"n/a",""),"")
D46: 2 | E46: BigQuery connnection | F46: FALSE | G46: FALSE | H46: FALSE | I46: FALSE | J46: FALSE | K46: FALSE | L46: FALSE | N46: =IFERROR(SWITCH(M46,"fail",0,"pass with recommendations",(#REF!*0.5),"pass",(#REF!*1),"n/a",""),"")
D47: 3 | E47: Search Console | F47: FALSE | G47: FALSE | H47: FALSE | I47: FALSE | J47: FALSE | K47: FALSE | L47: FALSE | N47: =IFERROR(SWITCH(M47,"fail",0,"pass with recommendations",(#REF!*0.5),"pass",(#REF!*1),"n/a",""),"")
D48: 4 | E48: DV360 connection | F48: FALSE | G48: FALSE | H48: FALSE | I48: FALSE | J48: FALSE | K48: FALSE | L48: FALSE | N48: =IFERROR(SWITCH(M48,"fail",0,"pass with recommendations",(#REF!*0.5),"pass",(#REF!*1),"n/a",""),"")
D49: 5 | E49: Other connections | F49: FALSE | G49: FALSE | H49: FALSE | I49: FALSE | J49: FALSE | K49: FALSE | L49: FALSE | N49: =IFERROR(SWITCH(M49,"fail",0,"pass with recommendations",(#REF!*0.5),"pass",(#REF!*1),"n/a",""),"")
B50: 4
C51: Data Stream settings | F51: =IFERROR(__xludf.DUMMYFUNCTION("SPARKLINE(COUNTIF(F53:L67,TRUE),{""charttype"",""bar"";""max"",COUNTA(F53:L67);""color1"",""green""})"),"") | N51: =COUNTIF(F53:L67,TRUE)/COUNTA(F53:L67) -> 0
B53: =COUNTIF(F53:L60,TRUE)/COUNTA(F53:L60) -> 0 | C53: Basic | D53: 1 | E53: Does the data stream have a unique and logical name | F53: FALSE | G53: FALSE | H53: FALSE | I53: FALSE | J53: FALSE | K53: FALSE | L53: FALSE | N53: =IFERROR(SWITCH(M53,"fail",0,"pass with recommendations",(#REF!*0.5),"pass",(#REF!*1),"n/a",""),"")
D54: 2 | E54: Enhanced measurement is enabled: | F54: FALSE | G54: FALSE | H54: FALSE | I54: FALSE | J54: FALSE | K54: FALSE | L54: FALSE | N54: =IFERROR(SWITCH(M54,"fail",0,"pass with recommendations",(#REF!*0.5),"pass",(#REF!*1),"n/a",""),"")
D55: 3 | E55: - Page changes based on the browser history events is enabled (for SPA). Works correctly | F55: FALSE | G55: FALSE | H55: FALSE | I55: FALSE | J55: FALSE | K55: FALSE | L55: FALSE | N55: =IFERROR(SWITCH(M55,"fail",0,"pass with recommendations",(#REF!*0.5),"pass",(#REF!*1),"n/a",""),"")
D56: 4 | E56: - scroll tracking | F56: FALSE | G56: FALSE | H56: FALSE | I56: FALSE | J56: FALSE | K56: FALSE | L56: FALSE | N56: =IFERROR(SWITCH(M56,"fail",0,"pass with recommendations",(#REF!*0.5),"pass",(#REF!*1),"n/a",""),"")
D57: 5 | E57: - otbound click tracking works correctly | F57: FALSE | G57: FALSE | H57: FALSE | I57: FALSE | J57: FALSE | K57: FALSE | L57: FALSE | N57: =IFERROR(SWITCH(M57,"fail",0,"pass with recommendations",(#REF!*0.5),"pass",(#REF!*1),"n/a",""),"")
D58: 6 | E58: - search term query parameters are added | F58: FALSE | G58: FALSE | H58: FALSE | I58: FALSE | J58: FALSE | K58: FALSE | L58: FALSE | N58: =IFERROR(SWITCH(M58,"fail",0,"pass with recommendations",(#REF!*0.5),"pass",(#REF!*1),"n/a",""),"")
D59: 7 | E59: - Youtube API is enabled | F59: FALSE | G59: FALSE | H59: FALSE | I59: FALSE | J59: FALSE | K59: FALSE | L59: FALSE | N59: =IFERROR(SWITCH(M59,"fail",0,"pass with recommendations",(#REF!*0.5),"pass",(#REF!*1),"n/a",""),"")
D60: 8 | E60: - file downloads | F60: FALSE | G60: FALSE | H60: FALSE | I60: FALSE | J60: FALSE | K60: FALSE | L60: FALSE | N60: =IFERROR(SWITCH(M60,"fail",0,"pass with recommendations",(#REF!*0.5),"pass",(#REF!*1),"n/a",""),"")
B61: =COUNTIF(F61:L63,TRUE)/COUNTA(F61:L63) -> 0 | C61: Advanced | D61: 9 | E61: Referral exclusion list is created: | F61: FALSE | G61: FALSE | H61: FALSE | I61: FALSE | J61: FALSE | K61: FALSE | L61: FALSE | N61: =IFERROR(SWITCH(M61,"fail",0,"pass with recommendations",(#REF!*0.5),"pass",(#REF!*1),"n/a",""),"")
D62: 10 | E62: - self referrals are excluded | F62: FALSE | G62: FALSE | H62: FALSE | I62: FALSE | J62: FALSE | K62: FALSE | L62: FALSE | N62: =IFERROR(SWITCH(M62,"fail",0,"pass with recommendations",(#REF!*0.5),"pass",(#REF!*1),"n/a",""),"")
D63: 11 | E63: - payment systems are excluded | F63: FALSE | G63: FALSE | H63: FALSE | I63: FALSE | J63: FALSE | K63: FALSE | L63: FALSE | N63: =IFERROR(SWITCH(M63,"fail",0,"pass with recommendations",(#REF!*0.5),"pass",(#REF!*1),"n/a",""),"")
B64: =COUNTIF(F64:L66,TRUE)/COUNTA(F64:L66) -> 0 | C64: Expert | D64: 12 | E64: Internal traffic defined correctly | F64: FALSE | G64: FALSE | H64: FALSE | I64: FALSE | J64: FALSE | K64: FALSE | L64: FALSE | N64: =IFERROR(SWITCH(M64,"fail",0,"pass with recommendations",(#REF!*0.5),"pass",(#REF!*1),"n/a",""),"")
D65: 13 | E65: Adjust session timeout | F65: FALSE | G65: FALSE | H65: FALSE | I65: FALSE | J65: FALSE | K65: FALSE | L65: FALSE | N65: =IFERROR(SWITCH(M65,"fail",0,"pass with recommendations",(#REF!*0.5),"pass",(#REF!*1),"n/a",""),"")
D66: 14 | E66: - adjust engaged session timeout | F66: FALSE | G66: FALSE | H66: FALSE | I66: FALSE | J66: FALSE | K66: FALSE | L66: FALSE | N66: =IFERROR(SWITCH(M66,"fail",0,"pass with recommendations",(#REF!*0.5),"pass",(#REF!*1),"n/a",""),"")
B67: =COUNTIF(F67:L67,TRUE)/COUNTA(F67:L67) -> 0 | C67: Champion | D67: 15 | E67: Cross-domain tracking is setted up | F67: FALSE | G67: FALSE | H67: FALSE | I67: FALSE | J67: FALSE | K67: FALSE | L67: FALSE | N67: =IFERROR(SWITCH(M67,"fail",0,"pass with recommendations",(#REF!*0.5),"pass",(#REF!*1),"n/a",""),"")
B68: 5
C69: Reporting Interface + Data Quality | F69: =IFERROR(__xludf.DUMMYFUNCTION("SPARKLINE(COUNTIF(F71:L97,TRUE),{""charttype"",""bar"";""max"",COUNTA(F71:L97);""color1"",""green""})"),"") | N69: =COUNTIF(F71:L97,TRUE)/COUNTA(F71:L97) -> 0
B71: =COUNTIF(F71:F80,TRUE)/COUNTA(E71:E80) -> 0 | C71: Basic | D71: 1 | E71: Property receives traffic (the amount of traffic is adequate, there are no unexpected drops or increases in traffic.) | F71: FALSE | G71: FALSE | H71: FALSE | I71: FALSE | J71: FALSE | K71: FALSE | L71: FALSE | N71: =IFERROR(SWITCH(M71,"fail",0,"pass with recommendations",(#REF!*0.5),"pass",(#REF!*1),"n/a",""),"")
D72: 2 | E72: Custom events are setted up | F72: FALSE | G72: FALSE | H72: FALSE | I72: FALSE | J72: FALSE | K72: FALSE | L72: FALSE | N72: =IFERROR(SWITCH(M72,"fail",0,"pass with recommendations",(#REF!*0.5),"pass",(#REF!*1),"n/a",""),"")
D73: 3 | E73: Conversions are setted up | F73: FALSE | G73: FALSE | H73: FALSE | I73: FALSE | J73: FALSE | K73: FALSE | L73: FALSE | N73: =IFERROR(SWITCH(M73,"fail",0,"pass with recommendations",(#REF!*0.5),"pass",(#REF!*1),"n/a",""),"")
D74: 4 | E74: Sources are attributed to the correct channels | F74: FALSE | G74: FALSE | H74: FALSE | I74: FALSE | J74: FALSE | K74: FALSE | L74: FALSE | N74: =IFERROR(SWITCH(M74,"fail",0,"pass with recommendations",(#REF!*0.5),"pass",(#REF!*1),"n/a",""),"")
D75: 5 | E75: Audiences are created | F75: FALSE | G75: FALSE | H75: FALSE | I75: FALSE | J75: FALSE | K75: FALSE | L75: FALSE | N75: =IFERROR(SWITCH(M75,"fail",0,"pass with recommendations",(#REF!*0.5),"pass",(#REF!*1),"n/a",""),"")
D76: 6 | E76: - organic searches are not tracked as referrals | F76: FALSE | G76: FALSE | H76: FALSE | I76: FALSE | J76: FALSE | K76: FALSE | L76: FALSE | N76: =IFERROR(SWITCH(M76,"fail",0,"pass with recommendations",(#REF!*0.5),"pass",(#REF!*1),"n/a",""),"")
D77: 7 | E77: - payment systems are not tracked as referrals | F77: FALSE | G77: FALSE | H77: FALSE | I77: FALSE | J77: FALSE | K77: FALSE | L77: FALSE | N77: =IFERROR(SWITCH(M77,"fail",0,"pass with recommendations",(#REF!*0.5),"pass",(#REF!*1),"n/a",""),"")
D78: 8 | E78: - correct direct traffic | F78: FALSE | G78: FALSE | H78: FALSE | I78: FALSE | J78: FALSE | K78: FALSE | L78: FALSE
D79: 9 | E79: - social traffic is attributed to correct channel | F79: FALSE | G79: FALSE | H79: FALSE | I79: FALSE | J79: FALSE | K79: FALSE | L79: FALSE | N79: =IFERROR(SWITCH(M79,"fail",0,"pass with recommendations",(#REF!*0.5),"pass",(#REF!*1),"n/a",""),"")
D80: 10 | E80: No personal information (phone, email etc) | F80: FALSE | G80: FALSE | H80: FALSE | I80: FALSE | J80: FALSE | K80: FALSE | L80: FALSE | N80: =IFERROR(SWITCH(M80,"fail",0,"pass with recommendations",(#REF!*0.5),"pass",(#REF!*1),"n/a",""),"")
B81: =COUNTIF(F81:F91,TRUE)/COUNTA(E81:E91) -> 0 | C81: Advanced | D81: 11 | E81: The currency is displayed correctly | F81: FALSE | G81: FALSE | H81: FALSE | I81: FALSE | J81: FALSE | K81: FALSE | L81: FALSE | N81: =IFERROR(SWITCH(M81,"fail",0,"pass with recommendations",(#REF!*0.5),"pass",(#REF!*1),"n/a",""),"")
D82: 12 | E82: - the Add To Cart Rate a healthy number | F82: FALSE | G82: FALSE | H82: FALSE | I82: FALSE | J82: FALSE | K82: FALSE | L82: FALSE | N82: =IFERROR(SWITCH(M82,"fail",0,"pass with recommendations",(#REF!*0.5),"pass",(#REF!*1),"n/a",""),"")
D83: 13 | E83: Custom metrics are configured | F83: FALSE | G83: FALSE | H83: FALSE | I83: FALSE | J83: FALSE | K83: FALSE | L83: FALSE | N83: =IFERROR(SWITCH(M83,"fail",0,"pass with recommendations",(#REF!*0.5),"pass",(#REF!*1),"n/a",""),"")
D84: 14 | E84: Cutsom Channel Grouping is created | F84: FALSE | G84: FALSE | H84: FALSE | I84: FALSE | J84: FALSE | K84: FALSE | L84: FALSE
D85: 15 | E85: User id is setted up | F85: FALSE | G85: FALSE | H85: FALSE | I85: FALSE | J85: FALSE | K85: FALSE | L85: FALSE
D86: 16 | E86: Custom dimensions are configured | F86: FALSE | G86: FALSE | H86: FALSE | I86: FALSE | J86: FALSE | K86: FALSE | L86: FALSE
D87: 17 | E87: Enhanced ecommerce reporting is configured | F87: FALSE | G87: FALSE | H87: FALSE | I87: FALSE | J87: FALSE | K87: FALSE | L87: FALSE | N87: =IFERROR(SWITCH(M87,"fail",0,"pass with recommendations",(#REF!*0.5),"pass",(#REF!*1),"n/a",""),"")
D88: 18 | E88: Does the client know what the hard and soft KPI's of the website are and is this clearly defined? | F88: FALSE | G88: FALSE | H88: FALSE | I88: FALSE | J88: FALSE | K88: FALSE | L88: FALSE
D89: 19 | E89: - all needed events are tracked | F89: FALSE | G89: FALSE | H89: FALSE | I89: FALSE | J89: FALSE | K89: FALSE | L89: FALSE | N89: =IFERROR(SWITCH(M89,"fail",0,"pass with recommendations",(#REF!*0.5),"pass",(#REF!*1),"n/a",""),"")
D90: 20 | E90: - number of events in checkout funnel is logical (step 1 is bigger than step 2; number of checkouts is higher than number of purchases, etc) | F90: FALSE | G90: FALSE | H90: FALSE | I90: FALSE | J90: FALSE | K90: FALSE | L90: FALSE | N90: =IFERROR(SWITCH(M90,"fail",0,"pass with recommendations",(#REF!*0.5),"pass",(#REF!*1),"n/a",""),"")
D91: 21 | E91: - the transaction rate a healthy number | F91: FALSE | G91: FALSE | H91: FALSE | I91: FALSE | J91: FALSE | K91: FALSE | L91: FALSE | N91: =IFERROR(SWITCH(M91,"fail",0,"pass with recommendations",(#REF!*0.5),"pass",(#REF!*1),"n/a",""),"")
B92: =COUNTIF(F92:L93,TRUE)/COUNTA(F92:L93) -> 0 | C92: Expert | D92: 22 | E92: Returns are being tracked | F92: FALSE | G92: FALSE | H92: FALSE | I92: FALSE | J92: FALSE | K92: FALSE | L92: FALSE | N92: =IFERROR(SWITCH(M92,"fail",0,"pass with recommendations",(#REF!*0.5),"pass",(#REF!*1),"n/a",""),"")
D93: 23 | E93: Content groups are setted up | F93: FALSE | G93: FALSE | H93: FALSE | I93: FALSE | J93: FALSE | K93: FALSE | L93: FALSE | N93: =IFERROR(SWITCH(M93,"fail",0,"pass with recommendations",(#REF!*0.5),"pass",(#REF!*1),"n/a",""),"")
B94: =COUNTIF(F94:L97,TRUE)/COUNTA(F94:L97) -> 0 | C94: Champion | D94: 24 | E94: Is the data enrichment parameter timestamp being collected? | F94: FALSE | G94: FALSE | H94: FALSE | I94: FALSE | J94: FALSE | K94: FALSE | L94: FALSE | N94: =IFERROR(SWITCH(M94,"fail",0,"pass with recommendations",(#REF!*0.5),"pass",(#REF!*1),"n/a",""),"")
D95: 25 | E95: Is the data enrichment parameter consent parameters being collected? | F95: FALSE | G95: FALSE | H95: FALSE | I95: FALSE | J95: FALSE | K95: FALSE | L95: FALSE | N95: =IFERROR(SWITCH(M95,"fail",0,"pass with recommendations",(#REF!*0.5),"pass",(#REF!*1),"n/a",""),"")
D96: 26 | E96: Is the data enrichment parameter client-id being collected? | F96: FALSE | G96: FALSE | H96: FALSE | I96: FALSE | J96: FALSE | K96: FALSE | L96: FALSE | N96: =IFERROR(SWITCH(M96,"fail",0,"pass with recommendations",(#REF!*0.5),"pass",(#REF!*1),"n/a",""),"")
D97: 27 | E97: Is the data enrichment parameter login status being collected? | F97: FALSE | G97: FALSE | H97: FALSE | I97: FALSE | J97: FALSE | K97: FALSE | L97: FALSE | N97: =IFERROR(SWITCH(M97,"fail",0,"pass with recommendations",(#REF!*0.5),"pass",(#REF!*1),"n/a",""),"")
B99: SUMMARY (relevance to be adjusted to client needs) | P99: << in the column on the left you can decide if a certain topic is more or less important compared to others - to decide how important it is for the total score of a client Example given: Feed management is not always relevant for a company (B2B). You can give the relevance a score of 0 and it won't be calculated in the total average score Default setting: all topics at 100%
E101: Topic | F101: Topic relevance 0-100% | N101: Total score
C103: 1 | E103: =C11 -> Tracking coverage | F103: 1 | M103: =IFERROR(__xludf.DUMMYFUNCTION("F11"),"") | N103: =N11 -> 0
C105: 2 | E105: =C22 -> Property settings | F105: 1 | M105: =IFERROR(__xludf.DUMMYFUNCTION("F22"),"") | N105: =N22 -> 0
C107: 3 | E107: =C43 -> Product links | F107: 1 | M107: =IFERROR(__xludf.DUMMYFUNCTION("F43"),"") | N107: =N43 -> 0
C109: 4 | E109: =C51 -> Data Stream settings | F109: 1 | M109: =IFERROR(__xludf.DUMMYFUNCTION("F51"),"") | N109: =N51 -> 0
C111: 5 | E111: =C69 -> Reporting Interface + Data Quality | F111: 1 | M111: =IFERROR(__xludf.DUMMYFUNCTION("F69"),"") | N111: =N69 -> 0
C113: 6
C115: 7
C117: 8
C119: 9
...

Sheet DV360
E2: MUST READ: How to use? 1. Only click a checkbox when the topic on the left - is 100% completed 2. Don't check the box if you "just" checked the topic if it was applicable 3. The same topic can be in multiple stages (different levels of maturity) | F2: FR | G2: NL | H2: DE | I2: BE | J2: UK | K2: US | L2: IT | M2: Adaptation topics (V) | N2: Topics not finalized (X) | P2: Last updated at 15/11/2023 by Daniel Ferreira
F3: TRUE | G3: TRUE | H3: TRUE | I3: TRUE | J3: TRUE | K3: TRUE | L3: TRUE | M3: =(COUNTIF(F:L,TRUE))-COUNTIF(F3:L3,true) -> 0 | N3: =COUNTIF(F:L,FALSE) -> 322
B4: =N99 -> 0 | F4: =COUNTIF(F:F,TRUE)-1 -> 0 | G4: =COUNTIF(G:G,TRUE)-1 -> 0 | H4: =COUNTIF(H:H,TRUE)-1 -> 0 | I4: =COUNTIF(I:I,TRUE)-1 -> 0 | J4: =COUNTIF(J:J,TRUE)-1 -> 0 | K4: =COUNTIF(K:K,TRUE)-1 -> 0 | L4: =COUNTIF(L:L,TRUE)-1 -> 0
F6: =COUNTIF(F:F,FALSE) -> 46 | G6: =COUNTIF(G:G,FALSE) -> 46 | H6: =COUNTIF(H:H,FALSE) -> 46 | I6: =COUNTIF(I:I,FALSE) -> 46 | J6: =COUNTIF(J:J,FALSE) -> 46 | K6: =COUNTIF(K:K,FALSE) -> 46 | L6: =COUNTIF(L:L,FALSE) -> 46
C8: Maturity | D8: # | E8: Topics | F8: FR | G8: NL | H8: DE | I8: BE | J8: UK | K8: US | L8: IT | M8: Details | N8: Comments / Action
E9: If a topic is not relevant for the client - delete the checkbox | F9: Only check a box if the topic is fully integrated | M9: Explain what the issue is if not checked | N9: What would be the next steps to finalize the topic
B10: 1
C11: Campaign setup | F11: =IFERROR(__xludf.DUMMYFUNCTION("SPARKLINE(COUNTIF(F13:L24,TRUE),{""charttype"",""bar"";""max"",COUNTA(F13:L24);""color1"",""green""})"),"") | N11: =COUNTIF(F13:L24,TRUE)/COUNTA(F13:L24) -> 0
B13: =COUNTIF(F13:L16,TRUE)/COUNTA(F13:L16) -> 0 | C13: Basic | D13: 1 | E13: Single campaign setup (built&forget) | F13: FALSE | G13: FALSE | H13: FALSE | I13: FALSE | J13: FALSE | K13: FALSE | L13: FALSE | M13: =IFERROR(SWITCH(F13,"fail",0,"pass with recommendations",(#REF!*0.5),"pass",(#REF!*1),"n/a",""),"") | N13: =IFERROR(SWITCH(M13,"fail",0,"pass with recommendations",(#REF!*0.5),"pass",(#REF!*1),"n/a",""),"") | P13: Comment box:
D14: 2 | E14: Creating a inclusion or exclusion list | F14: FALSE | G14: FALSE | H14: FALSE | I14: FALSE | J14: FALSE | K14: FALSE | L14: FALSE | P14: Please ad topics which we have missed over here so we can add them in a later stage
D15: 3 | E15: Frequency management | F15: FALSE | G15: FALSE | H15: FALSE | I15: FALSE | J15: FALSE | K15: FALSE | L15: FALSE
D16: 4 | E16: Pacing management | F16: FALSE | G16: FALSE | H16: FALSE | I16: FALSE | J16: FALSE | K16: FALSE | L16: FALSE | M16: =IFERROR(SWITCH(F16,"fail",0,"pass with recommendations",(#REF!*0.5),"pass",(#REF!*1),"n/a",""),"") | N16: =IFERROR(SWITCH(M16,"fail",0,"pass with recommendations",(#REF!*0.5),"pass",(#REF!*1),"n/a",""),"")
B17: =COUNTIF(F17:L20,TRUE)/COUNTA(F17:L20) -> 0 | C17: Advanced | D17: 5 | E17: Accurate budget management between Campaign, IO, Line items | F17: FALSE | G17: FALSE | H17: FALSE | I17: FALSE | J17: FALSE | K17: FALSE | L17: FALSE | M17: =IFERROR(SWITCH(F17,"fail",0,"pass with recommendations",(#REF!*0.5),"pass",(#REF!*1),"n/a",""),"") | N17: =IFERROR(SWITCH(M17,"fail",0,"pass with recommendations",(#REF!*0.5),"pass",(#REF!*1),"n/a",""),"")
D18: 6 | E18: Brand safety settings | F18: FALSE | G18: FALSE | H18: FALSE | I18: FALSE | J18: FALSE | K18: FALSE | L18: FALSE
D19: 7 | E19: Naming convention on Campaign, IO and LI level | F19: FALSE | G19: FALSE | H19: FALSE | I19: FALSE | J19: FALSE | K19: FALSE | L19: FALSE
D20: 8 | E20: Aligned KPI's towards campaign planning | F20: FALSE | G20: FALSE | H20: FALSE | I20: FALSE | J20: FALSE | K20: FALSE | L20: FALSE | M20: =IFERROR(SWITCH(F20,"fail",0,"pass with recommendations",(#REF!*0.5),"pass",(#REF!*1),"n/a",""),"") | N20: =IFERROR(SWITCH(M20,"fail",0,"pass with recommendations",(#REF!*0.5),"pass",(#REF!*1),"n/a",""),"")
B21: =COUNTIF(F21:L22,TRUE)/COUNTA(F21:L22) -> 0 | C21: Expert | D21: 9 | E21: Setup using SDF files | F21: FALSE | G21: FALSE | H21: FALSE | I21: FALSE | J21: FALSE | K21: FALSE | L21: FALSE | M21: =IFERROR(SWITCH(F21,"fail",0,"pass with recommendations",(#REF!*0.5),"pass",(#REF!*1),"n/a",""),"") | N21: =IFERROR(SWITCH(M21,"fail",0,"pass with recommendations",(#REF!*0.5),"pass",(#REF!*1),"n/a",""),"")
D22: 10 | E22: Device targeting strategy | F22: FALSE | G22: FALSE | H22: FALSE | I22: FALSE | J22: FALSE | K22: FALSE | L22: FALSE | M22: =IFERROR(SWITCH(F22,"fail",0,"pass with recommendations",(#REF!*0.5),"pass",(#REF!*1),"n/a",""),"") | N22: =IFERROR(SWITCH(M22,"fail",0,"pass with recommendations",(#REF!*0.5),"pass",(#REF!*1),"n/a",""),"")
B23: =COUNTIF(F23:L24,TRUE)/COUNTA(F23:L24) -> 0 | C23: Champion | D23: 11 | E23: Custom bidding across different campaigns types | F23: FALSE | G23: FALSE | H23: FALSE | I23: FALSE | J23: FALSE | K23: FALSE | L23: FALSE | M23: =IFERROR(SWITCH(F23,"fail",0,"pass with recommendations",(#REF!*0.5),"pass",(#REF!*1),"n/a",""),"") | N23: =IFERROR(SWITCH(M23,"fail",0,"pass with recommendations",(#REF!*0.5),"pass",(#REF!*1),"n/a",""),"")
D24: 12 | E24: A naming convention tool to prevent errors and safeguard convention (e.g.: Grasp) | F24: FALSE | G24: FALSE | H24: FALSE | I24: FALSE | J24: FALSE | K24: FALSE | L24: FALSE | M24: =IFERROR(SWITCH(F24,"fail",0,"pass with recommendations",(#REF!*0.5),"pass",(#REF!*1),"n/a",""),"") | N24: =IFERROR(SWITCH(M24,"fail",0,"pass with recommendations",(#REF!*0.5),"pass",(#REF!*1),"n/a",""),"")
B25: 2
C26: Targeting | F26: =IFERROR(__xludf.DUMMYFUNCTION("SPARKLINE(COUNTIF(F28:L34,TRUE),{""charttype"",""bar"";""max"",COUNTA(F28:L34);""color1"",""green""})"),"") | N26: =COUNTIF(F28:L34,TRUE)/COUNTA(F28:L34) -> 0
B28: =COUNTIF(F28:L29,TRUE)/COUNTA(F28:L29) -> 0 | C28: Basic | D28: 1 | E28: Use of Google predefined audiences for inclusions | F28: FALSE | G28: FALSE | H28: FALSE | I28: FALSE | J28: FALSE | K28: FALSE | L28: FALSE | M28: =IFERROR(SWITCH(F28,"fail",0,"pass with recommendations",(#REF!*0.5),"pass",(#REF!*1),"n/a",""),"") | N28: =IFERROR(SWITCH(M28,"fail",0,"pass with recommendations",(#REF!*0.5),"pass",(#REF!*1),"n/a",""),"")
D29: 2 | E29: Use of Google predefined audiences for exclusions | F29: FALSE | G29: FALSE | H29: FALSE | I29: FALSE | J29: FALSE | K29: FALSE | L29: FALSE
B30: =COUNTIF(F30:L32,TRUE)/COUNTA(F30:L32) -> 0 | C30: Advanced | D30: 3 | E30: Working with (local) publishing deals | F30: FALSE | G30: FALSE | H30: FALSE | I30: FALSE | J30: FALSE | K30: FALSE | L30: FALSE | M30: =IFERROR(SWITCH(F30,"fail",0,"pass with recommendations",(#REF!*0.5),"pass",(#REF!*1),"n/a",""),"") | N30: =IFERROR(SWITCH(M30,"fail",0,"pass with recommendations",(#REF!*0.5),"pass",(#REF!*1),"n/a",""),"")
D31: 4 | E31: Work with extended uses of first party audiences | F31: FALSE | G31: FALSE | H31: FALSE | I31: FALSE | J31: FALSE | K31: FALSE | L31: FALSE
D32: 5 | E32: Audience strategy based on local personas | F32: FALSE | G32: FALSE | H32: FALSE | I32: FALSE | J32: FALSE | K32: FALSE | L32: FALSE | M32: =IFERROR(SWITCH(F32,"fail",0,"pass with recommendations",(#REF!*0.5),"pass",(#REF!*1),"n/a",""),"") | N32: =IFERROR(SWITCH(M32,"fail",0,"pass with recommendations",(#REF!*0.5),"pass",(#REF!*1),"n/a",""),"")
B33: =COUNTIF(F33:L33,TRUE)/COUNTA(F33:L33) -> 0 | C33: Expert | D33: 6 | E33: Making use of inentory buying strateg (private deals, guaranteed deals) | F33: FALSE | G33: FALSE | H33: FALSE | I33: FALSE | J33: FALSE | K33: FALSE | L33: FALSE | M33: =IFERROR(SWITCH(F33,"fail",0,"pass with recommendations",(#REF!*0.5),"pass",(#REF!*1),"n/a",""),"") | N33: =IFERROR(SWITCH(M33,"fail",0,"pass with recommendations",(#REF!*0.5),"pass",(#REF!*1),"n/a",""),"")
B34: =COUNTIF(F34:L34,TRUE)/COUNTA(F34:L34) -> 0 | C34: Champion | D34: 7 | E34: Automated input of 1st, 2nd and 3rd party data | F34: FALSE | G34: FALSE | H34: FALSE | I34: FALSE | J34: FALSE | K34: FALSE | L34: FALSE | M34: =IFERROR(SWITCH(F34,"fail",0,"pass with recommendations",(#REF!*0.5),"pass",(#REF!*1),"n/a",""),"") | N34: =IFERROR(SWITCH(M34,"fail",0,"pass with recommendations",(#REF!*0.5),"pass",(#REF!*1),"n/a",""),"")
B35: 3
C36: Conversion & KPIs | F36: =IFERROR(__xludf.DUMMYFUNCTION("SPARKLINE(COUNTIF(F38:L44,TRUE),{""charttype"",""bar"";""max"",COUNTA(F38:L44);""color1"",""green""})"),"") | N36: =COUNTIF(F38:L44,TRUE)/COUNTA(F38:L44) -> 0
B38: =COUNTIF(F38:L39,TRUE)/COUNTA(F38:L39) -> 0 | C38: Basic | D38: 1 | E38: Steer upon appropriate KPI's | F38: FALSE | G38: FALSE | H38: FALSE | I38: FALSE | J38: FALSE | K38: FALSE | L38: FALSE | M38: =IFERROR(SWITCH(F38,"fail",0,"pass with recommendations",(#REF!*0.5),"pass",(#REF!*1),"n/a",""),"") | N38: =IFERROR(SWITCH(M38,"fail",0,"pass with recommendations",(#REF!*0.5),"pass",(#REF!*1),"n/a",""),"")
D39: 2 | E39: Set up basic Floodlight (all pages) | F39: FALSE | G39: FALSE | H39: FALSE | I39: FALSE | J39: FALSE | K39: FALSE | L39: FALSE | M39: =IFERROR(SWITCH(F39,"fail",0,"pass with recommendations",(#REF!*0.5),"pass",(#REF!*1),"n/a",""),"") | N39: =IFERROR(SWITCH(M39,"fail",0,"pass with recommendations",(#REF!*0.5),"pass",(#REF!*1),"n/a",""),"")
B40: =COUNTIF(F40:L41,TRUE)/COUNTA(F40:L41) -> 0 | C40: Advanced | D40: 3 | E40: Set-up conversion floodlights | F40: FALSE | G40: FALSE | H40: FALSE | I40: FALSE | J40: FALSE | K40: FALSE | L40: FALSE | M40: =IFERROR(SWITCH(F40,"fail",0,"pass with recommendations",(#REF!*0.5),"pass",(#REF!*1),"n/a",""),"") | N40: =IFERROR(SWITCH(M40,"fail",0,"pass with recommendations",(#REF!*0.5),"pass",(#REF!*1),"n/a",""),"")
D41: 4 | E41: Set-up Google Analytics events | F41: FALSE | G41: FALSE | H41: FALSE | I41: FALSE | J41: FALSE | K41: FALSE | L41: FALSE | M41: =IFERROR(SWITCH(F41,"fail",0,"pass with recommendations",(#REF!*0.5),"pass",(#REF!*1),"n/a",""),"") | N41: =IFERROR(SWITCH(M41,"fail",0,"pass with recommendations",(#REF!*0.5),"pass",(#REF!*1),"n/a",""),"")
B42: =COUNTIF(F42:L43,TRUE)/COUNTA(F42:L43) -> 0 | C42: Expert | D42: 5 | E42: Soft conversion setup based on different steps of the funnel | F42: FALSE | G42: FALSE | H42: FALSE | I42: FALSE | J42: FALSE | K42: FALSE | L42: FALSE | M42: =IFERROR(SWITCH(F42,"fail",0,"pass with recommendations",(#REF!*0.5),"pass",(#REF!*1),"n/a",""),"") | N42: =IFERROR(SWITCH(M42,"fail",0,"pass with recommendations",(#REF!*0.5),"pass",(#REF!*1),"n/a",""),"")
D43: 6 | E43: Add soft conversions in campaign setup | F43: FALSE | G43: FALSE | H43: FALSE | I43: FALSE | J43: FALSE | K43: FALSE | L43: FALSE | M43: =IFERROR(SWITCH(F43,"fail",0,"pass with recommendations",(#REF!*0.5),"pass",(#REF!*1),"n/a",""),"") | N43: =IFERROR(SWITCH(M43,"fail",0,"pass with recommendations",(#REF!*0.5),"pass",(#REF!*1),"n/a",""),"")
B44: =COUNTIF(F44:L44,TRUE)/COUNTA(F44:L44) -> 0 | C44: Champion | D44: 7 | E44: Enhance bid strategies with CLV, feed- and margin based bids | F44: FALSE | G44: FALSE | H44: FALSE | I44: FALSE | J44: FALSE | K44: FALSE | L44: FALSE | M44: =IFERROR(SWITCH(F44,"fail",0,"pass with recommendations",(#REF!*0.5),"pass",(#REF!*1),"n/a",""),"") | N44: =IFERROR(SWITCH(M44,"fail",0,"pass with recommendations",(#REF!*0.5),"pass",(#REF!*1),"n/a",""),"")
B45: 4
C46: Attribution model | F46: =IFERROR(__xludf.DUMMYFUNCTION("SPARKLINE(COUNTIF(F48:L51,TRUE),{""charttype"",""bar"";""max"",COUNTA(F48:L51);""color1"",""green""})"),"") | N46: =COUNTIF(F48:L51,TRUE)/COUNTA(F48:L51) -> 0
B48: =COUNTIF(F48:L48,TRUE)/COUNTA(F48:L48) -> 0 | C48: Basic | D48: 1 | E48: No attribution model in place | F48: FALSE | G48: FALSE | H48: FALSE | I48: FALSE | J48: FALSE | K48: FALSE | L48: FALSE | M48: =IFERROR(SWITCH(F48,"fail",0,"pass with recommendations",(#REF!*0.5),"pass",(#REF!*1),"n/a",""),"") | N48: =IFERROR(SWITCH(M48,"fail",0,"pass with recommendations",(#REF!*0.5),"pass",(#REF!*1),"n/a",""),"")
B49: =COUNTIF(F49:L49,TRUE)/COUNTA(F49:L49) -> 0 | C49: Advanced | D49: 2 | E49: Start comparing different attribution models | F49: FALSE | G49: FALSE | H49: FALSE | I49: FALSE | J49: FALSE | K49: FALSE | L49: FALSE | M49: =IFERROR(SWITCH(F49,"fail",0,"pass with recommendations",(#REF!*0.5),"pass",(#REF!*1),"n/a",""),"") | N49: =IFERROR(SWITCH(M49,"fail",0,"pass with recommendations",(#REF!*0.5),"pass",(#REF!*1),"n/a",""),"")
B50: =COUNTIF(F50:L50,TRUE)/COUNTA(F50:L50) -> 0 | C50: Expert | D50: 3 | E50: DDA model is in place for DV360 | F50: FALSE | G50: FALSE | H50: FALSE | I50: FALSE | J50: FALSE | K50: FALSE | L50: FALSE | M50: =IFERROR(SWITCH(F50,"fail",0,"pass with recommendations",(#REF!*0.5),"pass",(#REF!*1),"n/a",""),"") | N50: =IFERROR(SWITCH(M50,"fail",0,"pass with recommendations",(#REF!*0.5),"pass",(#REF!*1),"n/a",""),"")
B51: =COUNTIF(F51:L51,TRUE)/COUNTA(F51:L51) -> 0 | C51: Champion | D51: 4 | E51: Custom attribution model (cookieless, statistical) | F51: FALSE | G51: FALSE | H51: FALSE | I51: FALSE | J51: FALSE | K51: FALSE | L51: FALSE | M51: =IFERROR(SWITCH(F51,"fail",0,"pass with recommendations",(#REF!*0.5),"pass",(#REF!*1),"n/a",""),"") | N51: =IFERROR(SWITCH(M51,"fail",0,"pass with recommendations",(#REF!*0.5),"pass",(#REF!*1),"n/a",""),"")
B52: 5
C53: Creatives | F53: =IFERROR(__xludf.DUMMYFUNCTION("SPARKLINE(COUNTIF(F55:L62,TRUE),{""charttype"",""bar"";""max"",COUNTA(F55:L62);""color1"",""green""})"),"") | N53: =COUNTIF(F55:L62,TRUE)/COUNTA(F55:L62) -> 0
B55: =COUNTIF(F55:L56,TRUE)/COUNTA(F55:L56) -> 0 | C55: Basic | D55: 1 | E55: Basic IAB format creatives (static) | F55: FALSE | G55: FALSE | H55: FALSE | I55: FALSE | J55: FALSE | K55: FALSE | L55: FALSE
D56: 2 | E56: Video creatives running (Youtube/ VOD/ Instream/ Outstream) | F56: FALSE | G56: FALSE | H56: FALSE | I56: FALSE | J56: FALSE | K56: FALSE | L56: FALSE
B57: =COUNTIF(F57:L59,TRUE)/COUNTA(F57:L59) -> 0 | C57: Advanced | D57: 3 | E57: Hosting creatives via CM360 for measurement | F57: FALSE | G57: FALSE | H57: FALSE | I57: FALSE | J57: FALSE | K57: FALSE | L57: FALSE | M57: =IFERROR(SWITCH(F57,"fail",0,"pass with recommendations",(#REF!*0.5),"pass",(#REF!*1),"n/a",""),"") | N57: =IFERROR(SWITCH(M57,"fail",0,"pass with recommendations",(#REF!*0.5),"pass",(#REF!*1),"n/a",""),"")
D58: 4 | E58: HTML5 banners running with different elements | F58: FALSE | G58: FALSE | H58: FALSE | I58: FALSE | J58: FALSE | K58: FALSE | L58: FALSE
D59: 5 | E59: Rich media banners (such as HPTO / Mobile Interscroller) | F59: FALSE | G59: FALSE | H59: FALSE | I59: FALSE | J59: FALSE | K59: FALSE | L59: FALSE
B60: =COUNTIF(F60:L61,TRUE)/COUNTA(F60:L61) -> 0 | C60: Expert | D60: 6 | E60: Different creatives per step in the funnel | F60: FALSE | G60: FALSE | H60: FALSE | I60: FALSE | J60: FALSE | K60: FALSE | L60: FALSE | M60: =IFERROR(SWITCH(F60,"fail",0,"pass with recommendations",(#REF!*0.5),"pass",(#REF!*1),"n/a",""),"") | N60: =IFERROR(SWITCH(M60,"fail",0,"pass with recommendations",(#REF!*0.5),"pass",(#REF!*1),"n/a",""),"")
D61: 7 | E61: Creative ad-sequency to boost storytelling | F61: FALSE | G61: FALSE | H61: FALSE | I61: FALSE | J61: FALSE | K61: FALSE | L61: FALSE
B62: =COUNTIF(F62:L62,TRUE)/COUNTA(F62:L62) -> 0 | C62: Champion | D62: 8 | E62: Customized messages per campaign, funnel and vertical (DCO) | F62: FALSE | G62: FALSE | H62: FALSE | I62: FALSE | J62: FALSE | K62: FALSE | L62: FALSE | M62: =IFERROR(SWITCH(F62,"fail",0,"pass with recommendations",(#REF!*0.5),"pass",(#REF!*1),"n/a",""),"") | N62: =IFERROR(SWITCH(M62,"fail",0,"pass with recommendations",(#REF!*0.5),"pass",(#REF!*1),"n/a",""),"")
B63: 6
C64: Reporting | F64: =IFERROR(__xludf.DUMMYFUNCTION("SPARKLINE(COUNTIF(F66:L73,TRUE),{""charttype"",""bar"";""max"",COUNTA(F66:L73);""color1"",""green""})"),"") | N64: =COUNTIF(F66:L73,TRUE)/COUNTA(F66:L73) -> 0
B66: =COUNTIF(F66:L66,TRUE)/COUNTA(F66:L66) -> 0 | C66: Basic | D66: 1 | E66: Manually based media metrics | F66: FALSE | G66: FALSE | H66: FALSE | I66: FALSE | J66: FALSE | K66: FALSE | L66: FALSE | M66: =IFERROR(SWITCH(F66,"fail",0,"pass with recommendations",(#REF!*0.5),"pass",(#REF!*1),"n/a",""),"") | N66: =IFERROR(SWITCH(M66,"fail",0,"pass with recommendations",(#REF!*0.5),"pass",(#REF!*1),"n/a",""),"")
B67: =COUNTIF(F67:L69,TRUE)/COUNTA(F67:L69) -> 0 | C67: Advanced | D67: 2 | E67: Setup brand lift studies | F67: FALSE | G67: FALSE | H67: FALSE | I67: FALSE | J67: FALSE | K67: FALSE | L67: FALSE | M67: =IFERROR(SWITCH(F67,"fail",0,"pass with recommendations",(#REF!*0.5),"pass",(#REF!*1),"n/a",""),"") | N67: =IFERROR(SWITCH(M67,"fail",0,"pass with recommendations",(#REF!*0.5),"pass",(#REF!*1),"n/a",""),"")
D68: 3 | E68: Set-up period manual reports | F68: FALSE | G68: FALSE | H68: FALSE | I68: FALSE | J68: FALSE | K68: FALSE | L68: FALSE
D69: 4 | E69: Irregular testing | F69: FALSE | G69: FALSE | H69: FALSE | I69: FALSE | J69: FALSE | K69: FALSE | L69: FALSE
B70: =COUNTIF(F70:L72,TRUE)/COUNTA(F70:L72) -> 0 | C70: Expert | D70: 5 | E70: Setup accelerated brand lift studies | F70: FALSE | G70: FALSE | H70: FALSE | I70: FALSE | J70: FALSE | K70: FALSE | L70: FALSE | M70: =IFERROR(SWITCH(F70,"fail",0,"pass with recommendations",(#REF!*0.5),"pass",(#REF!*1),"n/a",""),"") | N70: =IFERROR(SWITCH(M70,"fail",0,"pass with recommendations",(#REF!*0.5),"pass",(#REF!*1),"n/a",""),"")
D71: 6 | E71: Automatic in-platform reporting to share with stakeholders | F71: FALSE | G71: FALSE | H71: FALSE | I71: FALSE | J71: FALSE | K71: FALSE | L71: FALSE
D72: 7 | E72: Consistent testing and insights framework | F72: FALSE | G72: FALSE | H72: FALSE | I72: FALSE | J72: FALSE | K72: FALSE | L72: FALSE
B73: =COUNTIF(F73:L73,TRUE)/COUNTA(F73:L73) -> 0 | C73: Champion | D73: 8 | E73: Multiple platform reports to develop one truth about campaign insights | F73: FALSE | G73: FALSE | H73: FALSE | I73: FALSE | J73: FALSE | K73: FALSE | L73: FALSE | M73: =IFERROR(SWITCH(F73,"fail",0,"pass with recommendations",(#REF!*0.5),"pass",(#REF!*1),"n/a",""),"") | N73: =IFERROR(SWITCH(M73,"fail",0,"pass with recommendations",(#REF!*0.5),"pass",(#REF!*1),"n/a",""),"")
B75: SUMMARY (relevance to be adjusted to client needs) | P75: << in the column on the left you can decide if a certain topic is more or less important compared to others - to decide how important it is for the total score of a client Example given: Feed management is not always relevant for a company (B2B). You can give the relevance a score of 0 and it won't be calculated in the total average score Default setting: all topics at 100%
E77: Topic | F77: Topic relevance 0-100% | N77: Total score
C79: 1 | E79: =C11 -> Campaign setup | F79: 1 | M79: =IFERROR(__xludf.DUMMYFUNCTION("F11"),"") | N79: =N11 -> 0
C81: 2 | E81: =C26 -> Targeting | F81: 1 | M81: =IFERROR(__xludf.DUMMYFUNCTION("F26"),"") | N81: =N26 -> 0
C83: 3 | E83: =C36 -> Conversion & KPIs | F83: 1 | M83: =IFERROR(__xludf.DUMMYFUNCTION("F36"),"") | N83: =N36 -> 0
C85: 4 | E85: =C46 -> Attribution model | F85: 1 | M85: =IFERROR(__xludf.DUMMYFUNCTION("F46"),"") | N85: =N46 -> 0
C87: 5 | E87: =C53 -> Creatives | F87: 1 | M87: =IFERROR(__xludf.DUMMYFUNCTION("F53"),"") | N87: =N53 -> 0
C89: 6 | E89: =C64 -> Reporting | F89: 1 | M89: =IFERROR(__xludf.DUMMYFUNCTION("F64"),"") | N89: =N64 -> 0
C91: 7
C93: 8
C95: 9
C97: 10
M99: Total average weighted score | N99: =IFERROR(__xludf.DUMMYFUNCTION("AVERAGE.WEIGHTED(N79:N97,F79:F97)"),0.0) -> 0

Sheet (WIP) LINKEDIN
E2: MUST READ: How to use? 1. Only click a checkbox when the topic on the left - is 100% completed 2. Don't check the box if you "just" checked the topic if it was applicable 3. The same topic can be in multiple stages (different levels of maturity) | F2: FR | G2: NL | H2: DE | I2: BE | J2: UK | K2: US | L2: IT | M2: Adaptation topics (V) | N2: Topics not finalized (X)
F3: TRUE | G3: TRUE | H3: TRUE | I3: TRUE | J3: TRUE | K3: TRUE | L3: TRUE | M3: =(COUNTIF(F:L,TRUE))-COUNTIF(F3:L3,true) -> 0 | N3: =COUNTIF(F:L,FALSE) -> 441
B4: =N119 -> 0 | F4: =COUNTIF(F:F,TRUE)-1 -> 0 | G4: =COUNTIF(G:G,TRUE)-1 -> 0 | H4: =COUNTIF(H:H,TRUE)-1 -> 0 | I4: =COUNTIF(I:I,TRUE)-1 -> 0 | J4: =COUNTIF(J:J,TRUE)-1 -> 0 | K4: =COUNTIF(K:K,TRUE)-1 -> 0 | L4: =COUNTIF(L:L,TRUE)-1 -> 0
F6: =COUNTIF(F:F,FALSE) -> 63 | G6: =COUNTIF(G:G,FALSE) -> 63 | H6: =COUNTIF(H:H,FALSE) -> 63 | I6: =COUNTIF(I:I,FALSE) -> 63 | J6: =COUNTIF(J:J,FALSE) -> 63 | K6: =COUNTIF(K:K,FALSE) -> 63 | L6: =COUNTIF(L:L,FALSE) -> 63
C8: Maturity | D8: # | E8: Topics | F8: FR | G8: NL | H8: DE | I8: BE | J8: UK | K8: US | L8: IT | M8: Details | N8: Comments / Action
E9: If a topic is not relevant for the client - delete the checkbox | F9: Only check a box if the topic is fully integrated | M9: Explain what the issue is if not checked | N9: What would be the next steps to finalize the topic
B10: 1
C11: Account structure | F11: =IFERROR(__xludf.DUMMYFUNCTION("SPARKLINE(COUNTIF(F13:L24,TRUE),{""charttype"",""bar"";""max"",COUNTA(F13:L24);""color1"",""green""})"),"") | N11: =COUNTIF(F13:L24,TRUE)/COUNTA(F13:L24) -> 0
B13: =COUNTIF(F13:L16,TRUE)/COUNTA(F13:L16) -> 0 | C13: Basic | E13: No setup strategy is in place, and campaign are ran a sepertate entities | F13: FALSE | G13: FALSE | H13: FALSE | I13: FALSE | J13: FALSE | K13: FALSE | L13: FALSE | M13: =IFERROR(SWITCH(F13,"fail",0,"pass with recommendations",(#REF!*0.5),"pass",(#REF!*1),"n/a",""),"") | N13: =IFERROR(SWITCH(M13,"fail",0,"pass with recommendations",(#REF!*0.5),"pass",(#REF!*1),"n/a",""),"")
E14: 1 - max 2 ads per campaign | F14: FALSE | G14: FALSE | H14: FALSE | I14: FALSE | J14: FALSE | K14: FALSE | L14: FALSE
E15: Use of a simple UTM strategy (i.e. source and medium) | F15: FALSE | G15: FALSE | H15: FALSE | I15: FALSE | J15: FALSE | K15: FALSE | L15: FALSE | M15: =IFERROR(SWITCH(F15,"fail",0,"pass with recommendations",(#REF!*0.5),"pass",(#REF!*1),"n/a",""),"") | N15: =IFERROR(SWITCH(M15,"fail",0,"pass with recommendations",(#REF!*0.5),"pass",(#REF!*1),"n/a",""),"")
F16: FALSE | G16: FALSE | H16: FALSE | I16: FALSE | J16: FALSE | K16: FALSE | L16: FALSE
B17: =COUNTIF(F17:L18,TRUE)/COUNTA(F17:L18) -> 0 | C17: Advanced | E17: Use of campaign grouping | F17: FALSE | G17: FALSE | H17: FALSE | I17: FALSE | J17: FALSE | K17: FALSE | L17: FALSE | M17: =IFERROR(SWITCH(F17,"fail",0,"pass with recommendations",(#REF!*0.5),"pass",(#REF!*1),"n/a",""),"") | N17: =IFERROR(SWITCH(M17,"fail",0,"pass with recommendations",(#REF!*0.5),"pass",(#REF!*1),"n/a",""),"")
E18: Create a LinkedIn funnel by using an awareness layer and a consideration layer. | F18: FALSE | G18: FALSE | H18: FALSE | I18: FALSE | J18: FALSE | K18: FALSE | L18: FALSE | M18: =IFERROR(SWITCH(F18,"fail",0,"pass with recommendations",(#REF!*0.5),"pass",(#REF!*1),"n/a",""),"") | N18: =IFERROR(SWITCH(M18,"fail",0,"pass with recommendations",(#REF!*0.5),"pass",(#REF!*1),"n/a",""),"")
B19: =COUNTIF(F19:L21,TRUE)/COUNTA(F19:L21) -> 0 | C19: Expert | E19: Use of a clear naming convention aligned with all paid media channels in use | F19: FALSE | G19: FALSE | H19: FALSE | I19: FALSE | J19: FALSE | K19: FALSE | L19: FALSE | M19: =IFERROR(SWITCH(F19,"fail",0,"pass with recommendations",(#REF!*0.5),"pass",(#REF!*1),"n/a",""),"") | N19: =IFERROR(SWITCH(M19,"fail",0,"pass with recommendations",(#REF!*0.5),"pass",(#REF!*1),"n/a",""),"")
E20: Use of a structured UTM planning - with a UTM builder tool | F20: FALSE | G20: FALSE | H20: FALSE | I20: FALSE | J20: FALSE | K20: FALSE | L20: FALSE | M20: =IFERROR(SWITCH(F20,"fail",0,"pass with recommendations",(#REF!*0.5),"pass",(#REF!*1),"n/a",""),"") | N20: =IFERROR(SWITCH(M20,"fail",0,"pass with recommendations",(#REF!*0.5),"pass",(#REF!*1),"n/a",""),"")
F21: FALSE | G21: FALSE | H21: FALSE | I21: FALSE | J21: FALSE | K21: FALSE | L21: FALSE | M21: =IFERROR(SWITCH(F21,"fail",0,"pass with recommendations",(#REF!*0.5),"pass",(#REF!*1),"n/a",""),"") | N21: =IFERROR(SWITCH(M21,"fail",0,"pass with recommendations",(#REF!*0.5),"pass",(#REF!*1),"n/a",""),"")
B22: =COUNTIF(F22:L24,TRUE)/COUNTA(F22:L24) -> 0 | C22: Champion | F22: FALSE | G22: FALSE | H22: FALSE | I22: FALSE | J22: FALSE | K22: FALSE | L22: FALSE | M22: =IFERROR(SWITCH(F22,"fail",0,"pass with recommendations",(#REF!*0.5),"pass",(#REF!*1),"n/a",""),"") | N22: =IFERROR(SWITCH(M22,"fail",0,"pass with recommendations",(#REF!*0.5),"pass",(#REF!*1),"n/a",""),"")
F23: FALSE | G23: FALSE | H23: FALSE | I23: FALSE | J23: FALSE | K23: FALSE | L23: FALSE | M23: =IFERROR(SWITCH(F23,"fail",0,"pass with recommendations",(#REF!*0.5),"pass",(#REF!*1),"n/a",""),"") | N23: =IFERROR(SWITCH(M23,"fail",0,"pass with recommendations",(#REF!*0.5),"pass",(#REF!*1),"n/a",""),"")
F24: FALSE | G24: FALSE | H24: FALSE | I24: FALSE | J24: FALSE | K24: FALSE | L24: FALSE | M24: =IFERROR(SWITCH(F24,"fail",0,"pass with recommendations",(#REF!*0.5),"pass",(#REF!*1),"n/a",""),"") | N24: =IFERROR(SWITCH(M24,"fail",0,"pass with recommendations",(#REF!*0.5),"pass",(#REF!*1),"n/a",""),"")
B25: 2
C26: Budget & Bidding | F26: =IFERROR(__xludf.DUMMYFUNCTION("SPARKLINE(COUNTIF(F28:L37,TRUE),{""charttype"",""bar"";""max"",COUNTA(F28:L37);""color1"",""green""})"),"") | N26: =COUNTIF(F28:L37,TRUE)/COUNTA(F28:L37) -> 0
B28: =COUNTIF(F28:L29,TRUE)/COUNTA(F28:L29) -> 0 | C28: Basic | E28: Daily budget set up | F28: FALSE | G28: FALSE | H28: FALSE | I28: FALSE | J28: FALSE | K28: FALSE | L28: FALSE | M28: =IFERROR(SWITCH(F28,"fail",0,"pass with recommendations",(#REF!*0.5),"pass",(#REF!*1),"n/a",""),"") | N28: =IFERROR(SWITCH(M28,"fail",0,"pass with recommendations",(#REF!*0.5),"pass",(#REF!*1),"n/a",""),"")
E29: Manual bidding or cost cap set ul | F29: FALSE | G29: FALSE | H29: FALSE | I29: FALSE | J29: FALSE | K29: FALSE | L29: FALSE
B30: =COUNTIF(F30:L32,TRUE)/COUNTA(F30:L32) -> 0 | C30: Advanced | E30: Lifetime budget per campaign (instead of daily budget) | F30: FALSE | G30: FALSE | H30: FALSE | I30: FALSE | J30: FALSE | K30: FALSE | L30: FALSE | M30: =IFERROR(SWITCH(F30,"fail",0,"pass with recommendations",(#REF!*0.5),"pass",(#REF!*1),"n/a",""),"") | N30: =IFERROR(SWITCH(M30,"fail",0,"pass with recommendations",(#REF!*0.5),"pass",(#REF!*1),"n/a",""),"")
E31: Maximum delivery as bidding strategy | F31: FALSE | G31: FALSE | H31: FALSE | I31: FALSE | J31: FALSE | K31: FALSE | L31: FALSE
F32: FALSE | G32: FALSE | H32: FALSE | I32: FALSE | J32: FALSE | K32: FALSE | L32: FALSE | M32: =IFERROR(SWITCH(F32,"fail",0,"pass with recommendations",(#REF!*0.5),"pass",(#REF!*1),"n/a",""),"") | N32: =IFERROR(SWITCH(M32,"fail",0,"pass with recommendations",(#REF!*0.5),"pass",(#REF!*1),"n/a",""),"")
B33: =COUNTIF(F33:L34,TRUE)/COUNTA(F33:L34) -> 0 | C33: Expert | F33: FALSE | G33: FALSE | H33: FALSE | I33: FALSE | J33: FALSE | K33: FALSE | L33: FALSE | M33: =IFERROR(SWITCH(F33,"fail",0,"pass with recommendations",(#REF!*0.5),"pass",(#REF!*1),"n/a",""),"") | N33: =IFERROR(SWITCH(M33,"fail",0,"pass with recommendations",(#REF!*0.5),"pass",(#REF!*1),"n/a",""),"")
E34: Shared budget between funnel steps | F34: FALSE | G34: FALSE | H34: FALSE | I34: FALSE | J34: FALSE | K34: FALSE | L34: FALSE
B35: =COUNTIF(F35:L37,TRUE)/COUNTA(F35:L37) -> 0 | C35: Champion | E35: Cross channel budgets (media) | F35: FALSE | G35: FALSE | H35: FALSE | I35: FALSE | J35: FALSE | K35: FALSE | L35: FALSE | M35: =IFERROR(SWITCH(F35,"fail",0,"pass with recommendations",(#REF!*0.5),"pass",(#REF!*1),"n/a",""),"") | N35: =IFERROR(SWITCH(M35,"fail",0,"pass with recommendations",(#REF!*0.5),"pass",(#REF!*1),"n/a",""),"")
F36: FALSE | G36: FALSE | H36: FALSE | I36: FALSE | J36: FALSE | K36: FALSE | L36: FALSE | M36: =IFERROR(SWITCH(F36,"fail",0,"pass with recommendations",(#REF!*0.5),"pass",(#REF!*1),"n/a",""),"") | N36: =IFERROR(SWITCH(M36,"fail",0,"pass with recommendations",(#REF!*0.5),"pass",(#REF!*1),"n/a",""),"")
F37: FALSE | G37: FALSE | H37: FALSE | I37: FALSE | J37: FALSE | K37: FALSE | L37: FALSE | M37: =IFERROR(SWITCH(F37,"fail",0,"pass with recommendations",(#REF!*0.5),"pass",(#REF!*1),"n/a",""),"") | N37: =IFERROR(SWITCH(M37,"fail",0,"pass with recommendations",(#REF!*0.5),"pass",(#REF!*1),"n/a",""),"")
B38: 3
C39: Conversion & KPI | F39: =IFERROR(__xludf.DUMMYFUNCTION("SPARKLINE(COUNTIF(F41:L51,TRUE),{""charttype"",""bar"";""max"",COUNTA(F41:L51);""color1"",""green""})"),"") | N39: =COUNTIF(F41:L51,TRUE)/COUNTA(F41:L51) -> 0
B41: =COUNTIF(F41:L43,TRUE)/COUNTA(F41:L43) -> 0 | C41: Basic | E41: Insight Tag set up | F41: FALSE | G41: FALSE | H41: FALSE | I41: FALSE | J41: FALSE | K41: FALSE | L41: FALSE | M41: =IFERROR(SWITCH(F41,"fail",0,"pass with recommendations",(#REF!*0.5),"pass",(#REF!*1),"n/a",""),"") | N41: =IFERROR(SWITCH(M41,"fail",0,"pass with recommendations",(#REF!*0.5),"pass",(#REF!*1),"n/a",""),"")
E42: Online Conversions tracking (macro - only main action tracked) | F42: FALSE | G42: FALSE | H42: FALSE | I42: FALSE | J42: FALSE | K42: FALSE | L42: FALSE | M42: =IFERROR(SWITCH(F42,"fail",0,"pass with recommendations",(#REF!*0.5),"pass",(#REF!*1),"n/a",""),"") | N42: =IFERROR(SWITCH(M42,"fail",0,"pass with recommendations",(#REF!*0.5),"pass",(#REF!*1),"n/a",""),"")
F43: FALSE | G43: FALSE | H43: FALSE | I43: FALSE | J43: FALSE | K43: FALSE | L43: FALSE | M43: =IFERROR(SWITCH(F43,"fail",0,"pass with recommendations",(#REF!*0.5),"pass",(#REF!*1),"n/a",""),"") | N43: =IFERROR(SWITCH(M43,"fail",0,"pass with recommendations",(#REF!*0.5),"pass",(#REF!*1),"n/a",""),"")
B44: =COUNTIF(F44:L46,TRUE)/COUNTA(F44:L46) -> 0 | C44: Advanced | F44: FALSE | G44: FALSE | H44: FALSE | I44: FALSE | J44: FALSE | K44: FALSE | L44: FALSE | M44: =IFERROR(SWITCH(F44,"fail",0,"pass with recommendations",(#REF!*0.5),"pass",(#REF!*1),"n/a",""),"") | N44: =IFERROR(SWITCH(M44,"fail",0,"pass with recommendations",(#REF!*0.5),"pass",(#REF!*1),"n/a",""),"")
E45: Online Conversions tracking (micro/soft conversions) - i.e. quality visit | F45: FALSE | G45: FALSE | H45: FALSE | I45: FALSE | J45: FALSE | K45: FALSE | L45: FALSE | M45: =IFERROR(SWITCH(F45,"fail",0,"pass with recommendations",(#REF!*0.5),"pass",(#REF!*1),"n/a",""),"") | N45: =IFERROR(SWITCH(M45,"fail",0,"pass with recommendations",(#REF!*0.5),"pass",(#REF!*1),"n/a",""),"")
F46: FALSE | G46: FALSE | H46: FALSE | I46: FALSE | J46: FALSE | K46: FALSE | L46: FALSE
B47: =COUNTIF(F47:L49,TRUE)/COUNTA(F47:L49) -> 0 | C47: Expert | E47: Have different campaign goals per different stages of the funnel. | F47: FALSE | G47: FALSE | H47: FALSE | I47: FALSE | J47: FALSE | K47: FALSE | L47: FALSE | M47: =IFERROR(SWITCH(F47,"fail",0,"pass with recommendations",(#REF!*0.5),"pass",(#REF!*1),"n/a",""),"") | N47: =IFERROR(SWITCH(M47,"fail",0,"pass with recommendations",(#REF!*0.5),"pass",(#REF!*1),"n/a",""),"")
E48: A clear KPI framework with goals per funnel | F48: FALSE | G48: FALSE | H48: FALSE | I48: FALSE | J48: FALSE | K48: FALSE | L48: FALSE | M48: =IFERROR(SWITCH(F48,"fail",0,"pass with recommendations",(#REF!*0.5),"pass",(#REF!*1),"n/a",""),"") | N48: =IFERROR(SWITCH(M48,"fail",0,"pass with recommendations",(#REF!*0.5),"pass",(#REF!*1),"n/a",""),"")
F49: FALSE | G49: FALSE | H49: FALSE | I49: FALSE | J49: FALSE | K49: FALSE | L49: FALSE
B50: =COUNTIF(F50:L51,TRUE)/COUNTA(F50:L51) -> 0 | C50: Champion | E50: Offline Conversions API set up | F50: FALSE | G50: FALSE | H50: FALSE | I50: FALSE | J50: FALSE | K50: FALSE | L50: FALSE | M50: =IFERROR(SWITCH(F50,"fail",0,"pass with recommendations",(#REF!*0.5),"pass",(#REF!*1),"n/a",""),"") | N50: =IFERROR(SWITCH(M50,"fail",0,"pass with recommendations",(#REF!*0.5),"pass",(#REF!*1),"n/a",""),"")
E51: Use of dynamic UTMs for Revenue Tracking | F51: FALSE | G51: FALSE | H51: FALSE | I51: FALSE | J51: FALSE | K51: FALSE | L51: FALSE | M51: =IFERROR(SWITCH(F51,"fail",0,"pass with recommendations",(#REF!*0.5),"pass",(#REF!*1),"n/a",""),"") | N51: =IFERROR(SWITCH(M51,"fail",0,"pass with recommendations",(#REF!*0.5),"pass",(#REF!*1),"n/a",""),"")
B52: 4
C53: Audiences | F53: =IFERROR(__xludf.DUMMYFUNCTION("SPARKLINE(COUNTIF(F55:L61,TRUE),{""charttype"",""bar"";""max"",COUNTA(F55:L61);""color1"",""green""})"),"") | N53: =COUNTIF(F55:L61,TRUE)/COUNTA(F55:L61) -> 0
